Workbook

Sheet OBRA 251
B1: BELA NOVA CONSTRUTORA LTDA
B3: DEMONSTRAÇÃO DO RESULTADO APURADO
B5: OBRA 251 - ESTHER TOWERS - EZTEC
B7: OBRA EM ANDAMENTO
B9: Março a Dez/23 | C9: Jan a Dez/24 | D9: Jan a Dez/2025 | E9: Janeiro/2026 | F9: Fevereiro/2026 | G9: Março/2026 | H9: Abril/2026 | I9: Maio/2026 | J9: Junho/2026 | K9: Julho/2026 | L9: Agosto/2026 | M9: Setembro/2026 | N9: Outubro/2026 | O9: Novembro/2026 | P9: Dezembro/2026 | Q9: Acumulado | R9: % S/FAT | X9: 2025
A10: Receitas Brutas
A11: Servicos prestados | B11: 0 | C11: =SUM(E11:P11) -> 0 | D11: =SUM(F11:Q11) -> 0 | E11: 0 | F11: 0 | G11: 0 | H11: 0 | I11: 0 | J11: 0 | K11: 0 | L11: 0 | M11: 0 | N11: 0 | O11: 0 | P11: 0 | Q11: =B11+C11+E11+F11+G11+H11+I11+J11+K11+L11+M11+N11+O11+P11 -> 0 | R11: 1 | T11: =SUM(B11,C11,E11) -> 0 | V11: =T11-Q11 -> 0
A12: Locação de Equipamentos - 450 | B12: 0 | C12: =SUM(E12:P12) -> 0 | D12: =SUM(F12:Q12) -> 0 | E12: 0 | F12: 0 | G12: 0 | H12: 0 | I12: 0 | J12: 0 | K12: 0 | L12: 0 | M12: 0 | N12: 0 | O12: 0 | P12: 0 | Q12: =B12+C12+E12+F12+G12+H12+I12+J12+K12+L12+M12+N12+O12+P12 -> 0 | T12: =SUM(B12,C12,E12) -> 0 | V12: =T12-Q12 -> 0
A13: Receitas Brutas Total... | B13: =SUM(B11:B12) -> 0 | C13: =SUM(C11:C12) -> 0 | D13: =SUM(D11:D12) -> 0 | E13: =SUM(E11:E12) -> 0 | F13: =SUM(F11:F12) -> 0 | G13: =SUM(G11:G12) -> 0 | H13: =SUM(H11:H12) -> 0 | I13: =SUM(I11:I12) -> 0 | ... Q13: =SUM(Q11:Q12) -> 0 | R13: 1 | T13: =SUM(B13,C13,E13) -> 0 | V13: =T13-Q13 -> 0
T14: =SUM(B14,C14,E14) -> 0
A15: Custos | T15: =SUM(B15,C15,E15) -> 0
A16: Alimentação - 320 | B16: -10118.69 | C16: -2203.29 | D16: -46770.85 | E16: -6536.59 | F16: -5430.1 | G16: -5318.8 | H16: -4979.32 | I16: -5067.64 | J16: -3536.82 | K16: 0 | L16: 0 | M16: 0 | N16: 0 | O16: 0 | P16: 0 | Q16: =SUM(B16:P16) -> -89962.1 | T16: =SUM(B16:P16) -> -89962.1 | V16: =Q16-T16 -> 0 | X16: =Q16-C16-B16 -> -77640.12
A17: Combustíveis - 322 | B17: 0 | C17: =SUM(E17:P17) -> 0 | D17: 0 | E17: 0 | F17: 0 | G17: 0 | H17: 0 | I17: 0 | J17: 0 | K17: 0 | L17: 0 | M17: 0 | N17: 0 | O17: 0 | P17: 0 | Q17: =SUM(B17:P17) -> 0 | T17: =SUM(B17:P17) -> 0 | V17: =Q17-T17 -> 0 | X17: =Q17-C17-B17 -> 0
A18: Despesa com Radio e Telefonia Celular | B18: 0 | C18: =SUM(E18:P18) -> 0 | D18: 0 | E18: 0 | F18: 0 | G18: 0 | H18: 0 | I18: 0 | J18: 0 | K18: 0 | L18: 0 | M18: 0 | N18: 0 | O18: 0 | P18: 0 | Q18: =SUM(B18:P18) -> 0 | T18: =SUM(B18:P18) -> 0 | V18: =Q18-T18 -> 0 | X18: =Q18-C18-B18 -> 0
A19: Equipamento de Segurança - EPIs - 360 | B19: 0 | C19: -143.14 | D19: -41.1 | E19: 0 | F19: 0 | G19: 0 | H19: 0 | I19: 0 | J19: 0 | K19: 0 | L19: 0 | M19: 0 | N19: 0 | O19: 0 | P19: 0 | Q19: =SUM(B19:P19) -> -184.24 | T19: =SUM(B19:P19) -> -184.24 | V19: =Q19-T19 -> 0 | X19: =Q19-C19-B19 -> -41.1
A20: Ferias - 315 | B20: -7450.73 | C20: -8327.38 | D20: -37246.46 | E20: -4224.71 | F20: -3562.89 | G20: =-3562.89 -> -3562.89 | H20: -3339.96 | I20: -2266.7 | J20: -2930.17 | K20: 0 | L20: 0 | M20: 0 | N20: 0 | O20: 0 | P20: 0 | Q20: =SUM(B20:P20) -> -72911.89 | T20: =SUM(B20:P20) -> -72911.89 | V20: =Q20-T20 -> 0 | X20: =Q20-C20-B20 -> -57133.78
A21: FGTS - 317 | B21: -5450.68 | C21: -5940.21 | D21: -27685.78 | E21: -2539.14 | F21: -5335.84 | G21: =-2451.92-942.17 -> -3394.09 | H21: -2312.26 | I21: -1513.16 | J21: -1819.93 | K21: 0 | L21: 0 | M21: 0 | N21: 0 | O21: 0 | P21: 0 | Q21: =SUM(B21:P21) -> -55991.09 | T21: =SUM(B21:P21) -> -55991.09 | V21: =Q21-T21 -> 0 | X21: =Q21-C21-B21 -> -44600.2
A22: Horas Extras - 499 | B22: -10981.63 | C22: -9195.55 | D22: -26232.96 | E22: -2167.45 | F22: -3557.58 | G22: -2952.16 | H22: -1732.73 | I22: -760.59 | J22: -1288.42 | K22: 0 | L22: 0 | M22: 0 | N22: 0 | O22: 0 | P22: 0 | Q22: =SUM(B22:P22) -> -58869.07 | T22: =SUM(B22:P22) -> -58869.07 | V22: =Q22-T22 -> 0 | X22: =Q22-C22-B22 -> -38691.89
A23: Indenizações e Aviso Prévio - 318 | B23: 0 | C23: -929.69 | D23: -218.99 | E23: 0 | F23: 0 | G23: 0 | H23: 0 | I23: 0 | J23: 0 | K23: 0 | L23: 0 | M23: 0 | N23: 0 | O23: 0 | P23: 0 | Q23: =SUM(B23:P23) -> -1148.68 | T23: =SUM(B23:P23) -> -1148.68 | V23: =Q23-T23 -> 0 | X23: =Q23-C23-B23 -> -218.99
A24: Indenizações Trabalhistas Judiciais - 369 | B24: 0 | C24: =SUM(E24:P24) -> 0 | D24: 0 | E24: 0 | F24: 0 | G24: 0 | H24: 0 | I24: 0 | J24: 0 | K24: 0 | L24: 0 | M24: 0 | N24: 0 | O24: 0 | P24: 0 | Q24: =SUM(B24:P24) -> 0 | T24: =SUM(B24:P24) -> 0 | V24: =Q24-T24 -> 0 | X24: =Q24-C24-B24 -> 0
A25: INSS - 316 | B25: -6087.45 | C25: -6549.45 | D25: -44939.97 | E25: -5629.42 | F25: -5841.54 | G25: -5615.48 | H25: -5363.61 | I25: -3724 | J25: -4381.26 | K25: 0 | L25: 0 | M25: 0 | N25: 0 | O25: 0 | P25: 0 | Q25: =SUM(B25:P25) -> -88132.18 | T25: =SUM(B25:P25) -> -88132.18 | V25: =Q25-T25 -> 0 | X25: =Q25-C25-B25 -> -75495.28
A26: Locação de Andaimes - 328 | B26: 0 | C26: =SUM(E26:P26) -> 0 | D26: 0 | E26: 0 | F26: 0 | G26: 0 | H26: 0 | I26: 0 | J26: 0 | K26: 0 | L26: 0 | M26: 0 | N26: 0 | O26: 0 | P26: 0 | Q26: =SUM(B26:P26) -> 0 | T26: =SUM(B26:P26) -> 0 | V26: =Q26-T26 -> 0 | X26: =Q26-C26-B26 -> 0
A27: Locação de Máqs, Ferramentas e Equipamentos - | B27: 0 | C27: =SUM(E27:P27) -> 0 | D27: 0 | E27: 0 | F27: 0 | G27: 0 | H27: 0 | I27: 0 | J27: 0 | K27: 0 | L27: 0 | M27: 0 | N27: 0 | O27: 0 | P27: 0 | Q27: =SUM(B27:P27) -> 0 | T27: =SUM(B27:P27) -> 0 | V27: =Q27-T27 -> 0 | X27: =Q27-C27-B27 -> 0
A28: Manutenção de Equipamento - 394 | B28: 0 | C28: =SUM(E28:P28) -> 0 | D28: 0 | E28: 0 | F28: 0 | G28: 0 | H28: 0 | I28: 0 | J28: 0 | K28: 0 | L28: 0 | M28: 0 | N28: 0 | O28: 0 | P28: 0 | Q28: =SUM(B28:P28) -> 0 | T28: =SUM(B28:P28) -> 0 | V28: =Q28-T28 -> 0 | X28: =Q28-C28-B28 -> 0
A29: Manutenção de Veículos - 510 | B29: 0 | C29: =SUM(E29:P29) -> 0 | D29: 0 | E29: 0 | F29: 0 | G29: 0 | H29: 0 | I29: 0 | J29: 0 | K29: 0 | L29: 0 | M29: 0 | N29: 0 | O29: 0 | P29: 0 | Q29: =SUM(B29:P29) -> 0 | T29: =SUM(B29:P29) -> 0 | V29: =Q29-T29 -> 0 | X29: =Q29-C29-B29 -> 0
A30: Medicina Ocupacional e Assist médica - 3 | B30: -1129.53 | C30: -945 | D30: -2655 | E30: -540 | F30: -540 | G30: 0 | H30: 0 | I30: -405 | J30: -270 | K30: 0 | L30: 0 | M30: 0 | N30: 0 | O30: 0 | P30: 0 | Q30: =SUM(B30:P30) -> -6484.53 | T30: =SUM(B30:P30) -> -6484.53 | V30: =Q30-T30 -> 0 | X30: =Q30-C30-B30 -> -4410
A31: Móveis Não Imobilizado - 364 | B31: 0 | C31: =SUM(E31:P31) -> 0 | D31: 0 | E31: 0 | F31: 0 | G31: 0 | H31: 0 | I31: 0 | J31: 0 | K31: 0 | L31: 0 | M31: 0 | N31: 0 | O31: 0 | P31: 0 | Q31: =SUM(B31:P31) -> 0 | T31: =SUM(B31:P31) -> 0 | V31: =Q31-T31 -> 0 | X31: =Q31-C31-B31 -> 0
A32: Peças, Ferramentas e Acessórios - 361 | B32: -82.98 | C32: -52.47 | D32: -52.47 | E32: 0 | F32: 0 | G32: 0 | H32: 0 | I32: 0 | J32: 0 | K32: 0 | L32: 0 | M32: 0 | N32: 0 | O32: 0 | P32: 0 | Q32: =SUM(B32:P32) -> -187.92 | T32: =SUM(B32:P32) -> -187.92 | V32: =Q32-T32 -> 0 | X32: =Q32-C32-B32 -> -52.47
A33: Premios e Gratificacoes - 313 | B33: -13328 | C33: -13234 | D33: -280065.19 | E33: -27000.14 | F33: -29351 | G33: -38254 | H33: -23599 | I33: -14288 | J33: -16583 | K33: 0 | L33: 0 | M33: 0 | N33: 0 | O33: 0 | P33: 0 | Q33: =SUM(B33:P33) -> -455702.33 | T33: =SUM(B33:P33) -> -455702.33 | V33: =Q33-T33 -> 0 | X33: =Q33-C33-B33 -> -429140.33
A34: Salarios e Ordenados - 311 | B34: -57521.82 | C34: -58824.79 | D34: -262861.95 | E34: -29573.7 | F34: -27159.75 | G34: -24143.11 | H34: -27388.23 | I34: -18754.42 | J34: -22058.21 | K34: 0 | L34: 0 | M34: 0 | N34: 0 | O34: 0 | P34: 0 | Q34: =SUM(B34:P34) -> -528285.98 | T34: =SUM(B34:P34) -> -528285.98 | V34: =Q34-T34 -> 0 | X34: =Q34-C34-B34 -> -411939.37
A35: Serviços de Terceiros - 324 | B35: 0 | C35: -405 | D35: -405 | E35: 0 | F35: 0 | G35: 0 | H35: 0 | I35: 0 | J35: 0 | K35: 0 | L35: 0 | M35: 0 | N35: 0 | O35: 0 | P35: 0 | Q35: =SUM(B35:P35) -> -810 | T35: =SUM(B35:P35) -> -810 | V35: =Q35-T35 -> 0 | X35: =Q35-C35-B35 -> -405
A36: Seguro Riscos Execução de Serv. Trab. | B36: 0 | C36: =SUM(E36:P36) -> 0 | D36: 0 | E36: 0 | F36: 0 | G36: 0 | H36: 0 | I36: 0 | J36: 0 | K36: 0 | L36: 0 | M36: 0 | N36: 0 | O36: 0 | P36: 0 | Q36: =SUM(B36:P36) -> 0 | T36: =SUM(B36:P36) -> 0 | V36: =Q36-T36 -> 0 | X36: =Q36-C36-B36 -> 0
A37: Uniformes - 425 | B37: -639.86 | C37: -1211.38 | D37: -2528.41 | E37: 0 | F37: -20.06 | G37: 0 | H37: -153.65 | I37: 0 | J37: 0 | K37: 0 | L37: 0 | M37: 0 | N37: 0 | O37: 0 | P37: 0 | Q37: =SUM(B37:P37) -> -4553.36 | T37: =SUM(B37:P37) -> -4553.36 | V37: =Q37-T37 -> 0 | X37: =Q37-C37-B37 -> -2702.12
A38: Vale Transporte e Condução - 321 | B38: -6096.88 | C38: -7130 | D38: -22363.09 | E38: -2934.44 | F38: -2679.63 | G38: -3062.45 | H38: -2516.68 | I38: -3016.06 | J38: -1228.06 | K38: 0 | L38: 0 | M38: 0 | N38: 0 | O38: 0 | P38: 0 | Q38: =SUM(B38:P38) -> -51027.29 | T38: =SUM(B38:P38) -> -51027.29 | V38: =Q38-T38 -> 0 | X38: =Q38-C38-B38 -> -37800.41
A39: Provisão 13º Salario - 314 | B39: -5681.26 | C39: -6444.74 | D39: -26689.52 | E39: -3168.53 | F39: -2672.17 | G39: -2672.17 | H39: -2718.45 | I39: -1924.49 | J39: -2197.62 | K39: 0 | L39: 0 | M39: 0 | N39: 0 | O39: 0 | P39: 0 | Q39: =SUM(B39:P39) -> -54168.95 | T39: =SUM(B39:P39) -> -54168.95 | V39: =Q39-T39 -> 0 | X39: =Q39-C39-B39 -> -42042.95
A40: Cursos e treinamentos - 849 | B40: 0 | C40: =SUM(E40:P40) -> 0 | D40: 0 | E40: 0 | F40: 0 | G40: 0 | H40: 0 | I40: 0 | J40: 0 | K40: 0 | L40: 0 | M40: 0 | N40: 0 | O40: 0 | P40: 0 | Q40: =SUM(B40:P40) -> 0 | T40: =SUM(B40:P40) -> 0 | V40: =Q40-T40 -> 0 | X40: =Q40-C40-B40 -> 0
A41: Confraternização de Funcionários | B41: 0 | C41: =SUM(E41:P41) -> 0 | D41: 0 | E41: 0 | F41: 0 | G41: 0 | H41: 0 | I41: 0 | J41: 0 | K41: 0 | L41: 0 | M41: 0 | N41: 0 | O41: 0 | P41: 0 | Q41: =SUM(B41:P41) -> 0 | T41: =SUM(B41:P41) -> 0 | V41: =Q41-T41 -> 0 | X41: =Q41-C41-B41 -> 0
A42: Custos Total... | B42: =SUM(B16:B41) -> -124569.51 | C42: =SUM(C16:C41) -> -121536.09 | D42: =SUM(D16:D41) -> -780756.74 | E42: =SUM(E16:E41) -> -84314.12 | F42: =SUM(F16:F41) -> -86150.56 | G42: =SUM(G16:G41) -> -88975.15 | H42: =SUM(H16:H41) -> -74103.89 | I42: =SUM(I16:I41) -> -51720.06 | ... Q42: =SUM(Q16:Q41) -> -1468419.6 | T42: =SUM(B42:P42) -> -1468419.6 | V42: =Q42-T42 -> 0 | X42: =Q42-C42-B42 -> -1222314
T43: =SUM(B43:P43) -> 0 | V43: =Q43-T43 -> 0
A44: = Lucro/Prejuízo Bruto | B44: =B13+B42 -> -124569.51 | C44: =C13+C42 -> -121536.09 | D44: =D13+D42 -> -780756.74 | E44: =E13+E42 -> -84314.12 | F44: =F13+F42 -> -86150.56 | G44: =G13+G42 -> -88975.15 | H44: =H13+H42 -> -74103.89 | I44: =I13+I42 -> -51720.06 | ... P44: =P13+P42 -> 0 | Q44: =SUM(B44:P44) -> -1468419.6 | T44: =SUM(B44:P44) -> -1468419.6 | V44: =Q44-T44 -> 0 | X44: =Q44-C44-B44 -> -1222314
T45: =SUM(B45:P45) -> 0 | V45: =Q45-T45 -> 0
A46: (-) Impostos s/ Serviços - (13,15% s/ Faturamento) | B46: =-B11*13.15% -> 0 | C46: =-C11*13.15% -> 0 | D46: =-D11*13.15% -> 0 | E46: =-E11*13.15% -> 0 | F46: =-F11*13.15% -> 0 | G46: =-G11*13.15% -> 0 | H46: =-H11*13.15% -> 0 | I46: =-I11*13.15% -> 0 | ... P46: =-P11*13.15% -> 0 | Q46: =SUM(B46:P46) -> 0 | T46: =SUM(B46:P46) -> 0 | V46: =Q46-T46 -> 0 | X46: =Q46-C46-B46 -> 0
T47: =SUM(B47:P47) -> 0 | V47: =Q47-T47 -> 0
A48: (-) IRPJ e CSLL - (1,22% s/faturamento) | B48: =-B11*1.22% -> 0 | C48: =-C11*1.22% -> 0 | D48: =-D11*1.22% -> 0 | E48: =-E11*1.22% -> 0 | F48: =-F11*1.22% -> 0 | G48: =-G11*1.22% -> 0 | H48: =-H11*1.22% -> 0 | I48: =-I11*1.22% -> 0 | ... P48: =-P11*1.22% -> 0 | Q48: =SUM(B48:P48) -> 0 | T48: =SUM(B48:P48) -> 0 | V48: =Q48-T48 -> 0 | X48: =Q48-C48-B48 -> 0
T49: =SUM(B49:P49) -> 0 | V49: =Q49-T49 -> 0
A50: Total Desp Administrativas/Técnico - ( 5,56% Taxa Adm. Prevista) | B50: =B42*5.56% -> -6926.0648 | C50: =C42*5.56% -> -6757.4066 | D50: =D42*5.56% -> -43410.075 | E50: =E42*5.56% -> -4687.8651 | F50: =F42*5.56% -> -4789.9711 | G50: =G42*5.56% -> -4947.0183 | H50: =H42*5.56% -> -4120.1763 | I50: =I42*5.56% -> -2875.6353 | ... P50: =P42*5.56% -> 0 | Q50: =SUM(B50:P50) -> -81644.13 | T50: =SUM(B50:P50) -> -81644.13 | V50: =Q50-T50 -> 0 | X50: =Q50-C50-B50 -> -67960.659
T51: =SUM(B51:P51) -> 0 | V51: =Q51-T51 -> 0
A52: Total Despesas Financeiras -( 0,01% s/ Custo de Obras-média) | B52: =B42*0.01% -> -12.456951 | C52: =C42*0.01% -> -12.153609 | D52: =D42*0.01% -> -78.075674 | E52: =E42*0.01% -> -8.431412 | F52: =F42*0.01% -> -8.615056 | G52: =G42*0.01% -> -8.897515 | H52: =H42*0.01% -> -7.410389 | I52: =I42*0.01% -> -5.172006 | ... P52: =P42*0.01% -> 0 | Q52: =SUM(B52:P52) -> -146.84196 | T52: =SUM(B52:P52) -> -146.84196 | V52: =Q52-T52 -> 0 | X52: =Q52-C52-B52 -> -122.2314
T53: =SUM(B53:P53) -> 0 | V53: =Q53-T53 -> 0
A54: LUCRO/PREJUIZO - LIQUIDO DA OBRA - 251 - | B54: =B44+B50+B52+B46+B48 -> -131508.03 | C54: =C44+C50+C52+C46+C48 -> -128305.65 | D54: =D44+D50+D52+D46+D48 -> -824244.89 | E54: =E44+E50+E52+E46+E48 -> -89010.416 | F54: =F44+F50+F52+F46+F48 -> -90949.146 | G54: =G44+G50+G52+G46+G48 -> -93931.066 | H54: =H44+H50+H52+H46+H48 -> -78231.477 | I54: =I44+I50+I52+I46+I48 -> -54600.867 | ... P54: =P44+P50+P52+P46+P48 -> 0 | Q54: =SUM(B54:P54) -> -1550210.6 | T54: =SUM(B54:P54) -> -1550210.6 | V54: =Q54-T54 -> 0 | X54: =Q54-C54-B54 -> -1290396.9
A56: NÚMERO DE FUNCIONÁRIOS - FINAL DO MÊS | E56: 13 | F56: 12 | G56: 11 | H56: 11 | I56: 7 | J56: 8
A58: Elaborado: INOV SOLUÇÃO EMPRESARIAL E CONTÁBIL LTDA | Q58: 46203
B60: =B13+B42+B46+B48+B50+B52 -> -131508.03 | C60: =C13+C42+C46+C48+C50+C52 -> -128305.65 | D60: =D13+D42+D46+D48+D50+D52 -> -824244.89 | E60: =E13+E42+E46+E48+E50+E52 -> -89010.416 | F60: =F13+F42+F46+F48+F50+F52 -> -90949.146 | G60: =G13+G42+G46+G48+G50+G52 -> -93931.066 | H60: =H13+H42+H46+H48+H50+H52 -> -78231.477 | I60: =I13+I42+I46+I48+I50+I52 -> -54600.867 | ... Q60: =Q13+Q42+Q46+Q48+Q50+Q52 -> -1550210.6
B62: =B60-B54 -> 0 | C62: =C60-C54 -> 0 | D62: =D60-D54 -> 0 | E62: =E60-E54 -> 0 | F62: =F60-F54 -> 0 | G62: =G60-G54 -> 0 | H62: =H60-H54 -> 0 | I62: =I60-I54 -> 0 | ... Q62: =Q60-Q54 -> 0

Sheet OBRA 259 
A1: DEMONSTRAÇÃO DO RESULTADO APURADO
A3: OBRA 259 - ORION PATRIANI - PATRIANI
A5: OBRA ENCERRADA
B8: BOA NOVA | C8: BELA NOVA
B9: Jan a Fev/2022 | C9: Set a Dez/2021 | D9: Jan a Dez/2022 | E9: Jan a Dez/2023 | F9: Janeiro/2024 | G9: Fevereiro/2024 | H9: Março/2024 | I9: Abril/2024 | J9: Maio/2024 | K9: Junho/2024 | L9: Julho/2024 | M9: Agosto/2024 | N9: Setembro/2024 | O9: Outubro/2024 | P9: Novembro/2024 | Q9: Dezembro/2024 | R9: Acumulado | S9: % S/FAT
A10: Receitas Brutas
A11: Servicos prestados | B11: 0 | C11: 246533.35 | D11: =1431743.02-B11-C11 -> 1185209.7 | E11: =2893772.95-B11-C11-D11 -> 1462029.9 | F11: 0 | G11: 0 | H11: 0 | I11: 0 | J11: 0 | K11: 0 | L11: 0 | M11: 0 | N11: 0 | O11: 0 | P11: 0 | Q11: 0 | R11: =B11+C11+D11+E11+F11+G11+H11+I11+J11+K11+L11+M11+N11+O11+P11+Q11 -> 2893773 | S11: =R11/R13 -> 0.99522701 | U11: =SUM(B11:Q11) -> 2893773 | V11: =U11-R11 -> 0
A12: Locação de Equipamentos - 450 | B12: 0 | C12: 13878.18 | D12: =13878.18-B12-C12 -> 0 | E12: =13878.18-C12 -> 0 | F12: 0 | G12: 0 | H12: 0 | I12: 0 | J12: 0 | K12: 0 | L12: 0 | M12: 0 | N12: 0 | O12: 0 | P12: 0 | Q12: 0 | R12: =B12+C12+D12+E12+F12+G12+H12+I12+J12+K12+L12+M12+N12+O12+P12+Q12 -> 13878.18 | S12: =R12/R13 -> 0.0047729866 | U12: =SUM(B12:Q12) -> 13878.18 | V12: =U12-R12 -> 0
A13: Receitas Brutas Total... | B13: =B11+B12 -> 0 | C13: =C11+C12 -> 260411.53 | D13: =D11+D12 -> 1185209.7 | E13: =E11+E12 -> 1462029.9 | G13: =G11+G12 -> 0 | H13: =H11 -> 0 | I13: =I11 -> 0 | J13: =J11 -> 0 | K13: =K11 -> 0 | L13: =L11 -> 0 | M13: =M11 -> 0 | N13: =N11 -> 0 | O13: =O11 -> 0 | ... Q13: =Q11 -> 0 | R13: =SUM(R11:R12) -> 2907651.1 | S13: =SUM(S11:S12) -> 1 | U13: =SUM(B13:Q13) -> 2907651.1 | V13: =U13-R13 -> 0
U14: =SUM(B14:Q14) -> 0 | V14: =U14-R14 -> 0
A15: Custos | U15: =SUM(B15:Q15) -> 0 | V15: =U15-R15 -> 0
A16: Alimentação - 320 | B16: =15.07-287.72 -> -272.65 | C16: -3147.8 | D16: =-84418.97-B16-C16 -> -80998.52 | E16: =-190214.4-B16-C16-D16 -> -105795.43 | F16: 0 | G16: 0 | H16: 0 | I16: 0 | J16: 0 | K16: 0 | L16: 0 | M16: 0 | N16: 0 | O16: 0 | P16: 0 | Q16: 0 | R16: =B16+C16+D16+E16+F16+G16+H16+I16+J16+K16+L16+M16+N16+O16+P16+Q16 -> -190214.4 | S16: =-R16/$R$13 -> 0.065418577 | U16: =SUM(B16:Q16) -> -190214.4 | V16: =U16-R16 -> 0
A17: Combustíveis - 322 | B17: 0 | C17: 0 | D17: =-4053.88-B17-C17 -> -4053.88 | E17: =-4053.88-B17-C17-D17 -> 0 | F17: 0 | G17: 0 | H17: 0 | I17: 0 | J17: 0 | K17: 0 | L17: 0 | M17: 0 | N17: 0 | O17: 0 | P17: 0 | Q17: 0 | R17: =B17+C17+D17+E17+F17+G17+H17+I17+J17+K17+L17+M17+N17+O17+P17+Q17 -> -4053.88 | S17: =-R17/$R$13 -> 0.0013942113 | U17: =SUM(B17:Q17) -> -4053.88 | V17: =U17-R17 -> 0
A18: Despesa com Radio e Telefonia Celular | B18: 0 | C18: 0 | D18: =-1094-B18-C18 -> -1094 | E18: =-2174-B18-C18-D18 -> -1080 | F18: 0 | G18: 0 | H18: 0 | I18: 0 | J18: 0 | K18: 0 | L18: 0 | M18: 0 | N18: 0 | O18: 0 | P18: 0 | Q18: 0 | R18: =B18+C18+D18+E18+F18+G18+H18+I18+J18+K18+L18+M18+N18+O18+P18+Q18 -> -2174 | S18: =-R18/$R$13 -> 0.00074768255 | U18: =SUM(B18:Q18) -> -2174 | V18: =U18-R18 -> 0
A19: Equipamento de Segurança - EPIs - 360 | B19: 0 | C19: -3467.31 | D19: =-8069.23-B19-C19 -> -4601.92 | E19: =-10788.86-B19-C19-D19 -> -2719.63 | F19: 0 | G19: 0 | H19: 0 | I19: 0 | J19: 0 | K19: 0 | L19: 0 | M19: 0 | N19: 0 | O19: 0 | P19: 0 | Q19: 0 | R19: =B19+C19+D19+E19+F19+G19+H19+I19+J19+K19+L19+M19+N19+O19+P19+Q19 -> -10788.86 | S19: =-R19/$R$13 -> 0.003710507 | U19: =SUM(B19:Q19) -> -10788.86 | V19: =U19-R19 -> 0
A20: Ferias - 315 | B20: =-263.47-696.64 -> -960.11 | C20: -4277.4 | D20: =-54093.61-B20-C20 -> -48856.1 | E20: =-102612.88-B20-C20-D20 -> -48519.27 | F20: 0 | G20: 0 | H20: 0 | I20: 0 | J20: 0 | K20: 0 | L20: 0 | M20: 0 | N20: 0 | O20: 0 | P20: 0 | Q20: 0 | R20: =B20+C20+D20+E20+F20+G20+H20+I20+J20+K20+L20+M20+N20+O20+P20+Q20 -> -102612.88 | S20: =-R20/$R$13 -> 0.035290644 | U20: =SUM(B20:Q20) -> -102612.88 | V20: =U20-R20 -> 0
A21: FGTS - 317 | B21: =-162.42-460.3 -> -622.72 | C21: -1064 | D21: =-29386.17-B21-C21 -> -27699.45 | E21: =-60590.37-B21-C21-D21 -> -31204.2 | F21: 0 | G21: 0 | H21: 0 | I21: 0 | J21: 0 | K21: 0 | L21: 0 | M21: 0 | N21: 0 | O21: 0 | P21: 0 | Q21: 0 | R21: =B21+C21+D21+E21+F21+G21+H21+I21+J21+K21+L21+M21+N21+O21+P21+Q21 -> -60590.37 | S21: =-R21/$R$13 -> 0.020838253 | U21: =SUM(B21:Q21) -> -60590.37 | V21: =U21-R21 -> 0
A22: Horas Extras - 499 | B22: -632.27 | C22: 0 | D22: =-19127.09-B22-C22 -> -18494.82 | E22: =-41851.18-B22-C22-D22 -> -22724.09 | F22: 0 | G22: 0 | H22: 0 | I22: 0 | J22: 0 | K22: 0 | L22: 0 | M22: 0 | N22: 0 | O22: 0 | P22: 0 | Q22: 0 | R22: =B22+C22+D22+E22+F22+G22+H22+I22+J22+K22+L22+M22+N22+O22+P22+Q22 -> -41851.18 | S22: =-R22/$R$13 -> 0.014393467 | U22: =SUM(B22:Q22) -> -41851.18 | V22: =U22-R22 -> 0
A23: Indenizações e Aviso Prévio - 318 | B23: 0 | C23: 0 | D23: =2189.52-B23-C23 -> 2189.52 | E23: =2866.52-B23-C23-D23 -> 677 | F23: 0 | G23: 0 | H23: 0 | I23: 0 | J23: 0 | K23: 0 | L23: 0 | M23: 0 | N23: 0 | O23: 0 | P23: 0 | Q23: 0 | R23: =B23+C23+D23+E23+F23+G23+H23+I23+J23+K23+L23+M23+N23+O23+P23+Q23 -> 2866.52 | S23: =R23/$R$13 -> 0.00098585417 | U23: =SUM(B23:Q23) -> 2866.52 | V23: =U23-R23 -> 0
A24: Indenizações Trabalhistas Judiciais - 369 | B24: 0 | C24: 0 | D24: =0-B24-C24 -> 0 | E24: =0-B24-C24-D24 -> 0 | F24: 0 | G24: 0 | H24: 0 | I24: 0 | J24: 0 | K24: 0 | L24: 0 | M24: 0 | N24: 0 | O24: 0 | P24: 0 | Q24: 0 | R24: =B24+C24+D24+E24+F24+G24+H24+I24+J24+K24+L24+M24+N24+O24+P24+Q24 -> 0 | S24: =R24/$R$13 -> 0 | U24: =SUM(B24:Q24) -> 0 | V24: =U24-R24 -> 0
A25: INSS - 316 | B25: =-176.19-555.14 -> -731.33 | C25: -1730.4 | D25: =-35654.44-B25-C25 -> -33192.71 | E25: =-70619.5-B25-C25-D25 -> -34965.06 | F25: 0 | G25: 0 | H25: 0 | I25: 0 | J25: 0 | K25: 0 | L25: 0 | M25: 0 | N25: 0 | O25: 0 | P25: 0 | Q25: 0 | R25: =B25+C25+D25+E25+F25+G25+H25+I25+J25+K25+L25+M25+N25+O25+P25+Q25 -> -70619.5 | S25: =-R25/$R$13 -> 0.024287474 | U25: =SUM(B25:Q25) -> -70619.5 | V25: =U25-R25 -> 0
A26: Locação de Andaimes - 328 | B26: 0 | C26: 0 | D26: =-2889-B26-C26 -> -2889 | E26: =-7329-B26-C26-D26 -> -4440 | F26: 0 | G26: 0 | H26: 0 | I26: 0 | J26: 0 | K26: 0 | L26: 0 | M26: 0 | N26: 0 | O26: 0 | P26: 0 | Q26: 0 | R26: =B26+C26+D26+E26+F26+G26+H26+I26+J26+K26+L26+M26+N26+O26+P26+Q26 -> -7329 | S26: =-R26/$R$13 -> 0.0025205913 | U26: =SUM(B26:Q26) -> -7329 | V26: =U26-R26 -> 0
A27: Locação de Máqs, Ferramentas e Equipamentos - | B27: 0 | C27: 0 | D27: =-14203.89-B27-C27 -> -14203.89 | E27: =-33430.49-B27-C27-D27 -> -19226.6 | F27: 0 | G27: 0 | H27: 0 | I27: 0 | J27: 0 | K27: 0 | L27: 0 | M27: 0 | N27: 0 | O27: 0 | P27: 0 | Q27: 0 | R27: =B27+C27+D27+E27+F27+G27+H27+I27+J27+K27+L27+M27+N27+O27+P27+Q27 -> -33430.49 | S27: =-R27/$R$13 -> 0.011497421 | U27: =SUM(B27:Q27) -> -33430.49 | V27: =U27-R27 -> 0
A28: Manutenção de Equipamento - 394 | B28: =-42.42-69.23 -> -111.65 | C28: 0 | D28: =-111.65-B28-C28 -> 0 | E28: =-111.65-B28-C28-D28 -> 0 | F28: 0 | G28: 0 | H28: 0 | I28: 0 | J28: 0 | K28: 0 | L28: 0 | M28: 0 | N28: 0 | O28: 0 | P28: 0 | Q28: 0 | R28: =B28+C28+D28+E28+F28+G28+H28+I28+J28+K28+L28+M28+N28+O28+P28+Q28 -> -111.65 | S28: =-R28/$R$13 -> 3.8398692e-05 | U28: =SUM(B28:Q28) -> -111.65 | V28: =U28-R28 -> 0
A29: Manutenção de Veículos - 510 | B29: 0 | C29: 0 | D29: =-220-B29-C29 -> -220 | E29: =-220-B29-C29-D29 -> 0 | F29: 0 | G29: 0 | H29: 0 | I29: 0 | J29: 0 | K29: 0 | L29: 0 | M29: 0 | N29: 0 | O29: 0 | P29: 0 | Q29: 0 | R29: =B29+C29+D29+E29+F29+G29+H29+I29+J29+K29+L29+M29+N29+O29+P29+Q29 -> -220 | S29: =-R29/$R$13 -> 7.5662447e-05 | U29: =SUM(B29:Q29) -> -220 | V29: =U29-R29 -> 0
A30: Medicina Ocupacional e Assist médica - 3 | B30: 0 | C30: 0 | D30: =-4553.96-B30-C30 -> -4553.96 | E30: =-7000.4-B30-C30-D30 -> -2446.44 | F30: 0 | G30: 0 | H30: 0 | I30: 0 | J30: 0 | K30: 0 | L30: 0 | M30: 0 | N30: 0 | O30: 0 | P30: 0 | Q30: 0 | R30: =B30+C30+D30+E30+F30+G30+H30+I30+J30+K30+L30+M30+N30+O30+P30+Q30 -> -7000.4 | S30: =-R30/$R$13 -> 0.0024075791 | U30: =SUM(B30:Q30) -> -7000.4 | V30: =U30-R30 -> 0
A31: Móveis Não Imobilizado - 364 | B31: 0 | C31: 0 | D31: =-1700-B31-C31 -> -1700 | E31: =-1700-B31-C31-D31 -> 0 | F31: 0 | G31: 0 | H31: 0 | I31: 0 | J31: 0 | K31: 0 | L31: 0 | M31: 0 | N31: 0 | O31: 0 | P31: 0 | Q31: 0 | R31: =B31+C31+D31+E31+F31+G31+H31+I31+J31+K31+L31+M31+N31+O31+P31+Q31 -> -1700 | S31: =-R31/$R$13 -> 0.00058466436 | U31: =SUM(B31:Q31) -> -1700 | V31: =U31-R31 -> 0
A32: Peças, Ferramentas e Acessórios - 361 | B32: 0 | C32: -9447.04 | D32: =-31028.35-B32-C32 -> -21581.31 | E32: =-31119.46-B32-C32-D32 -> -91.11 | F32: 0 | G32: 0 | H32: 0 | I32: 0 | J32: 0 | K32: 0 | L32: 0 | M32: 0 | N32: 0 | O32: 0 | P32: 0 | Q32: 0 | R32: =B32+C32+D32+E32+F32+G32+H32+I32+J32+K32+L32+M32+N32+O32+P32+Q32 -> -31119.46 | S32: =-R32/$R$13 -> 0.010702611 | U32: =SUM(B32:Q32) -> -31119.46 | V32: =U32-R32 -> 0
A33: Premios e Gratificacoes - 313 | B33: =-1301-1682 -> -2983 | C33: -1644 | D33: =-164963.45-B33-C33 -> -160336.45 | E33: =-346100.83-B33-C33-D33 -> -181137.38 | F33: 0 | G33: 0 | H33: 0 | I33: 0 | J33: 0 | K33: 0 | L33: 0 | M33: 0 | N33: 0 | O33: 0 | P33: 0 | Q33: 0 | R33: =B33+C33+D33+E33+F33+G33+H33+I33+J33+K33+L33+M33+N33+O33+P33+Q33 -> -346100.83 | S33: =-R33/$R$13 -> 0.11903107 | U33: =SUM(B33:Q33) -> -346100.83 | V33: =U33-R33 -> 0
A34: Salarios e Ordenados - 311 | B34: =-2028.78-5591.34 -> -7620.12 | C34: -13299.43 | D34: =-357928.53-B34-C34 -> -337008.98 | E34: =-706283.73-B34-C34-D34 -> -348355.2 | F34: 0 | G34: 0 | H34: 0 | I34: 0 | J34: 0 | K34: 0 | L34: 0 | M34: 0 | N34: 0 | O34: 0 | P34: 0 | Q34: 0 | R34: =B34+C34+D34+E34+F34+G34+H34+I34+J34+K34+L34+M34+N34+O34+P34+Q34 -> -706283.73 | S34: =-R34/$R$13 -> 0.24290525 | U34: =SUM(B34:Q34) -> -706283.73 | V34: =U34-R34 -> 0
A35: Serviços de Terceiros - 324 | B35: -300 | C35: 0 | D35: =-364.5-B35-C35 -> -64.5 | E35: =-437.3-B35-C35-D35 -> -72.8 | F35: 0 | G35: 0 | H35: 0 | I35: 0 | J35: 0 | K35: 0 | L35: 0 | M35: 0 | N35: 0 | O35: 0 | P35: 0 | Q35: 0 | R35: =B35+C35+D35+E35+F35+G35+H35+I35+J35+K35+L35+M35+N35+O35+P35+Q35 -> -437.3 | S35: =-R35/$R$13 -> 0.00015039631 | U35: =SUM(B35:Q35) -> -437.3 | V35: =U35-R35 -> 0
A36: Seguro Riscos Execução de Serv. Trab. | B36: 0 | C36: 0 | D36: =0-B36-C36 -> 0 | E36: =0-B36-C36-D36 -> 0 | F36: 0 | G36: 0 | H36: 0 | I36: 0 | J36: 0 | K36: 0 | L36: 0 | M36: 0 | N36: 0 | O36: 0 | P36: 0 | Q36: 0 | R36: =B36+C36+D36+E36+F36+G36+H36+I36+J36+K36+L36+M36+N36+O36+P36+Q36 -> 0 | S36: =R36/$R$13 -> 0 | U36: =SUM(B36:Q36) -> 0 | V36: =U36-R36 -> 0
A37: Uniformes - 425 | B37: 0 | C37: -3442 | D37: =-6568.64-B37-C37 -> -3126.64 | E37: =-10452.41-B37-C37-D37 -> -3883.77 | F37: 0 | G37: 0 | H37: 0 | I37: 0 | J37: 0 | K37: 0 | L37: 0 | M37: 0 | N37: 0 | O37: 0 | P37: 0 | Q37: 0 | R37: =B37+C37+D37+E37+F37+G37+H37+I37+J37+K37+L37+M37+N37+O37+P37+Q37 -> -10452.41 | S37: =-R37/$R$13 -> 0.0035947951 | U37: =SUM(B37:Q37) -> -10452.41 | V37: =U37-R37 -> 0
A38: Vale Transporte e Condução - 321 | B38: =121.81+183.78 -> 305.59 | C38: 156.6 | D38: =-28488.44-B38-C38 -> -28950.63 | E38: =-67336.36-B38-C38-D38 -> -38847.92 | F38: 0 | G38: 0 | H38: 0 | I38: 0 | J38: 0 | K38: 0 | L38: 0 | M38: 0 | N38: 0 | O38: 0 | P38: 0 | Q38: 0 | R38: =B38+C38+D38+E38+F38+G38+H38+I38+J38+K38+L38+M38+N38+O38+P38+Q38 -> -67336.36 | S38: =-R38/$R$13 -> 0.023158335 | U38: =SUM(B38:Q38) -> -67336.36 | V38: =U38-R38 -> 0
A39: 13º Salario - 314 | B39: =-197.61-522.48 -> -720.09 | C39: -3174.64 | D39: =-38780.29-B39-C39 -> -34885.56 | E39: =-74177.15-B39-C39-D39 -> -35396.86 | F39: 0 | G39: 0 | H39: 0 | I39: 0 | J39: 0 | K39: 0 | L39: 0 | M39: 0 | N39: 0 | O39: 0 | P39: 0 | Q39: 0 | R39: =B39+C39+D39+E39+F39+G39+H39+I39+J39+K39+L39+M39+N39+O39+P39+Q39 -> -74177.15 | S39: =-R39/$R$13 -> 0.025511021 | U39: =SUM(B39:Q39) -> -74177.15 | V39: =U39-R39 -> 0
A40: Cursos e treinamentos | B40: 0 | C40: 0 | D40: 0 | E40: 0 | F40: 0 | G40: 0 | H40: 0 | I40: 0 | J40: 0 | K40: 0 | L40: 0 | M40: 0 | N40: 0 | O40: 0 | P40: 0 | Q40: 0 | R40: =B40+C40+D40+E40+F40+G40+H40+I40+J40+K40+L40+M40+N40+O40+P40+Q40 -> 0 | S40: =-R40/$R$13 -> 0 | U40: =SUM(B40:Q40) -> 0 | V40: =U40-R40 -> 0
A41: Confraternização de Funcionários | B41: 0 | C41: 0 | D41: 0 | E41: 0 | F41: 0 | G41: 0 | H41: 0 | I41: 0 | J41: 0 | K41: 0 | L41: 0 | M41: 0 | N41: 0 | O41: 0 | P41: 0 | Q41: 0 | R41: =B41+C41+D41+E41+F41+G41+H41+I41+J41+K41+L41+M41+N41+O41+P41+Q41 -> 0 | U41: =SUM(B41:Q41) -> 0 | V41: =U41-R41 -> 0
A42: Custos Total... | B42: =SUM(B16:B41) -> -14648.35 | C42: =SUM(C16:C41) -> -44537.42 | D42: =SUM(D16:D41) -> -826322.8 | E42: =SUM(E16:E41) -> -880228.76 | F42: =SUM(F16:F41) -> 0 | G42: =SUM(G16:G41) -> 0 | H42: =SUM(H16:H41) -> 0 | I42: =SUM(I16:I41) -> 0 | ... R42: =SUM(R16:R41) -> -1765737.3 | S42: =-R42/$R$13 -> 0.60727276 | U42: =SUM(B42:Q42) -> -1765737.3 | V42: =U42-R42 -> 0
U43: =SUM(B43:Q43) -> 0 | V43: =U43-R43 -> 0
A44: = Lucro/Prejuízo Bruto | B44: =B13+B42 -> -14648.35 | C44: =C13+C42 -> 215874.11 | D44: =D13+D42 -> 358886.87 | E44: =E13+E42 -> 581801.17 | F44: =F13+F42 -> 0 | G44: =G13+G42 -> 0 | H44: =H13+H42 -> 0 | I44: =I13+I42 -> 0 | ... Q44: =Q13+Q42 -> 0 | R44: =B44+C44+D44+E44+F44+G44+H44+I44+J44+K44+L44+M44+N44+O44+P44+Q44 -> 1141913.8 | S44: =R44/$R$13 -> 0.39272724 | U44: =SUM(B44:Q44) -> 1141913.8 | V44: =U44-R44 -> 0
U45: =SUM(B45:Q45) -> 0 | V45: =U45-R45 -> 0
A46: (-) Impostos s/ Serviços - (13,15% s/ Faturamento) | B46: =B13*-12.46% -> 0 | C46: =-C13*12.46% -> -32447.277 | D46: =-D13*12.46% -> -147677.12 | E46: =-E13*13.15% -> -192256.94 | F46: =-F13*13.15% -> 0 | G46: =-G13*13.15% -> 0 | H46: =-H13*13.15% -> 0 | I46: =-I13*13.15% -> 0 | J46: =-J13*13.15% -> 0 | K46: =-K13*13.15% -> 0 | L46: =-L13*13.15% -> 0 | ... N46: =-N13*13.15% -> 0 | O46: =-O11*13.15% -> 0 | P46: =-P11*13.15% -> 0 | Q46: =-Q11*13.15% -> 0 | R46: =B46+C46+D46+E46+F46+G46+H46+I46+J46+K46+L46+M46+N46+O46+P46+Q46 -> -372381.34 | S46: =-R46/$R$13 -> 0.12806947 | U46: =SUM(B46:Q46) -> -372381.34 | V46: =U46-R46 -> 0
U47: =SUM(B47:Q47) -> 0 | V47: =U47-R47 -> 0
A48: (-) IRPJ e CSLL - (1,22% s/faturamento) | B48: =-B11*1.22% -> 0 | C48: =-C11*1.22% -> -3007.7069 | D48: =-D11*1.22% -> -14459.558 | E48: =-E11*1.22% -> -17836.765 | F48: =-F11*1.22% -> 0 | G48: =-G11*1.22% -> 0 | H48: =-H11*1.22% -> 0 | I48: =-I11*1.22% -> 0 | ... Q48: =-Q11*1.22% -> 0 | R48: =B48+C48+D48+E48+F48+G48+H48+I48+J48+K48+L48+M48+N48+O48+P48+Q48 -> -35304.03 | S48: =-R48/$R$13 -> 0.01214177 | U48: =SUM(B48:Q48) -> -35304.03 | V48: =U48-R48 -> 0
U49: =SUM(B49:Q49) -> 0 | V49: =U49-R49 -> 0
A50: Total Desp Administrativas/Técnico - ( 5,56% Taxa Adm. Prevista) | B50: =B42*5.56% -> -814.44826 | C50: =C42*5.56% -> -2476.2806 | D50: =D42*5.56% -> -45943.548 | E50: =E42*5.56% -> -48940.719 | F50: =F42*5.56% -> 0 | G50: =G42*5.56% -> 0 | H50: =H42*5.56% -> 0 | I50: =I42*5.56% -> 0 | ... Q50: =Q42*5.56% -> 0 | R50: =B50+C50+D50+E50+F50+G50+H50+I50+J50+K50+L50+M50+N50+O50+P50+Q50 -> -98174.996 | S50: =-R50/$R$13 -> 0.033764366 | U50: =SUM(B50:Q50) -> -98174.996 | V50: =U50-R50 -> 0
U51: =SUM(B51:Q51) -> 0 | V51: =U51-R51 -> 0
A52: Total Despesas Financeiras -( 0,01% s/ Custo de Obras-média) | B52: =B42*2.76% -> -404.29446 | C52: =C42*2.76% -> -1229.2328 | D52: =D42*2.76% -> -22806.509 | E52: =E42*0.01% -> -88.022876 | F52: =F42*0.01% -> 0 | G52: =G42*0.01% -> 0 | H52: =H42*0.01% -> 0 | I52: =I42*0.01% -> 0 | J52: =J42*0.01% -> 0 | K52: =K42*0.01% -> 0 | L52: =L42*0.01% -> 0 | ... Q52: =Q42*0.01% -> 0 | R52: =B52+C52+D52+E52+F52+G52+H52+I52+J52+K52+L52+M52+N52+O52+P52+Q52 -> -24528.059 | S52: =-R52/$R$13 -> 0.0084356955 | U52: =SUM(B52:Q52) -> -24528.059 | V52: =U52-R52 -> 0
U53: =SUM(B53:Q53) -> 0 | V53: =U53-R53 -> 0
A54: LUCRO/PREJUIZO - LIQUIDO DA OBRA - 259 - | B54: =B44+B50+B52+B46+B48 -> -15867.093 | C54: =C44+C50+C52+C46+C48 -> 176713.61 | D54: =D44+D50+D52+D46+D48 -> 128000.13 | E54: =E44+E50+E52+E46+E48 -> 322678.73 | F54: =F44+F50+F52+F46+F48 -> 0 | G54: =G44+G50+G52+G46+G48 -> 0 | H54: =H44+H50+H52+H46+H48 -> 0 | I54: =I44+I50+I52+I46+I48 -> 0 | ... Q54: =Q44+Q50+Q52+Q46+Q48 -> 0 | R54: =B54+C54+D54+E54+F54+G54+H54+I54+J54+K54+L54+M54+N54+O54+P54+Q54 -> 611525.38 | S54: =R54/$R$13 -> 0.21031594 | U54: =SUM(B54:Q54) -> 611525.38 | V54: =U54-R54 -> 0
A57: NÚMERO DE FUNCIONÁRIOS - FINAL DO MÊS
A59: Elaborado: INOV SOLUÇÃO EMPRESARIAL E CONTÁBIL LTDA | S59: 45322
B61: =B13+B42+B46+B48+B50+B52 -> -15867.093 | C61: =C13+C42+C46+C48+C50+C52 -> 176713.61 | D61: =D13+D42+D46+D48+D50+D52 -> 128000.13 | E61: =E13+E42+E46+E48+E50+E52 -> 322678.73 | F61: =F13+F42+F46+F48+F50+F52 -> 0 | G61: =G13+G42+G46+G48+G50+G52 -> 0 | H61: =H13+H42+H46+H48+H50+H52 -> 0 | I61: =I13+I42+I46+I48+I50+I52 -> 0 | ... R61: =R13+R42+R46+R48+R50+R52 -> 611525.38
B64: =B61-B54 -> 0 | C64: =C61-C54 -> 0 | D64: =D61-D54 -> 0 | E64: =E61-E54 -> 0 | F64: =F61-F54 -> 0 | G64: =G61-G54 -> 0 | H64: =H61-H54 -> 0 | I64: =I61-I54 -> 0 | ... R64: =R61-R54 -> 0

Sheet OBRA 265
A1: BELA NOVA CONSTRUTORA LTDA
A3: DEMONSTRAÇÃO DO RESULTADO APURADO
A5: OBRA 265 - EPIC - PATRIANI
A7: OBRA ENCERRADA
B10: Abr a Dez/2022 | C10: Jan a Dez/2023 | D10: Janeiro/2024 | E10: Fevereiro/2024 | F10: Março/2024 | G10: Abril/2024 | H10: Maio/2024 | I10: Junho/2024 | J10: Julho/2024 | K10: Agosto/2024 | L10: Setembro/2024 | M10: Outubro/2024 | N10: Novembro/2024 | O10: Dezembro/2024 | P10: Acumulado | Q10: % S/FAT
A11: Receitas Brutas
A12: Servicos prestados | B12: 1073054.4 | C12: =3039481.55-B12 -> 1966427.2 | D12: 0 | E12: 49000 | F12: 0 | G12: 123252.53 | H12: 0 | I12: 0 | J12: 0 | K12: 0 | L12: 0 | M12: 0 | N12: 0 | O12: 0 | P12: =B12+C12+D12+E12+F12+G12+H12+I12+J12+K12+L12+M12+N12+O12 -> 3211734.1 | Q12: 1 | S12: =SUM(B12:H12) -> 3211734.1 | U12: =S12-P12 -> 0
A13: Locação de Equipamentos - 450 | B13: 0 | C13: 0 | D13: 0 | E13: 0 | F13: 0 | G13: 0 | H13: 0 | I13: 0 | J13: 0 | K13: 0 | L13: 0 | M13: 0 | N13: 0 | O13: 0 | P13: =B13+C13+D13+E13+F13+G13+H13+I13+J13+K13+L13+M13+N13+O13 -> 0 | S13: =SUM(B13:H13) -> 0 | U13: =S13-P13 -> 0
A14: Receitas Brutas Total... | B14: =B12+B13 -> 1073054.4 | C14: =C12+C13 -> 1966427.2 | D14: =D12+D13 -> 0 | E14: =E12+E13 -> 49000 | F14: =F12 -> 0 | G14: =G12 -> 123252.53 | H14: =H12 -> 0 | I14: =I12 -> 0 | J14: =J12 -> 0 | K14: =K12 -> 0 | L14: =L12 -> 0 | M14: =M12 -> 0 | ... O14: =O12 -> 0 | P14: =SUM(P12:P13) -> 3211734.1 | Q14: 1 | S14: =SUM(B14:H14) -> 3211734.1 | U14: =S14-P14 -> 0
S15: =SUM(B15:H15) -> 0 | U15: =S15-P15 -> 0
A16: Custos | S16: =SUM(B16:H16) -> 0 | U16: =S16-P16 -> 0
A17: Alimentação - 320 | B17: -58280.6 | C17: =-163575.93-B17 -> -105295.33 | D17: -2407.65 | E17: 30.14 | F17: 15.07 | G17: 15.07 | H17: 0 | I17: 0 | J17: 0 | K17: 0 | L17: 0 | M17: 0 | N17: 0 | O17: 0 | P17: =B17+C17+D17+E17+F17+G17+H17+I17+J17+K17+L17+M17+N17+O17 -> -165923.3 | Q17: =-P17/$P$14 -> 0.051661593 | S17: =SUM(B17:H17) -> -165923.3 | U17: =S17-P17 -> 0
A18: Combustíveis - 322 | B18: -3576.92 | C18: =-3576.92-B18 -> 0 | D18: 0 | E18: 0 | F18: 0 | G18: 0 | H18: 0 | I18: 0 | J18: 0 | K18: 0 | L18: 0 | M18: 0 | N18: 0 | O18: 0 | P18: =B18+C18+D18+E18+F18+G18+H18+I18+J18+K18+L18+M18+N18+O18 -> -3576.92 | Q18: =-P18/$P$14 -> 0.0011137037 | S18: =SUM(B18:H18) -> -3576.92 | U18: =S18-P18 -> 0
A19: Despesa com Radio e Telefonia Celular | B19: -646 | C19: =-1726-B19 -> -1080 | D19: 0 | E19: 0 | F19: 0 | G19: 0 | H19: 0 | I19: 0 | J19: 0 | K19: 0 | L19: 0 | M19: 0 | N19: 0 | O19: 0 | P19: =B19+C19+D19+E19+F19+G19+H19+I19+J19+K19+L19+M19+N19+O19 -> -1726 | Q19: =-P19/$P$14 -> 0.00053740439 | S19: =SUM(B19:H19) -> -1726 | U19: =S19-P19 -> 0
A20: Equipamento de Segurança - EPIs - 360 | B20: -3261.08 | C20: =-7389.99-B20 -> -4128.91 | D20: 0 | E20: 0 | F20: 0 | G20: 0 | H20: 0 | I20: 0 | J20: 0 | K20: 0 | L20: 0 | M20: 0 | N20: 0 | O20: 0 | P20: =B20+C20+D20+E20+F20+G20+H20+I20+J20+K20+L20+M20+N20+O20 -> -7389.99 | Q20: =-P20/$P$14 -> 0.0023009346 | S20: =SUM(B20:H20) -> -7389.99 | U20: =S20-P20 -> 0
A21: Ferias - 315 | B21: -37222.81 | C21: =-92794.88-B21 -> -55572.07 | D21: -624.25 | E21: -624.25 | F21: -312.12 | G21: 0 | H21: 0 | I21: 0 | J21: 0 | K21: 0 | L21: 0 | M21: 0 | N21: 0 | O21: 0 | P21: =B21+C21+D21+E21+F21+G21+H21+I21+J21+K21+L21+M21+N21+O21 -> -94355.5 | Q21: =-P21/$P$14 -> 0.029378366 | S21: =SUM(B21:H21) -> -94355.5 | U21: =S21-P21 -> 0
A22: FGTS - 317 | B22: -22076.8 | C22: =-58889.42-B22 -> -36812.62 | D22: -384.81 | E22: -384.81 | F22: -192.4 | G22: -192.4 | H22: -256.54 | I22: 0 | J22: 0 | K22: 0 | L22: 0 | M22: 0 | N22: 0 | O22: 0 | P22: =B22+C22+D22+E22+F22+G22+H22+I22+J22+K22+L22+M22+N22+O22 -> -60300.38 | Q22: =-P22/$P$14 -> 0.018775023 | S22: =SUM(B22:H22) -> -60300.38 | U22: =S22-P22 -> 0
A23: Horas Extras - 499 | B23: -15783.83 | C23: =-34957.72-B23 -> -19173.89 | D23: 0 | E23: 0 | F23: 0 | G23: 0 | H23: 0 | I23: 0 | J23: 0 | K23: 0 | L23: 0 | M23: 0 | N23: 0 | O23: 0 | P23: =B23+C23+D23+E23+F23+G23+H23+I23+J23+K23+L23+M23+N23+O23 -> -34957.72 | Q23: =-P23/$P$14 -> 0.010884376 | S23: =SUM(B23:H23) -> -34957.72 | U23: =S23-P23 -> 0
A24: Indenizações e Aviso Prévio - 318 | B24: 1520.02 | C24: =1520.02-B24 -> 0 | D24: 0 | E24: 0 | F24: 0 | G24: 0 | H24: 0 | I24: 0 | J24: 0 | K24: 0 | L24: 0 | M24: 0 | N24: 0 | O24: 0 | P24: =B24+C24+D24+E24+F24+G24+H24+I24+J24+K24+L24+M24+N24+O24 -> 1520.02 | Q24: =P24/$P$14 -> 0.00047327081 | S24: =SUM(B24:H24) -> 1520.02 | U24: =S24-P24 -> 0
A25: Indenizações Trabalhistas Judiciais - 369 | B25: 0 | C25: =0-B25 -> 0 | D25: 0 | E25: 0 | F25: 0 | G25: 0 | H25: 0 | I25: 0 | J25: 0 | K25: 0 | L25: 0 | M25: 0 | N25: 0 | O25: 0 | P25: =B25+C25+D25+E25+F25+G25+H25+I25+J25+K25+L25+M25+N25+O25 -> 0 | Q25: =P25/$P$14 -> 0 | S25: =SUM(B25:H25) -> 0 | U25: =S25-P25 -> 0
A26: INSS - 316 | B26: -27064.53 | C26: =-68169.57-B26 -> -41105.04 | D26: -423.29 | E26: -423.29 | F26: -211.65 | G26: -211.65 | H26: -282.19 | I26: 0 | J26: 0 | K26: 0 | L26: 0 | M26: 0 | N26: 0 | O26: 0 | P26: =B26+C26+D26+E26+F26+G26+H26+I26+J26+K26+L26+M26+N26+O26 -> -69721.64 | Q26: =-P26/$P$14 -> 0.02170841 | S26: =SUM(B26:H26) -> -69721.64 | U26: =S26-P26 -> 0
A27: Locação de Andaimes - 328 | B27: -2514.39 | C27: =-4779.39-B27 -> -2265 | D27: 0 | E27: 0 | F27: 0 | G27: 0 | H27: 0 | I27: 0 | J27: 0 | K27: 0 | L27: 0 | M27: 0 | N27: 0 | O27: 0 | P27: =B27+C27+D27+E27+F27+G27+H27+I27+J27+K27+L27+M27+N27+O27 -> -4779.39 | Q27: =-P27/$P$14 -> 0.0014881027 | S27: =SUM(B27:H27) -> -4779.39 | U27: =S27-P27 -> 0
A28: Locação de Máqs, Ferramentas e Equipamentos - | B28: -12475.82 | C28: =-40246.35-B28 -> -27770.53 | D28: 0 | E28: 0 | F28: 0 | G28: 0 | H28: 0 | I28: 0 | J28: 0 | K28: 0 | L28: 0 | M28: 0 | N28: 0 | O28: 0 | P28: =B28+C28+D28+E28+F28+G28+H28+I28+J28+K28+L28+M28+N28+O28 -> -40246.35 | Q28: =-P28/$P$14 -> 0.012531034 | S28: =SUM(B28:H28) -> -40246.35 | U28: =S28-P28 -> 0
A29: Manutenção de Equipamento - 394 | B29: 0 | C29: =0-B29 -> 0 | D29: 0 | E29: 0 | F29: 0 | G29: 0 | H29: 0 | I29: 0 | J29: 0 | K29: 0 | L29: 0 | M29: 0 | N29: 0 | O29: 0 | P29: =B29+C29+D29+E29+F29+G29+H29+I29+J29+K29+L29+M29+N29+O29 -> 0 | Q29: =-P29/$P$14 -> 0 | S29: =SUM(B29:H29) -> 0 | U29: =S29-P29 -> 0
A30: Manutenção de Veículos - 510 | B30: -220 | C30: =-220-B30 -> 0 | D30: 0 | E30: 0 | F30: 0 | G30: 0 | H30: 0 | I30: 0 | J30: 0 | K30: 0 | L30: 0 | M30: 0 | N30: 0 | O30: 0 | P30: =B30+C30+D30+E30+F30+G30+H30+I30+J30+K30+L30+M30+N30+O30 -> -220 | Q30: =-P30/$P$14 -> 6.8498822e-05 | S30: =SUM(B30:H30) -> -220 | U30: =S30-P30 -> 0
A31: Medicina Ocupacional e Assist médica - 3 | B31: -2718.34 | C31: =-5129.9-B31 -> -2411.56 | D31: 0 | E31: 0 | F31: 0 | G31: 0 | H31: 0 | I31: 0 | J31: 0 | K31: 0 | L31: 0 | M31: 0 | N31: 0 | O31: 0 | P31: =B31+C31+D31+E31+F31+G31+H31+I31+J31+K31+L31+M31+N31+O31 -> -5129.9 | Q31: =-P31/$P$14 -> 0.0015972368 | S31: =SUM(B31:H31) -> -5129.9 | U31: =S31-P31 -> 0
A32: Móveis Não Imobilizado - 364 | B32: 0 | C32: =0-B32 -> 0 | D32: 0 | E32: 0 | F32: 0 | G32: 0 | H32: 0 | I32: 0 | J32: 0 | K32: 0 | L32: 0 | M32: 0 | N32: 0 | O32: 0 | P32: =B32+C32+D32+E32+F32+G32+H32+I32+J32+K32+L32+M32+N32+O32 -> 0 | Q32: =P32/$P$14 -> 0 | S32: =SUM(B32:H32) -> 0 | U32: =S32-P32 -> 0
A33: Peças, Ferramentas e Acessórios - 361 | B33: -8145.26 | C33: =-8814.71-B33 -> -669.45 | D33: 0 | E33: 0 | F33: 0 | G33: 0 | H33: 0 | I33: 0 | J33: 0 | K33: 0 | L33: 0 | M33: 0 | N33: 0 | O33: 0 | P33: =B33+C33+D33+E33+F33+G33+H33+I33+J33+K33+L33+M33+N33+O33 -> -8814.71 | Q33: =-P33/$P$14 -> 0.0027445329 | S33: =SUM(B33:H33) -> -8814.71 | U33: =S33-P33 -> 0
A34: Premios e Gratificacoes - 313 | B34: -123190.74 | C34: =-301502.74-B34 -> -178312 | D34: -2590 | E34: -2638 | F34: -794 | G34: 0 | H34: 0 | I34: 0 | J34: 0 | K34: 0 | L34: 0 | M34: 0 | N34: 0 | O34: 0 | P34: =B34+C34+D34+E34+F34+G34+H34+I34+J34+K34+L34+M34+N34+O34 -> -307524.74 | Q34: =-P34/$P$14 -> 0.095750374 | S34: =SUM(B34:H34) -> -307524.74 | U34: =S34-P34 -> 0
A35: Salarios e Ordenados - 311 | B35: -270622.64 | C35: =-672681.71-B35 -> -402059.07 | D35: -4808.42 | E35: -4808.42 | F35: -2403.71 | G35: -2404.71 | H35: 0 | I35: 0 | J35: 0 | K35: 0 | L35: 0 | M35: 0 | N35: 0 | O35: 0 | P35: =B35+C35+D35+E35+F35+G35+H35+I35+J35+K35+L35+M35+N35+O35 -> -687106.97 | Q35: =-P35/$P$14 -> 0.21393644 | S35: =SUM(B35:H35) -> -687106.97 | U35: =S35-P35 -> 0
A36: Serviços de Terceiros - 324 | B36: -64.5 | C36: =-137.22-B36 -> -72.72 | D36: 0 | E36: 0 | F36: 0 | G36: 0 | H36: 0 | I36: 0 | J36: 0 | K36: 0 | L36: 0 | M36: 0 | N36: 0 | O36: 0 | P36: =B36+C36+D36+E36+F36+G36+H36+I36+J36+K36+L36+M36+N36+O36 -> -137.22 | Q36: =-P36/$P$14 -> 4.2724583e-05 | S36: =SUM(B36:H36) -> -137.22 | U36: =S36-P36 -> 0
A37: Seguro Riscos Execução de Serv. Trab. | B37: 0 | C37: =0-B37 -> 0 | D37: 0 | E37: 0 | F37: 0 | G37: 0 | H37: 0 | I37: 0 | J37: 0 | K37: 0 | L37: 0 | M37: 0 | N37: 0 | O37: 0 | P37: =B37+C37+D37+E37+F37+G37+H37+I37+J37+K37+L37+M37+N37+O37 -> 0 | Q37: =P37/$P$14 -> 0 | S37: =SUM(B37:H37) -> 0 | U37: =S37-P37 -> 0
A38: Uniformes - 425 | B38: -4838.47 | C38: =-10826.88-B38 -> -5988.41 | D38: 0 | E38: 0 | F38: 0 | G38: 0 | H38: 0 | I38: 0 | J38: 0 | K38: 0 | L38: 0 | M38: 0 | N38: 0 | O38: 0 | P38: =B38+C38+D38+E38+F38+G38+H38+I38+J38+K38+L38+M38+N38+O38 -> -10826.88 | Q38: =-P38/$P$14 -> 0.0033710387 | S38: =SUM(B38:H38) -> -10826.88 | U38: =S38-P38 -> 0
A39: Vale Transporte e Condução - 321 | B39: -22442.06 | C39: =-63211.64-B39 -> -40769.58 | D39: -643.9 | E39: -153 | F39: -258.9 | G39: -64.7 | H39: -199.5 | I39: 0 | J39: 0 | K39: 0 | L39: 0 | M39: 0 | N39: 0 | O39: 0 | P39: =B39+C39+D39+E39+F39+G39+H39+I39+J39+K39+L39+M39+N39+O39 -> -64531.64 | Q39: =-P39/$P$14 -> 0.02009246 | S39: =SUM(B39:H39) -> -64531.64 | U39: =S39-P39 -> 0
A40: 13º Salario - 314 | B40: -25007.33 | C40: =-65983.22-B40 -> -40975.89 | D40: -468.19 | E40: -468.19 | F40: -234.09 | G40: -234.09 | H40: 0 | I40: 0 | J40: 0 | K40: 0 | L40: 0 | M40: 0 | N40: 0 | O40: 0 | P40: =B40+C40+D40+E40+F40+G40+H40+I40+J40+K40+L40+M40+N40+O40 -> -67387.78 | Q40: =-P40/$P$14 -> 0.020981743 | S40: =SUM(B40:H40) -> -67387.78 | U40: =S40-P40 -> 0
A41: Cursos e treinamentos | B41: 0 | C41: =0-B41 -> 0 | D41: 0 | E41: 0 | F41: 0 | G41: 0 | H41: 0 | I41: 0 | J41: 0 | K41: 0 | L41: 0 | M41: 0 | N41: 0 | O41: 0 | P41: =B41+C41+D41+E41+F41+G41+H41+I41+J41+K41+L41+M41+N41+O41 -> 0 | Q41: =-P41/$P$14 -> 0 | S41: =SUM(B41:H41) -> 0 | U41: =S41-P41 -> 0
A42: Confraternização de Funcionários | B42: 0 | C42: 0 | D42: 0 | E42: 0 | F42: 0 | G42: 0 | H42: 0 | I42: 0 | J42: 0 | K42: 0 | L42: 0 | M42: 0 | N42: 0 | O42: 0 | P42: =B42+C42+D42+E42+F42+G42+H42+I42+J42+K42+L42+M42+N42+O42 -> 0 | Q42: =-P42/$P$14 -> 0 | S42: =SUM(B42:H42) -> 0 | U42: =S42-P42 -> 0
A43: Custos Total... | B43: =SUM(B17:B42) -> -638632.1 | C43: =SUM(C17:C42) -> -964462.07 | D43: =SUM(D17:D42) -> -12350.51 | E43: =SUM(E17:E42) -> -9469.82 | F43: =SUM(F17:F42) -> -4391.8 | G43: =SUM(G17:G42) -> -3092.48 | H43: =SUM(H17:H42) -> -738.23 | I43: =SUM(I17:I42) -> 0 | ... P43: =SUM(P17:P42) -> -1633137 | Q43: =-P43/$P$14 -> 0.50849073 | S43: =SUM(B43:H43) -> -1633137 | U43: =S43-P43 -> 0
S44: =SUM(B44:H44) -> 0 | U44: =S44-P44 -> 0
A45: = Lucro/Prejuízo Bruto | B45: =B14+B43 -> 434422.26 | C45: =C14+C43 -> 1001965.1 | D45: =D14+D43 -> -12350.51 | E45: =E14+E43 -> 39530.18 | F45: =F14+F43 -> -4391.8 | G45: =G14+G43 -> 120160.05 | H45: =H14+H43 -> -738.23 | I45: =I14+I43 -> 0 | ... O45: =O14+O43 -> 0 | P45: =B45+C45+D45+E45+F45+G45+H45+I45+J45+K45+L45+M45+N45+O45 -> 1578597.1 | Q45: =P45/$P$14 -> 0.49150927 | S45: =SUM(B45:H45) -> 1578597.1 | U45: =S45-P45 -> 0
S46: =SUM(B46:H46) -> 0 | U46: =S46-P46 -> 0
A47: (-) Impostos s/ Serviços - (13,15% s/ Faturamento) | B47: =-B12*13.15% -> -141106.65 | C47: =-C12*13.15% -> -258585.18 | D47: =-D12*13.15% -> 0 | E47: =-E12*13.15% -> -6443.5 | F47: =-F12*13.15% -> 0 | G47: =-G12*13.15% -> -16207.708 | H47: =-H12*13.15% -> 0 | I47: =-I12*13.15% -> 0 | ... O47: =-O12*13.15% -> 0 | P47: =B47+C47+D47+E47+F47+G47+H47+I47+J47+K47+L47+M47+N47+O47 -> -422343.03 | Q47: =-P47/$P$14 -> 0.1315 | S47: =SUM(B47:H47) -> -422343.03 | U47: =S47-P47 -> 0
S48: =SUM(B48:H48) -> 0 | U48: =S48-P48 -> 0
A49: (-) IRPJ e CSLL - (1,22% s/faturamento) | B49: =-B12*1.22% -> -13091.263 | C49: =-C12*1.22% -> -23990.412 | D49: =-D12*1.22% -> 0 | E49: =-E12*1.22% -> -597.8 | F49: =-F12*1.22% -> 0 | G49: =-G12*1.22% -> -1503.6809 | H49: =-H12*1.22% -> 0 | I49: =-I12*1.22% -> 0 | ... O49: =-O12*1.22% -> 0 | P49: =B49+C49+D49+E49+F49+G49+H49+I49+J49+K49+L49+M49+N49+O49 -> -39183.156 | Q49: =-P49/$P$14 -> 0.0122 | S49: =SUM(B49:H49) -> -39183.156 | U49: =S49-P49 -> 0
S50: =SUM(B50:H50) -> 0 | U50: =S50-P50 -> 0
A51: Total Desp Administrativas/Técnico - ( 5,56% Taxa Adm. Prevista) | B51: =B43*5.56% -> -35507.945 | C51: =C43*5.56% -> -53624.091 | D51: =D43*5.56% -> -686.68836 | E51: =E43*5.56% -> -526.52199 | F51: =F43*5.56% -> -244.18408 | G51: =G43*5.56% -> -171.94189 | H51: =H43*5.56% -> -41.045588 | I51: =I43*5.56% -> 0 | ... O51: =O43*5.56% -> 0 | P51: =B51+C51+D51+E51+F51+G51+H51+I51+J51+K51+L51+M51+N51+O51 -> -90802.418 | Q51: =-P51/$P$14 -> 0.028272085 | S51: =SUM(B51:H51) -> -90802.418 | U51: =S51-P51 -> 0
S52: =SUM(B52:H52) -> 0 | U52: =S52-P52 -> 0
A53: Total Despesas Financeiras -( 0,01% s/ Custo de Obras-média) | B53: -63.86 | C53: =C43*0.01% -> -96.446207 | D53: =D43*0.01% -> -1.235051 | E53: =E43*0.01% -> -0.946982 | F53: =F43*0.01% -> -0.43918 | G53: =G43*0.01% -> -0.309248 | H53: =H43*0.01% -> -0.073823 | I53: =I43*0.01% -> 0 | J53: =J43*0.01% -> 0 | ... O53: =O43*0.01% -> 0 | P53: =B53+C53+D53+E53+F53+G53+H53+I53+J53+K53+L53+M53+N53+O53 -> -163.31049 | Q53: =-P53/$P$14 -> 5.0848074e-05 | S53: =SUM(B53:H53) -> -163.31049 | U53: =S53-P53 -> 0
S54: =SUM(B54:H54) -> 0 | U54: =S54-P54 -> 0
A55: LUCRO/PREJUIZO - LIQUIDO DA OBRA - 265 - | B55: =B45+B51+B53+B47+B49 -> 244652.54 | C55: =C45+C51+C53+C47+C49 -> 665669 | D55: =D45+D51+D53+D47+D49 -> -13038.433 | E55: =E45+E51+E53+E47+E49 -> 31961.411 | F55: =F45+F51+F53+F47+F49 -> -4636.4233 | G55: =G45+G51+G53+G47+G49 -> 102276.41 | H55: =H45+H51+H53+H47+H49 -> -779.34941 | I55: =I45+I51+I53+I47+I49 -> 0 | ... O55: =O45+O51+O53+O47+O49 -> 0 | P55: =B55+C55+D55+E55+F55+G55+H55+I55+J55+K55+L55+M55+N55+O55 -> 1026105.2 | Q55: =P55/$P$14 -> 0.31948634 | S55: =SUM(B55:H55) -> 1026105.2 | U55: =S55-P55 -> 0
A58: NÚMERO DE FUNCIONÁRIOS - FINAL DO MÊS | C58: 0 | D58: 2 | E58: 2 | F58: 1 | G58: 1 | H58: 1
H59: FÉRIAS
A60: Elaborado: INOV SOLUÇÃO EMPRESARIAL E CONTÁBIL LTDA | H60: JOSÉ GUIA DE MENESES | Q60: 45443
B62: =B14+B43+B47+B49+B51+B53 -> 244652.54 | C62: =C14+C43+C47+C49+C51+C53 -> 665669 | D62: =D14+D43+D47+D49+D51+D53 -> -13038.433 | E62: =E14+E43+E47+E49+E51+E53 -> 31961.411 | F62: =F14+F43+F47+F49+F51+F53 -> -4636.4233 | G62: =G14+G43+G47+G49+G51+G53 -> 102276.41 | H62: =H14+H43+H47+H49+H51+H53 -> -779.34941 | I62: =I14+I43+I47+I49+I51+I53 -> 0 | ... P62: =P14+P43+P47+P49+P51+P53 -> 1026105.2
B64: =B55-B62 -> 0 | C64: =C55-C62 -> 0 | D64: =D55-D62 -> 0 | E64: =E55-E62 -> 0 | F64: =F55-F62 -> 0 | G64: =G55-G62 -> 0 | H64: =H55-H62 -> 0 | I64: =I55-I62 -> 0 | ... P64: =P55-P62 -> 0

Sheet OBRA 267
A1: BELA NOVA CONSTRUTORA EIRELI
A4: DEMONSTRAÇÃO DO RESULTADO APURADO
A6: OBRA 267 - SIGNATURE - EZTEC
A8: OBRA ENCERRADA
B10: Out a Dez/2022 | C10: Jan a Dez/2023 | D10: Jan a Dez/2024 | E10: Janeiro/2025 | F10: Fevereiro/2025 | G10: Março/2025 | H10: Abril/2025 | I10: Maio/2025 | J10: Junho/2025 | K10: Julho/2025 | L10: Agosto/2025 | M10: Setembro/2025 | N10: Outubro/2025 | O10: Novembro/2025 | P10: Dezembro/2025 | Q10: Acumulado | R10: % S/FAT
A11: Receitas Brutas
A12: Servicos prestados | B12: 0 | C12: 1032969.5 | D12: 104718.58 | E12: 0 | F12: 0 | G12: 0 | H12: 0 | I12: 0 | J12: 0 | K12: 0 | L12: 0 | M12: 0 | N12: 0 | O12: 0 | P12: 0 | Q12: =B12+C12+D12+E12+F12+G12+H12+I12+J12+K12+L12+M12+N12+O12+P12 -> 1137688.1 | R12: 1 | T12: =SUM(B12:P12) -> 1137688.1 | V12: =T12-Q12 -> 0
A13: Locação de Equipamentos - 450 | B13: 0 | C13: 0 | D13: =SUM(E13:P13) -> 0 | E13: 0 | F13: 0 | G13: 0 | H13: 0 | I13: 0 | J13: 0 | K13: 0 | L13: 0 | M13: 0 | N13: 0 | O13: 0 | P13: 0 | Q13: =B13+C13+D13+E13+F13+G13+H13+I13+J13+K13+L13+M13+N13+O13+P13 -> 0 | T13: =SUM(B13:P13) -> 0 | V13: =T13-Q13 -> 0
A14: Receitas Brutas Total... | B14: =B12+B13 -> 0 | C14: =C12+C13 -> 1032969.5 | D14: =SUM(D12:D13) -> 104718.58 | E14: =E12+E13 -> 0 | F14: =F12+F13 -> 0 | G14: =G12 -> 0 | H14: =H12 -> 0 | I14: =I12 -> 0 | J14: =J12 -> 0 | K14: =K12 -> 0 | L14: =L12 -> 0 | M14: =M12 -> 0 | N14: =N12 -> 0 | ... P14: =P12 -> 0 | Q14: =SUM(Q12:Q13) -> 1137688.1 | R14: 1 | T14: =SUM(B14:P14) -> 1137688.1 | V14: =T14-Q14 -> 0
T15: =SUM(B15:P15) -> 0
A16: Custos | T16: =SUM(B16:P16) -> 0
A17: Alimentação - 320 | B17: -6869.47 | C17: =-79288.13-B17 -> -72418.66 | D17: -24315.58 | E17: 0 | F17: 0 | G17: 0 | H17: 0 | I17: 0 | J17: 0 | K17: 0 | L17: 0 | M17: 0 | N17: 0 | O17: 0 | P17: 0 | Q17: =B17+C17+D17+E17+F17+G17+H17+I17+J17+K17+L17+M17+N17+O17+P17 -> -103603.71 | R17: =-Q17/$Q$14 -> 0.091065129 | T17: =SUM(B17:P17) -> -103603.71 | V17: =T17-Q17 -> 0
A18: Combustíveis - 322 | B18: -176.92 | C18: =-176.92-B18 -> 0 | D18: 0 | E18: 0 | F18: 0 | G18: 0 | H18: 0 | I18: 0 | J18: 0 | K18: 0 | L18: 0 | M18: 0 | N18: 0 | O18: 0 | P18: 0 | Q18: =B18+C18+D18+E18+F18+G18+H18+I18+J18+K18+L18+M18+N18+O18+P18 -> -176.92 | R18: =-Q18/$Q$14 -> 0.00015550836 | T18: =SUM(B18:P18) -> -176.92 | V18: =T18-Q18 -> 0
A19: Despesa com Radio e Telefonia Celular | B19: 0 | C19: =0-B19 -> 0 | D19: 0 | E19: 0 | F19: 0 | G19: 0 | H19: 0 | I19: 0 | J19: 0 | K19: 0 | L19: 0 | M19: 0 | N19: 0 | O19: 0 | P19: 0 | Q19: =B19+C19+D19+E19+F19+G19+H19+I19+J19+K19+L19+M19+N19+O19+P19 -> 0 | R19: =-Q19/$Q$14 -> 0 | T19: =SUM(B19:P19) -> 0 | V19: =T19-Q19 -> 0
A20: Equipamento de Segurança - EPIs - 360 | B20: -545.57 | C20: =-3103.7-B20 -> -2558.13 | D20: -725.75 | E20: 0 | F20: 0 | G20: 0 | H20: 0 | I20: 0 | J20: 0 | K20: 0 | L20: 0 | M20: 0 | N20: 0 | O20: 0 | P20: 0 | Q20: =B20+C20+D20+E20+F20+G20+H20+I20+J20+K20+L20+M20+N20+O20+P20 -> -3829.45 | R20: =-Q20/$Q$14 -> 0.003365993 | T20: =SUM(B20:P20) -> -3829.45 | V20: =T20-Q20 -> 0
A21: Ferias - 315 | B21: -6690.01 | C21: =-55840.11-B21 -> -49150.1 | D21: -12532.77 | E21: 0 | F21: 0 | G21: 0 | H21: 0 | I21: 0 | J21: 0 | K21: 0 | L21: 0 | M21: 0 | N21: 0 | O21: 0 | P21: 0 | Q21: =B21+C21+D21+E21+F21+G21+H21+I21+J21+K21+L21+M21+N21+O21+P21 -> -68372.88 | R21: =-Q21/$Q$14 -> 0.060098091 | T21: =SUM(B21:P21) -> -68372.88 | V21: =T21-Q21 -> 0
A22: FGTS - 317 | B22: -3950.11 | C22: =-36146-B22 -> -32195.89 | D22: -8021.56 | E22: 0 | F22: 0 | G22: 0 | H22: 0 | I22: 0 | J22: 0 | K22: 0 | L22: 0 | M22: 0 | N22: 0 | O22: 0 | P22: 0 | Q22: =B22+C22+D22+E22+F22+G22+H22+I22+J22+K22+L22+M22+N22+O22+P22 -> -44167.56 | R22: =-Q22/$Q$14 -> 0.038822206 | T22: =SUM(B22:P22) -> -44167.56 | V22: =T22-Q22 -> 0
A23: Horas Extras - 499 | B23: -2834.22 | C23: =-33881.77-B23 -> -31047.55 | D23: -3895.22 | E23: 0 | F23: 0 | G23: 0 | H23: 0 | I23: 0 | J23: 0 | K23: 0 | L23: 0 | M23: 0 | N23: 0 | O23: 0 | P23: 0 | Q23: =B23+C23+D23+E23+F23+G23+H23+I23+J23+K23+L23+M23+N23+O23+P23 -> -37776.99 | R23: =-Q23/$Q$14 -> 0.033205051 | T23: =SUM(B23:P23) -> -37776.99 | V23: =T23-Q23 -> 0
A24: Indenizações e Aviso Prévio - 318 | B24: 0 | C24: =0-B24 -> 0 | D24: 0 | E24: 0 | F24: 0 | G24: 0 | H24: 0 | I24: 0 | J24: 0 | K24: 0 | L24: 0 | M24: 0 | N24: 0 | O24: 0 | P24: 0 | Q24: =B24+C24+D24+E24+F24+G24+H24+I24+J24+K24+L24+M24+N24+O24+P24 -> 0 | R24: =-Q24/$Q$14 -> 0 | T24: =SUM(B24:P24) -> 0 | V24: =T24-Q24 -> 0
A25: Indenizações Trabalhistas Judiciais - 369 | B25: 0 | C25: =0-B25 -> 0 | D25: 0 | E25: 0 | F25: 0 | G25: 0 | H25: 0 | I25: 0 | J25: 0 | K25: 0 | L25: 0 | M25: 0 | N25: 0 | O25: 0 | P25: 0 | Q25: =B25+C25+D25+E25+F25+G25+H25+I25+J25+K25+L25+M25+N25+O25+P25 -> 0 | R25: =-Q25/$Q$14 -> 0 | T25: =SUM(B25:P25) -> 0 | V25: =T25-Q25 -> 0
A26: INSS - 316 | B26: -4770.4 | C26: =-41125.19-B26 -> -36354.79 | D26: -8823.73 | E26: 0 | F26: 0 | G26: 0 | H26: 0 | I26: 0 | J26: 0 | K26: 0 | L26: 0 | M26: 0 | N26: 0 | O26: 0 | P26: 0 | Q26: =B26+C26+D26+E26+F26+G26+H26+I26+J26+K26+L26+M26+N26+O26+P26 -> -49948.92 | R26: =-Q26/$Q$14 -> 0.04390388 | T26: =SUM(B26:P26) -> -49948.92 | V26: =T26-Q26 -> 0
A27: Locação de Andaimes - 328 | B27: 0 | C27: =0-B27 -> 0 | D27: 0 | E27: 0 | F27: 0 | G27: 0 | H27: 0 | I27: 0 | J27: 0 | K27: 0 | L27: 0 | M27: 0 | N27: 0 | O27: 0 | P27: 0 | Q27: =B27+C27+D27+E27+F27+G27+H27+I27+J27+K27+L27+M27+N27+O27+P27 -> 0 | R27: =-Q27/$Q$14 -> 0 | T27: =SUM(B27:P27) -> 0 | V27: =T27-Q27 -> 0
A28: Locação de Máqs, Ferramentas e Equipamentos - | B28: -11.87 | C28: =-11.87-B28 -> 0 | D28: 0 | E28: 0 | F28: 0 | G28: 0 | H28: 0 | I28: 0 | J28: 0 | K28: 0 | L28: 0 | M28: 0 | N28: 0 | O28: 0 | P28: 0 | Q28: =B28+C28+D28+E28+F28+G28+H28+I28+J28+K28+L28+M28+N28+O28+P28 -> -11.87 | R28: =-Q28/$Q$14 -> 1.043344e-05 | T28: =SUM(B28:P28) -> -11.87 | V28: =T28-Q28 -> 0
A29: Manutenção de Equipamento - 394 | B29: 0 | C29: =0-B29 -> 0 | D29: 0 | E29: 0 | F29: 0 | G29: 0 | H29: 0 | I29: 0 | J29: 0 | K29: 0 | L29: 0 | M29: 0 | N29: 0 | O29: 0 | P29: 0 | Q29: =B29+C29+D29+E29+F29+G29+H29+I29+J29+K29+L29+M29+N29+O29+P29 -> 0 | R29: =-Q29/$Q$14 -> 0 | T29: =SUM(B29:P29) -> 0 | V29: =T29-Q29 -> 0
A30: Manutenção de Veículos - 510 | B30: 0 | C30: =0-B30 -> 0 | D30: 0 | E30: 0 | F30: 0 | G30: 0 | H30: 0 | I30: 0 | J30: 0 | K30: 0 | L30: 0 | M30: 0 | N30: 0 | O30: 0 | P30: 0 | Q30: =B30+C30+D30+E30+F30+G30+H30+I30+J30+K30+L30+M30+N30+O30+P30 -> 0 | R30: =-Q30/$Q$14 -> 0 | T30: =SUM(B30:P30) -> 0 | V30: =T30-Q30 -> 0
A31: Medicina Ocupacional e Assist médica - 3 | B31: -984.52 | C31: =-3598.98-B31 -> -2614.46 | D31: -568 | E31: 0 | F31: 0 | G31: 0 | H31: 0 | I31: 0 | J31: 0 | K31: 0 | L31: 0 | M31: 0 | N31: 0 | O31: 0 | P31: 0 | Q31: =B31+C31+D31+E31+F31+G31+H31+I31+J31+K31+L31+M31+N31+O31+P31 -> -4166.98 | R31: =-Q31/$Q$14 -> 0.0036626736 | T31: =SUM(B31:P31) -> -4166.98 | V31: =T31-Q31 -> 0
A32: Móveis Não Imobilizado - 364 | B32: 0 | C32: =0-B32 -> 0 | D32: 0 | E32: 0 | F32: 0 | G32: 0 | H32: 0 | I32: 0 | J32: 0 | K32: 0 | L32: 0 | M32: 0 | N32: 0 | O32: 0 | P32: 0 | Q32: =B32+C32+D32+E32+F32+G32+H32+I32+J32+K32+L32+M32+N32+O32+P32 -> 0 | R32: =-Q32/$Q$14 -> 0 | T32: =SUM(B32:P32) -> 0 | V32: =T32-Q32 -> 0
A33: Peças, Ferramentas e Acessórios - 361 | B33: -774.52 | C33: =-1417.89-B33 -> -643.37 | D33: -27.9 | E33: 0 | F33: 0 | G33: 0 | H33: 0 | I33: 0 | J33: 0 | K33: 0 | L33: 0 | M33: 0 | N33: 0 | O33: 0 | P33: 0 | Q33: =B33+C33+D33+E33+F33+G33+H33+I33+J33+K33+L33+M33+N33+O33+P33 -> -1445.79 | R33: =-Q33/$Q$14 -> 0.0012708141 | T33: =SUM(B33:P33) -> -1445.79 | V33: =T33-Q33 -> 0
A34: Premios e Gratificacoes - 313 | B34: -29407 | C34: =-255872.91-B34 -> -226465.91 | D34: -40177.24 | E34: 0 | F34: 0 | G34: 0 | H34: 0 | I34: 0 | J34: 0 | K34: 0 | L34: 0 | M34: 0 | N34: 0 | O34: 0 | P34: 0 | Q34: =B34+C34+D34+E34+F34+G34+H34+I34+J34+K34+L34+M34+N34+O34+P34 -> -296050.15 | R34: =-Q34/$Q$14 -> 0.26022085 | T34: =SUM(B34:P34) -> -296050.15 | V34: =T34-Q34 -> 0
A35: Salarios e Ordenados - 311 | B35: -46525.16 | C35: =-399251.49-B35 -> -352726.33 | D35: -87109.87 | E35: 0 | F35: 0 | G35: 0 | H35: 0 | I35: 0 | J35: 0 | K35: 0 | L35: 0 | M35: 0 | N35: 0 | O35: 0 | P35: 0 | Q35: =B35+C35+D35+E35+F35+G35+H35+I35+J35+K35+L35+M35+N35+O35+P35 -> -486361.36 | R35: =-Q35/$Q$14 -> 0.42749975 | T35: =SUM(B35:P35) -> -486361.36 | V35: =T35-Q35 -> 0
A36: Serviços de Terceiros - 324 | B36: 0 | C36: =-72.72-B36 -> -72.72 | D36: 0 | E36: 0 | F36: 0 | G36: 0 | H36: 0 | I36: 0 | J36: 0 | K36: 0 | L36: 0 | M36: 0 | N36: 0 | O36: 0 | P36: 0 | Q36: =B36+C36+D36+E36+F36+G36+H36+I36+J36+K36+L36+M36+N36+O36+P36 -> -72.72 | R36: =-Q36/$Q$14 -> 6.3919103e-05 | T36: =SUM(B36:P36) -> -72.72 | V36: =T36-Q36 -> 0
A37: Seguro Riscos Execução de Serv. Trab. | B37: 0 | C37: =0-B37 -> 0 | D37: 0 | E37: 0 | F37: 0 | G37: 0 | H37: 0 | I37: 0 | J37: 0 | K37: 0 | L37: 0 | M37: 0 | N37: 0 | O37: 0 | P37: 0 | Q37: =B37+C37+D37+E37+F37+G37+H37+I37+J37+K37+L37+M37+N37+O37+P37 -> 0 | R37: =-Q37/$Q$14 -> 0 | T37: =SUM(B37:P37) -> 0 | V37: =T37-Q37 -> 0
A38: Uniformes - 425 | B38: -1829.37 | C38: =-8023.1-B38 -> -6193.73 | D38: -811.24 | E38: 0 | F38: 0 | G38: 0 | H38: 0 | I38: 0 | J38: 0 | K38: 0 | L38: 0 | M38: 0 | N38: 0 | O38: 0 | P38: 0 | Q38: =B38+C38+D38+E38+F38+G38+H38+I38+J38+K38+L38+M38+N38+O38+P38 -> -8834.34 | R38: =-Q38/$Q$14 -> 0.007765169 | T38: =SUM(B38:P38) -> -8834.34 | V38: =T38-Q38 -> 0
A39: Vale Transporte e Condução - 321 | B39: -4349.64 | C39: =-38410.3-B39 -> -34060.66 | D39: -9534.45 | E39: 0 | F39: 0 | G39: 0 | H39: 0 | I39: 0 | J39: 0 | K39: 0 | L39: 0 | M39: 0 | N39: 0 | O39: 0 | P39: 0 | Q39: =B39+C39+D39+E39+F39+G39+H39+I39+J39+K39+L39+M39+N39+O39+P39 -> -47944.75 | R39: =-Q39/$Q$14 -> 0.042142263 | T39: =SUM(B39:P39) -> -47944.75 | V39: =T39-Q39 -> 0
A40: 13º Salario - 314 | B40: -3124.79 | C40: =-40352.95-B40 -> -37228.16 | D40: -9800.8 | E40: 0 | F40: 0 | G40: 0 | H40: 0 | I40: 0 | J40: 0 | K40: 0 | L40: 0 | M40: 0 | N40: 0 | O40: 0 | P40: 0 | Q40: =B40+C40+D40+E40+F40+G40+H40+I40+J40+K40+L40+M40+N40+O40+P40 -> -50153.75 | R40: =-Q40/$Q$14 -> 0.044083921 | T40: =SUM(B40:P40) -> -50153.75 | V40: =T40-Q40 -> 0
A41: Cursos e treinamentos | B41: 0 | C41: =0-B41 -> 0 | D41: 0 | E41: 0 | F41: 0 | G41: 0 | H41: 0 | I41: 0 | J41: 0 | K41: 0 | L41: 0 | M41: 0 | N41: 0 | O41: 0 | P41: 0 | Q41: =B41+C41+D41+E41+F41+G41+H41+I41+J41+K41+L41+M41+N41+O41+P41 -> 0 | R41: =-Q41/$Q$14 -> 0 | T41: =SUM(B41:P41) -> 0 | V41: =T41-Q41 -> 0
A42: Confraternização de Funcionários | B42: 0 | C42: 0 | D42: =SUM(E42:P42) -> 0 | E42: 0 | F42: 0 | G42: 0 | H42: 0 | I42: 0 | J42: 0 | K42: 0 | L42: 0 | M42: 0 | N42: 0 | O42: 0 | P42: 0 | Q42: =B42+C42+D42+E42+F42+G42+H42+I42+J42+K42+L42+M42+N42+O42+P42 -> 0 | R42: =-Q42/$Q$14 -> 0 | T42: =SUM(B42:P42) -> 0 | V42: =T42-Q42 -> 0
A43: Custos Total... | B43: =SUM(B17:B42) -> -112843.57 | C43: =SUM(C17:C42) -> -883730.46 | D43: =SUM(D17:D42) -> -206344.11 | E43: =SUM(E17:E42) -> 0 | F43: =SUM(F17:F42) -> 0 | G43: =SUM(G17:G42) -> 0 | H43: =SUM(H17:H42) -> 0 | I43: =SUM(I17:I42) -> 0 | ... Q43: =SUM(Q17:Q42) -> -1202918.1 | R43: =-Q43/$Q$14 -> 1.0573356 | T43: =SUM(B43:P43) -> -1202918.1 | V43: =T43-Q43 -> 0
T44: =SUM(B44:P44) -> 0 | V44: =T44-Q44 -> 0
A45: = Lucro/Prejuízo Bruto | B45: =B14+B43 -> -112843.57 | C45: =C14+C43 -> 149239.02 | D45: =D14+D43 -> -101625.53 | E45: =E14+E43 -> 0 | F45: =F14+F43 -> 0 | G45: =G14+G43 -> 0 | H45: =H14+H43 -> 0 | I45: =I14+I43 -> 0 | ... P45: =P14+P43 -> 0 | Q45: =B45+C45+D45+E45+F45+G45+H45+I45+J45+K45+L45+M45+N45+O45+P45 -> -65230.08 | R45: =-Q45/$Q$14 -> 0.057335646 | T45: =SUM(B45:P45) -> -65230.08 | V45: =T45-Q45 -> 0
T46: =SUM(B46:P46) -> 0 | V46: =T46-Q46 -> 0
A47: (-) Impostos s/ Serviços - (13,15% s/ Faturamento) | B47: =-B12*12.46% -> 0 | C47: =-C12*13.15% -> -135835.49 | D47: =-D12*13.15% -> -13770.493 | E47: =-E12*13.15% -> 0 | F47: =-F12*13.15% -> 0 | G47: =-G12*13.15% -> 0 | H47: =-H12*13.15% -> 0 | I47: =-I12*13.15% -> 0 | J47: =-J12*13.15% -> 0 | ... P47: =-P12*13.15% -> 0 | Q47: =B47+C47+D47+E47+F47+G47+H47+I47+J47+K47+L47+M47+N47+O47+P47 -> -149605.98 | R47: =-Q47/$Q$14 -> 0.1315 | T47: =SUM(B47:P47) -> -149605.98 | V47: =T47-Q47 -> 0
T48: =SUM(B48:P48) -> 0 | V48: =T48-Q48 -> 0
A49: (-) IRPJ e CSLL - (1,22% s/faturamento) | B49: =-B12*1.22% -> 0 | C49: =-C12*1.22% -> -12602.228 | D49: =-D12*1.22% -> -1277.5667 | E49: =-E12*1.22% -> 0 | F49: =-F12*1.22% -> 0 | G49: =-G12*1.22% -> 0 | H49: =-H12*1.22% -> 0 | I49: =-I12*1.22% -> 0 | ... P49: =-P12*1.22% -> 0 | Q49: =B49+C49+D49+E49+F49+G49+H49+I49+J49+K49+L49+M49+N49+O49+P49 -> -13879.794 | R49: =-Q49/$Q$14 -> 0.0122 | T49: =SUM(B49:P49) -> -13879.794 | V49: =T49-Q49 -> 0
T50: =SUM(B50:P50) -> 0 | V50: =T50-Q50 -> 0
A51: Total Desp Administrativas/Técnico - ( 5,56% Taxa Adm. Prevista) | B51: -6274.1 | C51: =C43*5.56% -> -49135.414 | D51: =D43*5.56% -> -11472.733 | E51: =E43*5.56% -> 0 | F51: =F43*5.56% -> 0 | G51: =G43*5.56% -> 0 | H51: =H43*5.56% -> 0 | I51: =I43*5.56% -> 0 | J51: =J43*5.56% -> 0 | ... P51: =P43*5.56% -> 0 | Q51: =B51+C51+D51+E51+F51+G51+H51+I51+J51+K51+L51+M51+N51+O51+P51 -> -66882.246 | R51: =-Q51/$Q$14 -> 0.05878786 | T51: =SUM(B51:P51) -> -66882.246 | V51: =T51-Q51 -> 0
T52: =SUM(B52:P52) -> 0 | V52: =T52-Q52 -> 0
A53: Total Despesas Financeiras -( 0,01% s/ Custo de Obras-média) | B53: -11.28 | C53: =C43*0.01% -> -88.373046 | D53: =D43*0.01% -> -20.634411 | E53: =E43*0.01% -> 0 | F53: =F43*0.01% -> 0 | G53: =G43*0.01% -> 0 | H53: =H43*0.01% -> 0 | I53: =I43*0.01% -> 0 | J53: =J43*0.01% -> 0 | ... P53: =P43*0.01% -> 0 | Q53: =B53+C53+D53+E53+F53+G53+H53+I53+J53+K53+L53+M53+N53+O53+P53 -> -120.28746 | R53: =-Q53/$Q$14 -> 0.00010572973 | T53: =SUM(B53:P53) -> -120.28746 | V53: =T53-Q53 -> 0
T54: =SUM(B54:P54) -> 0 | V54: =T54-Q54 -> 0
A55: LUCRO/PREJUIZO - LIQUIDO DA OBRA - 267 - | B55: =B45+B51+B53+B47+B49 -> -119128.95 | C55: =C45+C51+C53+C47+C49 -> -48422.481 | D55: =D45+D51+D53+D47+D49 -> -128166.96 | E55: =E45+E51+E53+E47+E49 -> 0 | F55: =F45+F51+F53+F47+F49 -> 0 | G55: =G45+G51+G53+G47+G49 -> 0 | H55: =H45+H51+H53+H47+H49 -> 0 | I55: =I45+I51+I53+I47+I49 -> 0 | ... P55: =P45+P51+P53+P47+P49 -> 0 | Q55: =B55+C55+D55+E55+F55+G55+H55+I55+J55+K55+L55+M55+N55+O55+P55 -> -295718.39 | R55: =-Q55/$Q$14 -> 0.25992924 | T55: =SUM(B55:P55) -> -295718.39 | V55: =T55-Q55 -> 0
A58: NÚMERO DE FUNCIONÁRIOS - FINAL DO MÊS | G58: 8 | H58: 9 | I58: 7 | J58: 7 | K58: 1 | L58: 2 | M58: 1
A60: Elaborado: INOV SOLUÇÃO EMPRESARIAL E CONTÁBIL LTDA | R60: 310/01/2025
B62: =B14+B43+B47+B49+B51+B53 -> -119128.95 | C62: =C14+C43+C47+C49+C51+C53 -> -48422.481 | D62: =D14+D43+D47+D49+D51+D53 -> -128166.96 | E62: =E14+E43+E47+E49+E51+E53 -> 0 | F62: =F14+F43+F47+F49+F51+F53 -> 0 | G62: =G14+G43+G47+G49+G51+G53 -> 0 | H62: =H14+H43+H47+H49+H51+H53 -> 0 | I62: =I14+I43+I47+I49+I51+I53 -> 0 | ... Q62: =Q14+Q43+Q47+Q49+Q51+Q53 -> -295718.39
B64: =B55-B62 -> 0 | C64: =C55-C62 -> 0 | D64: =D55-D62 -> 0 | E64: =E55-E62 -> 0 | F64: =F55-F62 -> 0 | G64: =G55-G62 -> 0 | H64: =H55-H62 -> 0 | I64: =I55-I62 -> 0 | ... Q64: =Q55-Q62 -> 0

Sheet OBRA 268
A1: BELA NOVA CONSTRUTORA EIRELI
A3: DEMONSTRAÇÃO DO RESULTADO APURADO
A5: OBRA 268 - EREDITA - EZTEC
A7: OBRA ENCERRADA
B9: Out a Dez/2022 | C9: Jan a Dez/23 | D9: Janeiro/2024 | E9: Fevereiro/2024 | F9: Março/2024 | G9: Abril/2024 | H9: Maio/2024 | I9: Junho/2024 | J9: Julho/2024 | K9: Agosto/2024 | L9: Setembro/2024 | M9: Outubro/2024 | N9: Novembro/2024 | O9: Dezembro/2024 | P9: Acumulado | Q9: % S/FAT
A10: Receitas Brutas
A11: Servicos prestados | B11: 233796.98 | C11: =687246.83-B11 -> 453449.85 | D11: 0 | E11: 0 | F11: 0 | G11: 0 | H11: 0 | I11: 0 | J11: 0 | K11: 0 | L11: 0 | M11: 0 | N11: 0 | O11: 0 | P11: =B11+C11+D11+E11+F11+G11+H11+I11+J11+K11+L11+M11+N11+O11 -> 687246.83 | Q11: 1 | S11: =SUM(B11:H11) -> 687246.83 | U11: =S11-P11 -> 0
A12: Locação de Equipamentos - 450 | B12: 0 | C12: 0 | D12: 0 | E12: 0 | F12: 0 | G12: 0 | H12: 0 | I12: 0 | J12: 0 | K12: 0 | L12: 0 | M12: 0 | N12: 0 | O12: 0 | P12: =B12+C12+D12+E12+F12+G12+H12+I12+J12+K12+L12+M12+N12+O12 -> 0 | S12: =SUM(B12:H12) -> 0 | U12: =S12-P12 -> 0
A13: Receitas Brutas Total... | B13: =B11+B12 -> 233796.98 | C13: =SUM(C11:C12) -> 453449.85 | D13: =D11+D12 -> 0 | E13: =E11+E12 -> 0 | F13: =F11 -> 0 | G13: =G11 -> 0 | H13: =H11 -> 0 | I13: =I11 -> 0 | J13: =J11 -> 0 | K13: =K11 -> 0 | L13: =L11 -> 0 | M13: =M11 -> 0 | ... O13: =O11 -> 0 | P13: =SUM(P11:P12) -> 687246.83 | Q13: 1 | S13: =SUM(B13:H13) -> 687246.83 | U13: =S13-P13 -> 0
S14: =SUM(B14:H14) -> 0 | U14: =S14-P14 -> 0
A15: Custos | S15: =SUM(B15:H15) -> 0 | U15: =S15-P15 -> 0
A16: Alimentação - 320 | B16: -3481.54 | C16: =-35095.93-B16 -> -31614.39 | D16: 0 | E16: 0 | F16: 0 | G16: 0 | H16: 0 | I16: 0 | J16: 0 | K16: 0 | L16: 0 | M16: 0 | N16: 0 | O16: 0 | P16: =B16+C16+D16+E16+F16+G16+H16+I16+J16+K16+L16+M16+N16+O16 -> -35095.93 | Q16: =-P16/$P$11 -> 0.051067431 | S16: =SUM(B16:H16) -> -35095.93 | U16: =S16-P16 -> 0
A17: Combustíveis - 322 | B17: -176.92 | C17: =-176.92-B17 -> 0 | D17: 0 | E17: 0 | F17: 0 | G17: 0 | H17: 0 | I17: 0 | J17: 0 | K17: 0 | L17: 0 | M17: 0 | N17: 0 | O17: 0 | P17: =B17+C17+D17+E17+F17+G17+H17+I17+J17+K17+L17+M17+N17+O17 -> -176.92 | Q17: =-P17/$P$11 -> 0.00025743298 | S17: =SUM(B17:H17) -> -176.92 | U17: =S17-P17 -> 0
A18: Despesa com Radio e Telefonia Celular | B18: 0 | C18: =0-B18 -> 0 | D18: 0 | E18: 0 | F18: 0 | G18: 0 | H18: 0 | I18: 0 | J18: 0 | K18: 0 | L18: 0 | M18: 0 | N18: 0 | O18: 0 | P18: =B18+C18+D18+E18+F18+G18+H18+I18+J18+K18+L18+M18+N18+O18 -> 0 | Q18: =-P18/$P$11 -> 0 | S18: =SUM(B18:H18) -> 0 | U18: =S18-P18 -> 0
A19: Equipamento de Segurança - EPIs - 360 | B19: -319.3 | C19: =-340.27-B19 -> -20.97 | D19: 0 | E19: 0 | F19: 0 | G19: 0 | H19: 0 | I19: 0 | J19: 0 | K19: 0 | L19: 0 | M19: 0 | N19: 0 | O19: 0 | P19: =B19+C19+D19+E19+F19+G19+H19+I19+J19+K19+L19+M19+N19+O19 -> -340.27 | Q19: =-P19/$P$11 -> 0.00049512051 | S19: =SUM(B19:H19) -> -340.27 | U19: =S19-P19 -> 0
A20: Ferias - 315 | B20: -3345 | C20: =-27438.66-B20 -> -24093.66 | D20: -312.12 | E20: -312.12 | F20: -312.12 | G20: -312.12 | H20: -326.25 | I20: 0 | J20: 0 | K20: 0 | L20: 0 | M20: 0 | N20: 0 | O20: 0 | P20: =B20+C20+D20+E20+F20+G20+H20+I20+J20+K20+L20+M20+N20+O20 -> -29013.39 | Q20: =-P20/$P$11 -> 0.042216841 | S20: =SUM(B20:H20) -> -29013.39 | U20: =S20-P20 -> 0
A21: FGTS - 317 | B21: -1662.39 | C21: =-16909.44-B21 -> -15247.05 | D21: -192.4 | E21: -192.4 | F21: -192.4 | G21: -192.4 | H21: -201.11 | I21: 0 | J21: 0 | K21: 0 | L21: 0 | M21: 0 | N21: 0 | O21: 0 | P21: =B21+C21+D21+E21+F21+G21+H21+I21+J21+K21+L21+M21+N21+O21 -> -17880.15 | Q21: =-P21/$P$11 -> 0.026017072 | S21: =SUM(B21:H21) -> -17880.15 | U21: =S21-P21 -> 0
A22: Horas Extras - 499 | B22: -850.72 | C22: =-7772.22-B22 -> -6921.5 | D22: 0 | E22: 0 | F22: 0 | G22: 0 | H22: 0 | I22: 0 | J22: 0 | K22: 0 | L22: 0 | M22: 0 | N22: 0 | O22: 0 | P22: =B22+C22+D22+E22+F22+G22+H22+I22+J22+K22+L22+M22+N22+O22 -> -7772.22 | Q22: =-P22/$P$11 -> 0.011309212 | S22: =SUM(B22:H22) -> -7772.22 | U22: =S22-P22 -> 0
A23: Indenizações e Aviso Prévio - 318 | B23: 0 | C23: =5252.36-B23 -> 5252.36 | D23: 0 | E23: 0 | F23: 0 | G23: 0 | H23: 0 | I23: 0 | J23: 0 | K23: 0 | L23: 0 | M23: 0 | N23: 0 | O23: 0 | P23: =B23+C23+D23+E23+F23+G23+H23+I23+J23+K23+L23+M23+N23+O23 -> 5252.36 | Q23: =P23/$P$11 -> 0.0076426107 | S23: =SUM(B23:H23) -> 5252.36 | U23: =S23-P23 -> 0
A24: Indenizações Trabalhistas Judiciais - 369 | B24: 1313.9 | C24: =1313.9-B24 -> 0 | D24: 0 | E24: 0 | F24: 0 | G24: 0 | H24: 0 | I24: 0 | J24: 0 | K24: 0 | L24: 0 | M24: 0 | N24: 0 | O24: 0 | P24: =B24+C24+D24+E24+F24+G24+H24+I24+J24+K24+L24+M24+N24+O24 -> 1313.9 | Q24: =P24/$P$11 -> 0.0019118313 | S24: =SUM(B24:H24) -> 1313.9 | U24: =S24-P24 -> 0
A25: INSS - 316 | B25: -2008.73 | C25: =-17755.96-B25 -> -15747.23 | D25: 0 | E25: 0 | F25: 0 | G25: 0 | H25: 0 | I25: 0 | J25: 0 | K25: 0 | L25: 0 | M25: 0 | N25: 0 | O25: 0 | P25: =B25+C25+D25+E25+F25+G25+H25+I25+J25+K25+L25+M25+N25+O25 -> -17755.96 | Q25: =-P25/$P$11 -> 0.025836365 | S25: =SUM(B25:H25) -> -17755.96 | U25: =S25-P25 -> 0
A26: Locação de Andaimes - 328 | B26: 0 | C26: =0-B26 -> 0 | D26: 0 | E26: 0 | F26: 0 | G26: 0 | H26: 0 | I26: 0 | J26: 0 | K26: 0 | L26: 0 | M26: 0 | N26: 0 | O26: 0 | P26: =B26+C26+D26+E26+F26+G26+H26+I26+J26+K26+L26+M26+N26+O26 -> 0 | Q26: =-P26/$P$11 -> 0 | S26: =SUM(B26:H26) -> 0 | U26: =S26-P26 -> 0
A27: Locação de Máqs, Ferramentas e Equipamentos - | B27: -11.87 | C27: =-11.87-B27 -> 0 | D27: 0 | E27: 0 | F27: 0 | G27: 0 | H27: 0 | I27: 0 | J27: 0 | K27: 0 | L27: 0 | M27: 0 | N27: 0 | O27: 0 | P27: =B27+C27+D27+E27+F27+G27+H27+I27+J27+K27+L27+M27+N27+O27 -> -11.87 | Q27: =-P27/$P$11 -> 1.7271815e-05 | S27: =SUM(B27:H27) -> -11.87 | U27: =S27-P27 -> 0
A28: Manutenção de Equipamento - 394 | B28: 0 | C28: =0-B28 -> 0 | D28: 0 | E28: 0 | F28: 0 | G28: 0 | H28: 0 | I28: 0 | J28: 0 | K28: 0 | L28: 0 | M28: 0 | N28: 0 | O28: 0 | P28: =B28+C28+D28+E28+F28+G28+H28+I28+J28+K28+L28+M28+N28+O28 -> 0 | Q28: =-P28/$P$11 -> 0 | S28: =SUM(B28:H28) -> 0 | U28: =S28-P28 -> 0
A29: Manutenção de Veículos - 510 | B29: 0 | C29: =0-B29 -> 0 | D29: 0 | E29: 0 | F29: 0 | G29: 0 | H29: 0 | I29: 0 | J29: 0 | K29: 0 | L29: 0 | M29: 0 | N29: 0 | O29: 0 | P29: =B29+C29+D29+E29+F29+G29+H29+I29+J29+K29+L29+M29+N29+O29 -> 0 | Q29: =-P29/$P$11 -> 0 | S29: =SUM(B29:H29) -> 0 | U29: =S29-P29 -> 0
A30: Medicina Ocupacional e Assist médica - 3 | B30: -547.35 | C30: =-2067.01-B30 -> -1519.66 | D30: 0 | E30: 0 | F30: 0 | G30: 0 | H30: 0 | I30: 0 | J30: 0 | K30: 0 | L30: 0 | M30: 0 | N30: 0 | O30: 0 | P30: =B30+C30+D30+E30+F30+G30+H30+I30+J30+K30+L30+M30+N30+O30 -> -2067.01 | Q30: =-P30/$P$11 -> 0.0030076676 | S30: =SUM(B30:H30) -> -2067.01 | U30: =S30-P30 -> 0
A31: Móveis Não Imobilizado - 364 | B31: 0 | C31: =0-B31 -> 0 | D31: 0 | E31: 0 | F31: 0 | G31: 0 | H31: 0 | I31: 0 | J31: 0 | K31: 0 | L31: 0 | M31: 0 | N31: 0 | O31: 0 | P31: =B31+C31+D31+E31+F31+G31+H31+I31+J31+K31+L31+M31+N31+O31 -> 0 | Q31: =-P31/$P$11 -> 0 | S31: =SUM(B31:H31) -> 0 | U31: =S31-P31 -> 0
A32: Peças, Ferramentas e Acessórios - 361 | B32: 0 | C32: =-172.08-B32 -> -172.08 | D32: 0 | E32: 0 | F32: 0 | G32: 0 | H32: 0 | I32: 0 | J32: 0 | K32: 0 | L32: 0 | M32: 0 | N32: 0 | O32: 0 | P32: =B32+C32+D32+E32+F32+G32+H32+I32+J32+K32+L32+M32+N32+O32 -> -172.08 | Q32: =-P32/$P$11 -> 0.00025039039 | S32: =SUM(B32:H32) -> -172.08 | U32: =S32-P32 -> 0
A33: Premios e Gratificacoes - 313 | B33: -9281 | C33: =-89210-B33 -> -79929 | D33: 0 | E33: 0 | F33: 0 | G33: 0 | H33: 0 | I33: 0 | J33: 0 | K33: 0 | L33: 0 | M33: 0 | N33: 0 | O33: 0 | P33: =B33+C33+D33+E33+F33+G33+H33+I33+J33+K33+L33+M33+N33+O33 -> -89210 | Q33: =-P33/$P$11 -> 0.1298078 | S33: =SUM(B33:H33) -> -89210 | U33: =S33-P33 -> 0
A34: Salarios e Ordenados - 311 | B34: -19744.89 | C34: =-180672-B34 -> -160927.11 | D34: 0 | E34: 0 | F34: 0 | G34: 0 | H34: 0 | I34: 0 | J34: 0 | K34: 0 | L34: 0 | M34: 0 | N34: 0 | O34: 0 | P34: =B34+C34+D34+E34+F34+G34+H34+I34+J34+K34+L34+M34+N34+O34 -> -180672 | Q34: =-P34/$P$11 -> 0.26289245 | S34: =SUM(B34:H34) -> -180672 | U34: =S34-P34 -> 0
A35: Serviços de Terceiros - 324 | B35: 0 | C35: =-72.72-B35 -> -72.72 | D35: 0 | E35: 0 | F35: 0 | G35: 0 | H35: 0 | I35: 0 | J35: 0 | K35: 0 | L35: 0 | M35: 0 | N35: 0 | O35: 0 | P35: =B35+C35+D35+E35+F35+G35+H35+I35+J35+K35+L35+M35+N35+O35 -> -72.72 | Q35: =-P35/$P$11 -> 0.00010581351 | S35: =SUM(B35:H35) -> -72.72 | U35: =S35-P35 -> 0
A36: Seguro Riscos Execução de Serv. Trab. | B36: 0 | C36: =0-B36 -> 0 | D36: 0 | E36: 0 | F36: 0 | G36: 0 | H36: 0 | I36: 0 | J36: 0 | K36: 0 | L36: 0 | M36: 0 | N36: 0 | O36: 0 | P36: =B36+C36+D36+E36+F36+G36+H36+I36+J36+K36+L36+M36+N36+O36 -> 0 | Q36: =-P36/$P$11 -> 0 | S36: =SUM(B36:H36) -> 0 | U36: =S36-P36 -> 0
A37: Uniformes - 425 | B37: -728.46 | C37: =-3306-B37 -> -2577.54 | D37: 0 | E37: 0 | F37: 0 | G37: 0 | H37: 0 | I37: 0 | J37: 0 | K37: 0 | L37: 0 | M37: 0 | N37: 0 | O37: 0 | P37: =B37+C37+D37+E37+F37+G37+H37+I37+J37+K37+L37+M37+N37+O37 -> -3306 | Q37: =-P37/$P$11 -> 0.0048104987 | S37: =SUM(B37:H37) -> -3306 | U37: =S37-P37 -> 0
A38: Vale Transporte e Condução - 321 | B38: -1345.92 | C38: =-16865.8-B38 -> -15519.88 | D38: 0 | E38: 0 | F38: 0 | G38: 0 | H38: 0 | I38: 0 | J38: 0 | K38: 0 | L38: 0 | M38: 0 | N38: 0 | O38: 0 | P38: =B38+C38+D38+E38+F38+G38+H38+I38+J38+K38+L38+M38+N38+O38 -> -16865.8 | Q38: =-P38/$P$11 -> 0.02454111 | S38: =SUM(B38:H38) -> -16865.8 | U38: =S38-P38 -> 0
A39: 13º Salario - 314 | B39: -2450.27 | C39: =-20573.66-B39 -> -18123.39 | D39: 0 | E39: 0 | F39: 0 | G39: 0 | H39: 0 | I39: 0 | J39: 0 | K39: 0 | L39: 0 | M39: 0 | N39: 0 | O39: 0 | P39: =B39+C39+D39+E39+F39+G39+H39+I39+J39+K39+L39+M39+N39+O39 -> -20573.66 | Q39: =-P39/$P$11 -> 0.029936348 | S39: =SUM(B39:H39) -> -20573.66 | U39: =S39-P39 -> 0
A40: Cursos e treinamentos | B40: 0 | C40: =0-B40 -> 0 | D40: 0 | E40: 0 | F40: 0 | G40: 0 | H40: 0 | I40: 0 | J40: 0 | K40: 0 | L40: 0 | M40: 0 | N40: 0 | O40: 0 | P40: =B40+C40+D40+E40+F40+G40+H40+I40+J40+K40+L40+M40+N40+O40 -> 0 | Q40: =-P40/$P$11 -> 0 | S40: =SUM(B40:H40) -> 0 | U40: =S40-P40 -> 0
A41: Confraternização de Funcionários | B41: 0 | C41: 0 | D41: 0 | E41: 0 | F41: 0 | G41: 0 | H41: 0 | I41: 0 | J41: 0 | K41: 0 | L41: 0 | M41: 0 | N41: 0 | O41: 0 | P41: =B41+C41+D41+E41+F41+G41+H41+I41+J41+K41+L41+M41+N41+O41 -> 0 | Q41: =-P41/$P$11 -> 0 | S41: =SUM(B41:H41) -> 0 | U41: =S41-P41 -> 0
A42: Custos Total... | B42: =SUM(B16:B41) -> -44640.46 | C42: =SUM(C16:C41) -> -367233.82 | D42: =SUM(D16:D41) -> -504.52 | E42: =SUM(E16:E41) -> -504.52 | F42: =SUM(F16:F41) -> -504.52 | G42: =SUM(G16:G41) -> -504.52 | H42: =SUM(H16:H41) -> -527.36 | I42: =SUM(I16:I41) -> 0 | ... P42: =SUM(P16:P41) -> -414419.72 | Q42: =-P42/$P$11 -> 0.60301438 | S42: =SUM(B42:H42) -> -414419.72 | U42: =S42-P42 -> 0
I43: =SUM(I16:I41) -> 0 | J43: =SUM(J16:J41) -> 0 | K43: =SUM(K16:K41) -> 0 | L43: =SUM(L16:L41) -> 0 | M43: =SUM(M16:M41) -> 0 | N43: =SUM(N16:N41) -> 0 | O43: =SUM(O16:O41) -> 0 | S43: =SUM(B43:H43) -> 0 | U43: =S43-P43 -> 0
A44: = Lucro/Prejuízo Bruto | B44: =B13+B42 -> 189156.52 | C44: =C13+C42 -> 86216.03 | D44: =D13+D42 -> -504.52 | E44: =E13+E42 -> -504.52 | F44: =F13+F42 -> -504.52 | G44: =G13+G42 -> -504.52 | H44: =H13+H42 -> -527.36 | I44: =I13+I42 -> 0 | ... O44: =O13+O42 -> 0 | P44: =B44+C44+D44+E44+F44+G44+H44+I44+J44+K44+L44+M44+N44+O44 -> 272827.11 | Q44: =P44/$P$11 -> 0.39698562 | S44: =SUM(B44:H44) -> 272827.11 | U44: =S44-P44 -> 0
S45: =SUM(B45:H45) -> 0 | U45: =S45-P45 -> 0
A46: (-) Impostos s/ Serviços - (13,15% s/ Faturamento) | B46: -30744.3 | C46: =-C11*13.15% -> -59628.655 | D46: =-D11*13.15% -> 0 | E46: =-E11*13.15% -> 0 | F46: =-F11*13.15% -> 0 | G46: =-G11*13.15% -> 0 | H46: =-H11*13.15% -> 0 | I46: =-I11*13.15% -> 0 | J46: =-J11*13.15% -> 0 | ... O46: =-O11*13.15% -> 0 | P46: =B46+C46+D46+E46+F46+G46+H46+I46+J46+K46+L46+M46+N46+O46 -> -90372.955 | Q46: =-P46/$P$11 -> 0.1315 | S46: =SUM(B46:H46) -> -90372.955 | U46: =S46-P46 -> 0
S47: =SUM(B47:H47) -> 0 | U47: =S47-P47 -> 0
A48: (-) IRPJ e CSLL - (1,22% s/faturamento) | B48: =-B11*1.22% -> -2852.3232 | C48: =-C11*1.22% -> -5532.0882 | D48: =-D11*1.22% -> 0 | E48: =-E11*1.22% -> 0 | F48: =-F11*1.22% -> 0 | G48: =-G11*1.22% -> 0 | H48: =-H11*1.22% -> 0 | I48: =-I11*1.22% -> 0 | ... O48: =-O11*1.22% -> 0 | P48: =B48+C48+D48+E48+F48+G48+H48+I48+J48+K48+L48+M48+N48+O48 -> -8384.4113 | Q48: =-P48/$P$11 -> 0.0122 | S48: =SUM(B48:H48) -> -8384.4113 | U48: =S48-P48 -> 0
S49: =SUM(B49:H49) -> 0 | U49: =S49-P49 -> 0
A50: Total Desp Administrativas/Técnico - ( 5,56% Taxa Adm. Prevista) | B50: =B42*5.56% -> -2482.0096 | C50: =C42*5.56% -> -20418.2 | D50: =D42*5.56% -> -28.051312 | E50: =E42*5.56% -> -28.051312 | F50: =F42*5.56% -> -28.051312 | G50: =G42*5.56% -> -28.051312 | H50: =H42*5.56% -> -29.321216 | I50: =I42*5.56% -> 0 | ... O50: =O42*5.56% -> 0 | P50: =B50+C50+D50+E50+F50+G50+H50+I50+J50+K50+L50+M50+N50+O50 -> -23041.736 | Q50: =-P50/$P$11 -> 0.033527599 | S50: =SUM(B50:H50) -> -23041.736 | U50: =S50-P50 -> 0
S51: =SUM(B51:H51) -> 0 | U51: =S51-P51 -> 0
A52: Total Despesas Financeiras -( 0,01% s/ Custo de Obras-média) | B52: -4.46 | C52: =C42*0.01% -> -36.723382 | D52: =D42*0.01% -> -0.050452 | E52: =E42*0.01% -> -0.050452 | F52: =F42*0.01% -> -0.050452 | G52: =G42*0.01% -> -0.050452 | H52: =H42*0.01% -> -0.052736 | I52: =I42*0.01% -> 0 | J52: =J42*0.01% -> 0 | ... O52: =O42*0.01% -> 0 | P52: =B52+C52+D52+E52+F52+G52+H52+I52+J52+K52+L52+M52+N52+O52 -> -41.437926 | Q52: =-P52/$P$11 -> 6.0295551e-05 | S52: =SUM(B52:H52) -> -41.437926 | U52: =S52-P52 -> 0
S53: =SUM(B53:H53) -> 0 | U53: =S53-P53 -> 0
A54: LUCRO/PREJUIZO - LIQUIDO DA OBRA - 268 - | B54: =B44+B50+B52+B46+B48 -> 153073.43 | C54: =C44+C50+C52+C46+C48 -> 600.36278 | D54: =D44+D50+D52+D46+D48 -> -532.62176 | E54: =E44+E50+E52+E46+E48 -> -532.62176 | F54: =F44+F50+F52+F46+F48 -> -532.62176 | G54: =G44+G50+G52+G46+G48 -> -532.62176 | H54: =H44+H50+H52+H46+H48 -> -556.73395 | I54: =I44+I50+I52+I46+I48 -> 0 | ... O54: =O44+O50+O52+O46+O48 -> 0 | P54: =B54+C54+D54+E54+F54+G54+H54+I54+J54+K54+L54+M54+N54+O54 -> 150986.57 | Q54: =P54/$P$11 -> 0.21969773 | S54: =SUM(B54:H54) -> 150986.57 | U54: =S54-P54 -> 0
A56: NÚMERO DE FUNCIONÁRIOS - FINAL DO MÊS | D56: 1 | E56: 1 | F56: 1 | G56: 1 | H56: 1
D57: FÉRIAS | E57: AFASTADO | F57: AFASTADO | G57: AFASTADO | H57: AFASTADO
A58: Elaborado: INOV SOLUÇÃO EMPRESARIAL E CONTÁBIL LTDA | E58: Geraldo Silvino | F58: Geraldo Silvino | G58: Geraldo Silvino | H58: Geraldo Silvino | Q58: 45443
B62: =B13+B42+B46+B48+B50+B52 -> 153073.43 | C62: =C13+C42+C46+C48+C50+C52 -> 600.36278 | D62: =D13+D42+D46+D48+D50+D52 -> -532.62176 | E62: =E13+E42+E46+E48+E50+E52 -> -532.62176 | F62: =F13+F42+F46+F48+F50+F52 -> -532.62176 | G62: =G13+G42+G46+G48+G50+G52 -> -532.62176 | H62: =H13+H42+H46+H48+H50+H52 -> -556.73395 | I62: =I13+I42+I46+I48+I50+I52 -> 0 | ... P62: =P13+P42+P46+P48+P50+P52 -> 150986.57
B65: =B54-B62 -> 0 | C65: =C54-C62 -> 0 | D65: =D54-D62 -> 0 | E65: =E54-E62 -> 0 | F65: =F54-F62 -> 0 | G65: =G54-G62 -> 0 | H65: =H54-H62 -> 0 | I65: =I54-I62 -> 0 | ... P65: =P54-P62 -> 0

Sheet OBRA 269
A1: DEMONSTRAÇÃO DO RESULTADO APURADO
A3: OBRA 269 - V.B FARIA LIMA - BUENO NETO
A5: OBRA ENCERRADA
B7: Ago a Dez/2023 | C7: Janeiro/2024 | D7: Fevereiro/2024 | E7: Março/2024 | F7: Abril/2024 | G7: Maio/2024 | H7: Junho/2024 | I7: Julho/2024 | J7: Agosto/2024 | K7: Setembro/2024 | L7: Outubro/2024 | M7: Novembro/2024 | N7: Dezembro/2024 | O7: Acumulado | P7: % S/FAT
A8: Receitas Brutas
A9: Servicos prestados | B9: 0 | C9: 0 | D9: 0 | E9: 0 | F9: 0 | G9: 0 | H9: 0 | I9: 0 | J9: 0 | K9: 0 | L9: 0 | M9: 0 | N9: 0 | O9: =B9+C9+D9+E9+F9+G9+H9+I9+J9+K9+L9+M9+N9 -> 0 | P9: 1 | R9: =SUM(B9:E9) -> 0 | S9: =R9-O9 -> 0
A10: Locação de Equipamentos - 450 | B10: 0 | C10: 0 | D10: 0 | E10: 0 | F10: 0 | G10: 0 | H10: 0 | I10: 0 | J10: 0 | K10: 0 | L10: 0 | M10: 0 | N10: 0 | O10: =B10+C10+D10+E10+F10+G10+H10+I10+J10+K10+L10+M10+N10 -> 0 | R10: =SUM(B10:E10) -> 0 | S10: =R10-O10 -> 0
A11: Receitas Brutas Total... | B11: =SUM(B9:B10) -> 0 | C11: =SUM(C9:C10) -> 0 | D11: =SUM(D9:D10) -> 0 | E11: =SUM(E9:E10) -> 0 | F11: =SUM(F9:F10) -> 0 | G11: =SUM(G9:G10) -> 0 | H11: =SUM(H9:H10) -> 0 | I11: =SUM(I9:I10) -> 0 | ... O11: =SUM(O9:O10) -> 0 | P11: 1 | R11: =SUM(B11:E11) -> 0 | S11: =R11-O11 -> 0
R12: =SUM(B12:E12) -> 0 | S12: =R12-O12 -> 0
A13: Custos | R13: =SUM(B13:E13) -> 0 | S13: =R13-O13 -> 0
A14: Alimentação - 320 | B14: 60.28 | C14: 15.07 | D14: 15.07 | E14: 0 | F14: 0 | G14: 0 | H14: 0 | I14: 0 | J14: 0 | K14: 0 | L14: 0 | M14: 0 | N14: 0 | O14: =B14+C14+D14+E14+F14+G14+H14+I14+J14+K14+L14+M14+N14 -> 90.42 | R14: =SUM(B14:E14) -> 90.42 | S14: =R14-O14 -> 0
A15: Combustíveis - 322 | B15: 0 | C15: 0 | D15: 0 | E15: 0 | F15: 0 | G15: 0 | H15: 0 | I15: 0 | J15: 0 | K15: 0 | L15: 0 | M15: 0 | N15: 0 | O15: =B15+C15+D15+E15+F15+G15+H15+I15+J15+K15+L15+M15+N15 -> 0 | R15: =SUM(B15:E15) -> 0 | S15: =R15-O15 -> 0
A16: Despesa com Radio e Telefonia Celular | B16: 0 | C16: 0 | D16: 0 | E16: 0 | F16: 0 | G16: 0 | H16: 0 | I16: 0 | J16: 0 | K16: 0 | L16: 0 | M16: 0 | N16: 0 | O16: =B16+C16+D16+E16+F16+G16+H16+I16+J16+K16+L16+M16+N16 -> 0 | R16: =SUM(B16:E16) -> 0 | S16: =R16-O16 -> 0
A17: Equipamento de Segurança - EPIs - 360 | B17: 0 | C17: 0 | D17: 0 | E17: 0 | F17: 0 | G17: 0 | H17: 0 | I17: 0 | J17: 0 | K17: 0 | L17: 0 | M17: 0 | N17: 0 | O17: =B17+C17+D17+E17+F17+G17+H17+I17+J17+K17+L17+M17+N17 -> 0 | R17: =SUM(B17:E17) -> 0 | S17: =R17-O17 -> 0
A18: Ferias - 315 | B18: -1181.03 | C18: -312.12 | D18: -312.12 | E18: -312.12 | F18: 0 | G18: 0 | H18: 0 | I18: 0 | J18: 0 | K18: 0 | L18: 0 | M18: 0 | N18: 0 | O18: =B18+C18+D18+E18+F18+G18+H18+I18+J18+K18+L18+M18+N18 -> -2117.39 | R18: =SUM(B18:E18) -> -2117.39 | S18: =R18-O18 -> 0
A19: FGTS - 317 | B19: -788.2 | C19: -192.4 | D19: -192.4 | E19: -256.54 | F19: 0 | G19: 0 | H19: 0 | I19: 0 | J19: 0 | K19: 0 | L19: 0 | M19: 0 | N19: 0 | O19: =B19+C19+D19+E19+F19+G19+H19+I19+J19+K19+L19+M19+N19 -> -1429.54 | R19: =SUM(B19:E19) -> -1429.54 | S19: =R19-O19 -> 0
A20: Horas Extras - 499 | B20: -752.26 | C20: 0 | D20: 0 | E20: 0 | F20: 0 | G20: 0 | H20: 0 | I20: 0 | J20: 0 | K20: 0 | L20: 0 | M20: 0 | N20: 0 | O20: =B20+C20+D20+E20+F20+G20+H20+I20+J20+K20+L20+M20+N20 -> -752.26 | R20: =SUM(B20:E20) -> -752.26 | S20: =R20-O20 -> 0
A21: Indenizações e Aviso Prévio - 318 | B21: 0 | C21: 0 | D21: 0 | E21: 0 | F21: 0 | G21: 0 | H21: 0 | I21: 0 | J21: 0 | K21: 0 | L21: 0 | M21: 0 | N21: 0 | O21: =B21+C21+D21+E21+F21+G21+H21+I21+J21+K21+L21+M21+N21 -> 0 | R21: =SUM(B21:E21) -> 0 | S21: =R21-O21 -> 0
A22: Indenizações Trabalhistas Judiciais - 369 | B22: 0 | C22: 0 | D22: 0 | E22: 0 | F22: 0 | G22: 0 | H22: 0 | I22: 0 | J22: 0 | K22: 0 | L22: 0 | M22: 0 | N22: 0 | O22: =B22+C22+D22+E22+F22+G22+H22+I22+J22+K22+L22+M22+N22 -> 0 | R22: =SUM(B22:E22) -> 0 | S22: =R22-O22 -> 0
A23: INSS - 316 | B23: -867.05 | C23: -211.65 | D23: -211.65 | E23: -282.19 | F23: 0 | G23: 0 | H23: 0 | I23: 0 | J23: 0 | K23: 0 | L23: 0 | M23: 0 | N23: 0 | O23: =B23+C23+D23+E23+F23+G23+H23+I23+J23+K23+L23+M23+N23 -> -1572.54 | R23: =SUM(B23:E23) -> -1572.54 | S23: =R23-O23 -> 0
A24: Locação de Andaimes - 328 | B24: 0 | C24: 0 | D24: 0 | E24: 0 | F24: 0 | G24: 0 | H24: 0 | I24: 0 | J24: 0 | K24: 0 | L24: 0 | M24: 0 | N24: 0 | O24: =B24+C24+D24+E24+F24+G24+H24+I24+J24+K24+L24+M24+N24 -> 0 | R24: =SUM(B24:E24) -> 0 | S24: =R24-O24 -> 0
A25: Locação de Máqs, Ferramentas e Equipamentos - | B25: 0 | C25: 0 | D25: 0 | E25: 0 | F25: 0 | G25: 0 | H25: 0 | I25: 0 | J25: 0 | K25: 0 | L25: 0 | M25: 0 | N25: 0 | O25: =B25+C25+D25+E25+F25+G25+H25+I25+J25+K25+L25+M25+N25 -> 0 | R25: =SUM(B25:E25) -> 0 | S25: =R25-O25 -> 0
... A39: Confraternização de Funcionários | B39: 0 | C39: 0 | D39: 0 | E39: 0 | F39: 0 | G39: 0 | H39: 0 | I39: 0 | J39: 0 | K39: 0 | L39: 0 | M39: 0 | N39: 0 | O39: =B39+C39+D39+E39+F39+G39+H39+I39+J39+K39+L39+M39+N39 -> 0 | R39: =SUM(B39:E39) -> 0 | S39: =R39-O39 -> 0
A40: Custos Total... | B40: =SUM(B14:B39) -> -13925.89 | C40: =SUM(C14:C39) -> -3505.1 | D40: =SUM(D14:D39) -> -3571.8 | E40: =SUM(E14:E39) -> -1463.39 | F40: =SUM(F14:F39) -> 0 | G40: =SUM(G14:G39) -> 0 | H40: =SUM(H14:H39) -> 0 | I40: =SUM(I14:I39) -> 0 | ... O40: =SUM(O14:O39) -> -22466.18 | R40: =SUM(B40:E40) -> -22466.18 | S40: =R40-O40 -> 0
R41: =SUM(B41:E41) -> 0 | S41: =R41-O41 -> 0
A42: = Lucro/Prejuízo Bruto | B42: =B11+B40 -> -13925.89 | C42: =C11+C40 -> -3505.1 | D42: =D11+D40 -> -3571.8 | E42: =E11+E40 -> -1463.39 | F42: =F11+F40 -> 0 | G42: =G11+G40 -> 0 | H42: =H11+H40 -> 0 | I42: =I11+I40 -> 0 | ... N42: =N11+N40 -> 0 | O42: =B42+C42+D42+E42+F42+G42+H42+I42+J42+K42+L42+M42+N42 -> -22466.18 | R42: =SUM(B42:E42) -> -22466.18 | S42: =R42-O42 -> 0
R43: =SUM(B43:E43) -> 0 | S43: =R43-O43 -> 0
A44: (-) Impostos s/ Serviços - (13,15% s/ Faturamento) | B44: =-B9*13.15% -> 0 | C44: =-C9*13.15% -> 0 | D44: =-D9*13.15% -> 0 | E44: =-E9*13.15% -> 0 | F44: =-F9*13.15% -> 0 | G44: =-G9*13.15% -> 0 | H44: =-H9*13.15% -> 0 | I44: =-I9*13.15% -> 0 | ... N44: =-N9*13.15% -> 0 | O44: =B44+C44+D44+E44+F44+G44+H44+I44+J44+K44+L44+M44+N44 -> 0 | R44: =SUM(B44:E44) -> 0 | S44: =R44-O44 -> 0
R45: =SUM(B45:E45) -> 0 | S45: =R45-O45 -> 0
A46: (-) IRPJ e CSLL - (1,22% s/faturamento) | B46: =-B9*1.22% -> 0 | C46: =-C9*1.22% -> 0 | D46: =-D9*1.22% -> 0 | E46: =-E9*1.22% -> 0 | F46: =-F9*1.22% -> 0 | G46: =-G9*1.22% -> 0 | H46: =-H9*1.22% -> 0 | I46: =-I9*1.22% -> 0 | ... N46: =-N9*1.22% -> 0 | O46: =B46+C46+D46+E46+F46+G46+H46+I46+J46+K46+L46+M46+N46 -> 0 | R46: =SUM(B46:E46) -> 0 | S46: =R46-O46 -> 0
R47: =SUM(B47:E47) -> 0 | S47: =R47-O47 -> 0
A48: Total Desp Administrativas/Técnico - ( 5,56% Taxa Adm. Prevista) | B48: =B40*5.56% -> -774.27948 | C48: =C40*5.56% -> -194.88356 | D48: =D40*5.56% -> -198.59208 | E48: =E40*5.56% -> -81.364484 | F48: =F40*5.56% -> 0 | G48: =G40*5.56% -> 0 | H48: =H40*5.56% -> 0 | I48: =I40*5.56% -> 0 | ... N48: =N40*5.56% -> 0 | O48: =B48+C48+D48+E48+F48+G48+H48+I48+J48+K48+L48+M48+N48 -> -1249.1196 | R48: =SUM(B48:E48) -> -1249.1196 | S48: =R48-O48 -> 0
R49: =SUM(B49:E49) -> 0 | S49: =R49-O49 -> 0
A50: Total Despesas Financeiras -( 0,01% s/ Custo de Obras-média) | B50: =B40*0.01% -> -1.392589 | C50: =C40*0.01% -> -0.35051 | D50: =D40*0.01% -> -0.35718 | E50: =E40*0.01% -> -0.146339 | F50: =F40*0.01% -> 0 | G50: =G40*0.01% -> 0 | H50: =H40*0.01% -> 0 | I50: =I40*0.01% -> 0 | ... N50: =N40*0.01% -> 0 | O50: =B50+C50+D50+E50+F50+G50+H50+I50+J50+K50+L50+M50+N50 -> -2.246618 | R50: =SUM(B50:E50) -> -2.246618 | S50: =R50-O50 -> 0
R51: =SUM(B51:E51) -> 0 | S51: =R51-O51 -> 0
A52: LUCRO/PREJUIZO - LIQUIDO DA OBRA - 269 - | B52: =B42+B48+B50+B44+B46 -> -14701.562 | C52: =C42+C48+C50+C44+C46 -> -3700.3341 | D52: =D42+D48+D50+D44+D46 -> -3770.7493 | E52: =E42+E48+E50+E44+E46 -> -1544.9008 | F52: =F42+F48+F50+F44+F46 -> 0 | G52: =G42+G48+G50+G44+G46 -> 0 | H52: =H42+H48+H50+H44+H46 -> 0 | I52: =I42+I48+I50+I44+I46 -> 0 | ... N52: =N42+N48+N50+N44+N46 -> 0 | O52: =B52+C52+D52+E52+F52+G52+H52+I52+J52+K52+L52+M52+N52 -> -23717.546 | R52: =SUM(B52:E52) -> -23717.546 | S52: =R52-O52 -> 0
A54: NÚMERO DE FUNCIONÁRIOS - FINAL DO MÊS | C54: 1 | D54: 1 | E54: 1
P55: 45412
A56: Elaborado: INOV SOLUÇÃO EMPRESARIAL E CONTÁBIL LTDA
B57: =B11+B40+B44+B46+B48+B50 -> -14701.562 | C57: =C11+C40+C44+C46+C48+C50 -> -3700.3341 | D57: =D11+D40+D44+D46+D48+D50 -> -3770.7493 | E57: =E11+E40+E44+E46+E48+E50 -> -1544.9008 | F57: =F11+F40+F44+F46+F48+F50 -> 0 | G57: =G11+G40+G44+G46+G48+G50 -> 0 | H57: =H11+H40+H44+H46+H48+H50 -> 0 | I57: =I11+I40+I44+I46+I48+I50 -> 0 | ... O57: =O11+O40+O44+O46+O48+O50 -> -23717.546
B59: =B52-B57 -> 0 | C59: =C52-C57 -> 0 | D59: =D52-D57 -> 0 | E59: =E52-E57 -> 0 | F59: =F52-F57 -> 0 | G59: =G52-G57 -> 0 | H59: =H52-H57 -> 0 | I59: =I52-I57 -> 0 | ... O59: =O52-O57 -> 0

Sheet OBRA 270
A1: DEMONSTRAÇÃO DO RESULTADO APURADO
A3: OBRA 270 - PÇ LINDENBERG C. MONZA - ADOLPHO LINDENBERG
A5: OBRA EM ANDAMENTO
B8: Agos a Dez/2023 | C8: Jan a Dez/2024 | D8: Janeiro/2024 | E8: Fevereiro/2024 | F8: Março/2024 | G8: Abril/2024 | H8: Maio/2024 | I8: Junho/2024 | J8: Julho/2024 | K8: Agosto/2024 | L8: Setembro/2024 | M8: Outubro/2024 | N8: Novembro/2024 | O8: Dezembro/2024 | P8: Acumulado | Q8: % S/FAT
A9: Receitas Brutas
A10: Servicos prestados | B10: 169151.39 | C10: 57807 | D10: 0 | E10: 0 | F10: 0 | G10: 0 | H10: 0 | I10: 0 | J10: 0 | K10: 0 | L10: 0 | M10: 0 | N10: 0 | O10: 0 | P10: =B10+C10+D10+E10+F10+G10+H10+I10+J10+K10+L10+M10+N10+O10 -> 226958.39 | Q10: 1 | S10: =SUM(B10:O10) -> 226958.39 | T10: =P10-S10 -> 0
A11: Locação de Equipamentos - 450 | B11: 0 | C11: =SUM(D11:O11) -> 0 | D11: 0 | E11: 0 | F11: 0 | G11: 0 | H11: 0 | I11: 0 | J11: 0 | K11: 0 | L11: 0 | M11: 0 | N11: 0 | O11: 0 | P11: =B11+C11+D11+E11+F11+G11+H11+I11+J11+K11+L11+M11+N11+O11 -> 0 | S11: =SUM(B11:O11) -> 0 | T11: =P11-S11 -> 0
A12: Receitas Brutas Total... | B12: =SUM(B10:B11) -> 169151.39 | C12: =SUM(C10:C11) -> 57807 | D12: =SUM(D10:D11) -> 0 | E12: =SUM(E10:E11) -> 0 | F12: =SUM(F10:F11) -> 0 | G12: =SUM(G10:G11) -> 0 | H12: =SUM(H10:H11) -> 0 | I12: =SUM(I10:I11) -> 0 | ... P12: =SUM(P10:P11) -> 226958.39 | Q12: 1 | S12: =SUM(B12:O12) -> 226958.39 | T12: =P12-S12 -> 0
S13: =SUM(B13:O13) -> 0 | T13: =P13-S13 -> 0
A14: Custos | S14: =SUM(B14:O14) -> 0 | T14: =P14-S14 -> 0
A15: Alimentação - 320 | B15: -6741.84 | C15: -1899.68 | D15: 0 | E15: 0 | F15: 0 | G15: 0 | H15: 0 | I15: 0 | J15: 0 | K15: 0 | L15: 0 | M15: 0 | N15: 0 | O15: 0 | P15: =B15+C15+D15+E15+F15+G15+H15+I15+J15+K15+L15+M15+N15+O15 -> -8641.52 | Q15: =-P15/$P$12 -> 0.038075349 | S15: =SUM(B15:O15) -> -8641.52 | T15: =P15-S15 -> 0
A16: Combustíveis - 322 | B16: 0 | C16: =SUM(D16:O16) -> 0 | D16: 0 | E16: 0 | F16: 0 | G16: 0 | H16: 0 | I16: 0 | J16: 0 | K16: 0 | L16: 0 | M16: 0 | N16: 0 | O16: 0 | P16: =B16+C16+D16+E16+F16+G16+H16+I16+J16+K16+L16+M16+N16+O16 -> 0 | Q16: =-P16/$P$12 -> 0 | S16: =SUM(B16:O16) -> 0 | T16: =P16-S16 -> 0
A17: Despesa com Radio e Telefonia Celular | B17: 0 | C17: =SUM(D17:O17) -> 0 | D17: 0 | E17: 0 | F17: 0 | G17: 0 | H17: 0 | I17: 0 | J17: 0 | K17: 0 | L17: 0 | M17: 0 | N17: 0 | O17: 0 | P17: =B17+C17+D17+E17+F17+G17+H17+I17+J17+K17+L17+M17+N17+O17 -> 0 | Q17: =-P17/$P$12 -> 0 | S17: =SUM(B17:O17) -> 0 | T17: =P17-S17 -> 0
A18: Equipamento de Segurança - EPIs - 360 | B18: -76.77 | C18: -609.1 | D18: 0 | E18: 0 | F18: 0 | G18: 0 | H18: 0 | I18: 0 | J18: 0 | K18: 0 | L18: 0 | M18: 0 | N18: 0 | O18: 0 | P18: =B18+C18+D18+E18+F18+G18+H18+I18+J18+K18+L18+M18+N18+O18 -> -685.87 | Q18: =-P18/$P$12 -> 0.0030220077 | S18: =SUM(B18:O18) -> -685.87 | T18: =P18-S18 -> 0
A19: Ferias - 315 | B19: -5552.07 | C19: -2435.95 | D19: 0 | E19: 0 | F19: 0 | G19: 0 | H19: 0 | I19: 0 | J19: 0 | K19: 0 | L19: 0 | M19: 0 | N19: 0 | O19: 0 | P19: =B19+C19+D19+E19+F19+G19+H19+I19+J19+K19+L19+M19+N19+O19 -> -7988.02 | Q19: =-P19/$P$12 -> 0.035195967 | S19: =SUM(B19:O19) -> -7988.02 | T19: =P19-S19 -> 0
A20: FGTS - 317 | B20: -3141.8 | C20: -1519.87 | D20: 0 | E20: 0 | F20: 0 | G20: 0 | H20: 0 | I20: 0 | J20: 0 | K20: 0 | L20: 0 | M20: 0 | N20: 0 | O20: 0 | P20: =B20+C20+D20+E20+F20+G20+H20+I20+J20+K20+L20+M20+N20+O20 -> -4661.67 | Q20: =-P20/$P$12 -> 0.020539756 | S20: =SUM(B20:O20) -> -4661.67 | T20: =P20-S20 -> 0
A21: Horas Extras - 499 | B21: -250.8 | C21: -219.26 | D21: 0 | E21: 0 | F21: 0 | G21: 0 | H21: 0 | I21: 0 | J21: 0 | K21: 0 | L21: 0 | M21: 0 | N21: 0 | O21: 0 | P21: =B21+C21+D21+E21+F21+G21+H21+I21+J21+K21+L21+M21+N21+O21 -> -470.06 | Q21: =-P21/$P$12 -> 0.0020711285 | S21: =SUM(B21:O21) -> -470.06 | T21: =P21-S21 -> 0
A22: Indenizações e Aviso Prévio - 318 | B22: 0 | C22: =SUM(D22:O22) -> 0 | D22: 0 | E22: 0 | F22: 0 | G22: 0 | H22: 0 | I22: 0 | J22: 0 | K22: 0 | L22: 0 | M22: 0 | N22: 0 | O22: 0 | P22: =B22+C22+D22+E22+F22+G22+H22+I22+J22+K22+L22+M22+N22+O22 -> 0 | Q22: =-P22/$P$12 -> 0 | S22: =SUM(B22:O22) -> 0 | T22: =P22-S22 -> 0
A23: Indenizações Trabalhistas Judiciais - 369 | B23: -3455.99 | C23: =SUM(D23:O23) -> 0 | D23: 0 | E23: 0 | F23: 0 | G23: 0 | H23: 0 | I23: 0 | J23: 0 | K23: 0 | L23: 0 | M23: 0 | N23: 0 | O23: 0 | P23: =B23+C23+D23+E23+F23+G23+H23+I23+J23+K23+L23+M23+N23+O23 -> -3455.99 | Q23: =-P23/$P$12 -> 0.015227417 | S23: =SUM(B23:O23) -> -3455.99 | T23: =P23-S23 -> 0
A24: INSS - 316 | B24: 0 | C24: -1707.98 | D24: 0 | E24: 0 | F24: 0 | G24: 0 | H24: 0 | I24: 0 | J24: 0 | K24: 0 | L24: 0 | M24: 0 | N24: 0 | O24: 0 | P24: =B24+C24+D24+E24+F24+G24+H24+I24+J24+K24+L24+M24+N24+O24 -> -1707.98 | Q24: =-P24/$P$12 -> 0.0075255204 | S24: =SUM(B24:O24) -> -1707.98 | T24: =P24-S24 -> 0
A25: Locação de Andaimes - 328 | B25: 0 | C25: =SUM(D25:O25) -> 0 | D25: 0 | E25: 0 | F25: 0 | G25: 0 | H25: 0 | I25: 0 | J25: 0 | K25: 0 | L25: 0 | M25: 0 | N25: 0 | O25: 0 | P25: =B25+C25+D25+E25+F25+G25+H25+I25+J25+K25+L25+M25+N25+O25 -> 0 | Q25: =-P25/$P$12 -> 0 | S25: =SUM(B25:O25) -> 0 | T25: =P25-S25 -> 0
A26: Locação de Máqs, Ferramentas e Equipamentos - | B26: 0 | C26: =SUM(D26:O26) -> 0 | D26: 0 | E26: 0 | F26: 0 | G26: 0 | H26: 0 | I26: 0 | J26: 0 | K26: 0 | L26: 0 | M26: 0 | N26: 0 | O26: 0 | P26: =B26+C26+D26+E26+F26+G26+H26+I26+J26+K26+L26+M26+N26+O26 -> 0 | Q26: =-P26/$P$12 -> 0 | S26: =SUM(B26:O26) -> 0 | T26: =P26-S26 -> 0
A27: Manutenção de Equipamento - 394 | B27: 0 | C27: =SUM(D27:O27) -> 0 | D27: 0 | E27: 0 | F27: 0 | G27: 0 | H27: 0 | I27: 0 | J27: 0 | K27: 0 | L27: 0 | M27: 0 | N27: 0 | O27: 0 | P27: =B27+C27+D27+E27+F27+G27+H27+I27+J27+K27+L27+M27+N27+O27 -> 0 | Q27: =-P27/$P$12 -> 0 | S27: =SUM(B27:O27) -> 0 | T27: =P27-S27 -> 0
A28: Manutenção de Veículos - 510 | B28: 0 | C28: =SUM(D28:O28) -> 0 | D28: 0 | E28: 0 | F28: 0 | G28: 0 | H28: 0 | I28: 0 | J28: 0 | K28: 0 | L28: 0 | M28: 0 | N28: 0 | O28: 0 | P28: =B28+C28+D28+E28+F28+G28+H28+I28+J28+K28+L28+M28+N28+O28 -> 0 | Q28: =-P28/$P$12 -> 0 | S28: =SUM(B28:O28) -> 0 | T28: =P28-S28 -> 0
A29: Medicina Ocupacional e Assist médica - 3 | B29: -270 | C29: -45 | D29: 0 | E29: 0 | F29: 0 | G29: 0 | H29: 0 | I29: 0 | J29: 0 | K29: 0 | L29: 0 | M29: 0 | N29: 0 | O29: 0 | P29: =B29+C29+D29+E29+F29+G29+H29+I29+J29+K29+L29+M29+N29+O29 -> -315 | Q29: =-P29/$P$12 -> 0.0013879196 | S29: =SUM(B29:O29) -> -315 | T29: =P29-S29 -> 0
A30: Móveis Não Imobilizado - 364 | B30: 0 | C30: =SUM(D30:O30) -> 0 | D30: 0 | E30: 0 | F30: 0 | G30: 0 | H30: 0 | I30: 0 | J30: 0 | K30: 0 | L30: 0 | M30: 0 | N30: 0 | O30: 0 | P30: =B30+C30+D30+E30+F30+G30+H30+I30+J30+K30+L30+M30+N30+O30 -> 0 | Q30: =-P30/$P$12 -> 0 | S30: =SUM(B30:O30) -> 0 | T30: =P30-S30 -> 0
A31: Peças, Ferramentas e Acessórios - 361 | B31: -185.5 | C31: 0 | D31: 0 | E31: 0 | F31: 0 | G31: 0 | H31: 0 | I31: 0 | J31: 0 | K31: 0 | L31: 0 | M31: 0 | N31: 0 | O31: 0 | P31: =B31+C31+D31+E31+F31+G31+H31+I31+J31+K31+L31+M31+N31+O31 -> -185.5 | Q31: =-P31/$P$12 -> 0.00081733044 | S31: =SUM(B31:O31) -> -185.5 | T31: =P31-S31 -> 0
A32: Premios e Gratificacoes - 313 | B32: -10832 | C32: -4179 | D32: 0 | E32: 0 | F32: 0 | G32: 0 | H32: 0 | I32: 0 | J32: 0 | K32: 0 | L32: 0 | M32: 0 | N32: 0 | O32: 0 | P32: =B32+C32+D32+E32+F32+G32+H32+I32+J32+K32+L32+M32+N32+O32 -> -15011 | Q32: =-P32/$P$12 -> 0.066139877 | S32: =SUM(B32:O32) -> -15011 | T32: =P32-S32 -> 0
A33: Salarios e Ordenados - 311 | B33: -35386.11 | C33: -18241.45 | D33: 0 | E33: 0 | F33: 0 | G33: 0 | H33: 0 | I33: 0 | J33: 0 | K33: 0 | L33: 0 | M33: 0 | N33: 0 | O33: 0 | P33: =B33+C33+D33+E33+F33+G33+H33+I33+J33+K33+L33+M33+N33+O33 -> -53627.56 | Q33: =-P33/$P$12 -> 0.23628807 | S33: =SUM(B33:O33) -> -53627.56 | T33: =P33-S33 -> 0
A34: Serviços de Terceiros - 324 | B34: 0 | C34: -24080.32 | D34: 0 | E34: 0 | F34: 0 | G34: 0 | H34: 0 | I34: 0 | J34: 0 | K34: 0 | L34: 0 | M34: 0 | N34: 0 | O34: 0 | P34: =B34+C34+D34+E34+F34+G34+H34+I34+J34+K34+L34+M34+N34+O34 -> -24080.32 | Q34: =-P34/$P$12 -> 0.10610015 | S34: =SUM(B34:O34) -> -24080.32 | T34: =P34-S34 -> 0
A35: Seguro Riscos Execução de Serv. Trab. | B35: 0 | C35: =SUM(D35:O35) -> 0 | D35: 0 | E35: 0 | F35: 0 | G35: 0 | H35: 0 | I35: 0 | J35: 0 | K35: 0 | L35: 0 | M35: 0 | N35: 0 | O35: 0 | P35: =B35+C35+D35+E35+F35+G35+H35+I35+J35+K35+L35+M35+N35+O35 -> 0 | Q35: =-P35/$P$12 -> 0 | S35: =SUM(B35:O35) -> 0 | T35: =P35-S35 -> 0
A36: Uniformes - 425 | B36: -357.92 | C36: -442.75 | D36: 0 | E36: 0 | F36: 0 | G36: 0 | H36: 0 | I36: 0 | J36: 0 | K36: 0 | L36: 0 | M36: 0 | N36: 0 | O36: 0 | P36: =B36+C36+D36+E36+F36+G36+H36+I36+J36+K36+L36+M36+N36+O36 -> -800.67 | Q36: =-P36/$P$12 -> 0.0035278273 | S36: =SUM(B36:O36) -> -800.67 | T36: =P36-S36 -> 0
A37: Vale Transporte e Condução - 321 | B37: -1625.5 | C37: -2112.79 | D37: 0 | E37: 0 | F37: 0 | G37: 0 | H37: 0 | I37: 0 | J37: 0 | K37: 0 | L37: 0 | M37: 0 | N37: 0 | O37: 0 | P37: =B37+C37+D37+E37+F37+G37+H37+I37+J37+K37+L37+M37+N37+O37 -> -3738.29 | Q37: =-P37/$P$12 -> 0.016471257 | S37: =SUM(B37:O37) -> -3738.29 | T37: =P37-S37 -> 0
A38: 13º Salario - 314 | B38: -4392.57 | C38: -1826.97 | D38: 0 | E38: 0 | F38: 0 | G38: 0 | H38: 0 | I38: 0 | J38: 0 | K38: 0 | L38: 0 | M38: 0 | N38: 0 | O38: 0 | P38: =B38+C38+D38+E38+F38+G38+H38+I38+J38+K38+L38+M38+N38+O38 -> -6219.54 | Q38: =-P38/$P$12 -> 0.027403878 | S38: =SUM(B38:O38) -> -6219.54 | T38: =P38-S38 -> 0
A39: Cursos e treinamentos | B39: 0 | C39: =SUM(D39:O39) -> 0 | D39: 0 | E39: 0 | F39: 0 | G39: 0 | H39: 0 | I39: 0 | J39: 0 | K39: 0 | L39: 0 | M39: 0 | N39: 0 | O39: 0 | P39: =B39+C39+D39+E39+F39+G39+H39+I39+J39+K39+L39+M39+N39+O39 -> 0 | Q39: =-P39/$P$12 -> 0 | S39: =SUM(B39:O39) -> 0 | T39: =P39-S39 -> 0
A40: Confraternização de Funcionários | B40: 0 | C40: =SUM(D40:O40) -> 0 | D40: 0 | E40: 0 | F40: 0 | G40: 0 | H40: 0 | I40: 0 | J40: 0 | K40: 0 | L40: 0 | M40: 0 | N40: 0 | O40: 0 | P40: =B40+C40+D40+E40+F40+G40+H40+I40+J40+K40+L40+M40+N40+O40 -> 0 | Q40: =-P40/$P$12 -> 0 | S40: =SUM(B40:O40) -> 0 | T40: =P40-S40 -> 0
A41: Custos Total... | B41: =SUM(B15:B40) -> -72268.87 | C41: =SUM(C15:C40) -> -59320.12 | D41: =SUM(D15:D40) -> 0 | E41: =SUM(E15:E40) -> 0 | F41: =SUM(F15:F40) -> 0 | G41: =SUM(G15:G40) -> 0 | H41: =SUM(H15:H40) -> 0 | I41: =SUM(I15:I40) -> 0 | ... P41: =SUM(P15:P40) -> -131588.99 | Q41: =-P41/$P$12 -> 0.57979346 | S41: =SUM(B41:O41) -> -131588.99 | T41: =P41-S41 -> 0
S42: =SUM(B42:O42) -> 0 | T42: =P42-S42 -> 0
A43: = Lucro/Prejuízo Bruto | B43: =B12+B41 -> 96882.52 | C43: =C12+C41 -> -1513.12 | D43: =D12+D41 -> 0 | E43: =E12+E41 -> 0 | F43: =F12+F41 -> 0 | G43: =G12+G41 -> 0 | H43: =H12+H41 -> 0 | I43: =I12+I41 -> 0 | ... O43: =O12+O41 -> 0 | P43: =B43+C43+D43+E43+F43+G43+H43+I43+J43+K43+L43+M43+N43+O43 -> 95369.4 | Q43: =P43/$P$12 -> 0.42020654 | S43: =SUM(B43:O43) -> 95369.4 | T43: =P43-S43 -> 0
J44: =SUM(J12,J41) -> 0 | K44: =SUM(K12,K41) -> 0 | L44: =SUM(L12,L41) -> 0 | M44: =SUM(M12,M41) -> 0 | N44: =SUM(N12,N41) -> 0 | O44: =SUM(O12,O41) -> 0 | S44: =SUM(B44:O44) -> 0
A45: (-) Impostos s/ Serviços - (13,15% s/ Faturamento) | B45: =-B10*13.15% -> -22243.408 | C45: =-C10*13.15% -> -7601.6205 | D45: =-D10*13.15% -> 0 | E45: =-E10*13.15% -> 0 | F45: =-F10*13.15% -> 0 | G45: =-G10*13.15% -> 0 | H45: =-H10*13.15% -> 0 | I45: =-I10*13.15% -> 0 | ... O45: =-O10*13.15% -> 0 | P45: =B45+C45+D45+E45+F45+G45+H45+I45+J45+K45+L45+M45+N45+O45 -> -29845.028 | Q45: =-P45/$P$12 -> 0.1315 | S45: =SUM(B45:O45) -> -29845.028 | T45: =P45-S45 -> 0
S46: =SUM(B46:O46) -> 0 | T46: =P46-S46 -> 0
A47: (-) IRPJ e CSLL - (1,22% s/faturamento) | B47: =-B10*1.22% -> -2063.647 | C47: =-C10*1.22% -> -705.2454 | D47: =-D10*1.22% -> 0 | E47: =-E10*1.22% -> 0 | F47: =-F10*1.22% -> 0 | G47: =-G10*1.22% -> 0 | H47: =-H10*1.22% -> 0 | I47: =-I10*1.22% -> 0 | ... O47: =-O10*1.22% -> 0 | P47: =B47+C47+D47+E47+F47+G47+H47+I47+J47+K47+L47+M47+N47+O47 -> -2768.8924 | Q47: =-P47/$P$12 -> 0.0122 | S47: =SUM(B47:O47) -> -2768.8924 | T47: =P47-S47 -> 0
S48: =SUM(B48:O48) -> 0 | T48: =P48-S48 -> 0
A49: Total Desp Administrativas/Técnico - ( 5,56% Taxa Adm. Prevista) | B49: =B41*5.56% -> -4018.1492 | C49: =C41*5.56% -> -3298.1987 | D49: =D41*5.56% -> 0 | E49: =E41*5.56% -> 0 | F49: =F41*5.56% -> 0 | G49: =G41*5.56% -> 0 | H49: =H41*5.56% -> 0 | I49: =I41*5.56% -> 0 | ... O49: =O41*5.56% -> 0 | P49: =B49+C49+D49+E49+F49+G49+H49+I49+J49+K49+L49+M49+N49+O49 -> -7316.3478 | Q49: =-P49/$P$12 -> 0.032236516 | S49: =SUM(B49:O49) -> -7316.3478 | T49: =P49-S49 -> 0
S50: =SUM(B50:O50) -> 0 | T50: =P50-S50 -> 0
A51: Total Despesas Financeiras -( 0,01% s/ Custo de Obras-média) | B51: =B41*0.01% -> -7.226887 | C51: =C41*0.01% -> -5.932012 | D51: =D41*0.01% -> 0 | E51: =E41*0.01% -> 0 | F51: =F41*0.01% -> 0 | G51: =G41*0.01% -> 0 | H51: =H41*0.01% -> 0 | I51: =I41*0.01% -> 0 | ... O51: =O41*0.01% -> 0 | P51: =B51+C51+D51+E51+F51+G51+H51+I51+J51+K51+L51+M51+N51+O51 -> -13.158899 | Q51: =-P51/$P$12 -> 5.7979346e-05 | S51: =SUM(B51:O51) -> -13.158899 | T51: =P51-S51 -> 0
S52: =SUM(B52:O52) -> 0 | T52: =P52-S52 -> 0
A53: LUCRO/PREJUIZO - LIQUIDO DA OBRA - 270 - | B53: =B43+B49+B51+B45+B47 -> 68550.089 | C53: =C43+C49+C51+C45+C47 -> -13124.117 | D53: =D43+D49+D51+D45+D47 -> 0 | E53: =E43+E49+E51+E45+E47 -> 0 | F53: =F43+F49+F51+F45+F47 -> 0 | G53: =G43+G49+G51+G45+G47 -> 0 | H53: =H43+H49+H51+H45+H47 -> 0 | I53: =I43+I49+I51+I45+I47 -> 0 | ... O53: =O43+O49+O51+O45+O47 -> 0 | P53: =B53+C53+D53+E53+F53+G53+H53+I53+J53+K53+L53+M53+N53+O53 -> 55425.973 | Q53: =P53/$P$12 -> 0.24421205 | S53: =SUM(B53:O53) -> 55425.973 | T53: =P53-S53 -> 0
A55: NÚMERO DE FUNCIONÁRIOS - FINAL DO MÊS
A57: Elaborado: INOV SOLUÇÃO EMPRESARIAL E CONTÁBIL LTDA | Q57: 45688
B58: =B12+B41+B45+B47+B49+B51 -> 68550.089 | C58: =C12+C41+C45+C47+C49+C51 -> -13124.117 | D58: =D12+D41+D45+D47+D49+D51 -> 0 | E58: =E12+E41+E45+E47+E49+E51 -> 0 | F58: =F12+F41+F45+F47+F49+F51 -> 0 | G58: =G12+G41+G45+G47+G49+G51 -> 0 | H58: =H12+H41+H45+H47+H49+H51 -> 0 | I58: =I12+I41+I45+I47+I49+I51 -> 0 | ... P58: =P12+P41+P45+P47+P49+P51 -> 55425.973
B60: =B53-B58 -> 0 | C60: =C53-C58 -> 0 | D60: =D53-D58 -> 0 | E60: =E53-E58 -> 0 | F60: =F53-F58 -> 0 | G60: =G53-G58 -> 0 | H60: =H53-H58 -> 0 | I60: =I53-I58 -> 0 | ... P60: =P53-P58 -> 0

Sheet OBRA 274
A1: BELA NOVA CONSTRUTORA LTDA
A3: DEMONSTRAÇÃO DO RESULTADO APURADO
A5: OBRA 274 - INFINITY IBM - EZTEC
A7: OBRA EM ANDAMENTO
B10: Agos a Dez/2022 | C10: Jan a Dez/2023 | D10: Jan a Dez/2024 | E10: Jan a Dez/2025 | F10: Janeiro/2026 | G10: Fevereiro/2026 | H10: Março/2026 | I10: Abril/2026 | J10: Maio/2026 | K10: Junho/2026 | L10: Julho/2026 | M10: Agosto/2026 | N10: Setembro/2026 | O10: Outubro/2026 | P10: Novembro/2026 | Q10: Dezembro/2026 | R10: Acumulado | S10: % S/FAT | W10: 2025
A11: Receitas Brutas
A12: Servicos prestados | B12: 95153.94 | C12: =1095952.49-B12 -> 1000798.6 | D12: 4628367.4 | E12: 3617151 | F12: 120000 | G12: 0 | H12: 30000 | I12: 0 | J12: 0 | K12: 30000 | L12: 0 | M12: 0 | N12: 0 | O12: 0 | P12: 0 | Q12: 0 | R12: =SUM(B12:Q12) -> 9521471 | S12: 1 | U12: =SUM(B12:Q12) -> 9521471 | V12: =R12-U12 -> 0 | W12: =R12-B12-C12-D12 -> 3797151
A13: Locação de Equipamentos - 450 | B13: 0 | C13: 0 | E13: 0 | F13: 0 | G13: 0 | H13: 0 | I13: 0 | J13: 0 | K13: 0 | L13: 0 | M13: 0 | N13: 0 | O13: 0 | P13: 0 | Q13: 0 | R13: =SUM(B13:Q13) -> 0 | U13: =SUM(B13:Q13) -> 0 | V13: =R13-U13 -> 0 | W13: =R13-B13-C13-D13 -> 0
A14: Receitas Brutas Total... | B14: =B12+B13 -> 95153.94 | C14: =C12+C13 -> 1000798.6 | D14: =D12+D13 -> 4628367.4 | E14: =E12+E13 -> 3617151 | F14: =F12+F13 -> 120000 | G14: =G12+G13 -> 0 | H14: =H12+H13 -> 30000 | I14: =SUM(I12:I13) -> 0 | J14: =SUM(J12:J13) -> 0 | K14: =SUM(K12:K13) -> 30000 | L14: =SUM(L12:L13) -> 0 | M14: =SUM(M12:M13) -> 0 | N14: =SUM(N12:N13) -> 0 | O14: =SUM(O12:O13) -> 0 | P14: =SUM(P12:P13) -> 0 | ... R14: =SUM(R12:R13) -> 9521471 | S14: 1 | U14: =SUM(B14:Q14) -> 9521471 | V14: =R14-U14 -> 0 | W14: =R14-B14-C14-D14 -> 3797151
U15: =SUM(B15:Q15) -> 0 | V15: =R15-U15 -> 0 | W15: =R15-B15-C15-D15 -> 0
A16: Custos | U16: =SUM(B16:Q16) -> 0 | V16: =R16-U16 -> 0 | W16: =R16-B16-C16-D16 -> 0
A17: Alimentação - 320 | B17: -9460.58 | C17: =-111112.44-B17 -> -101651.86 | D17: -218731.13 | E17: -206940.59 | F17: -7171.55 | G17: -9008.2 | H17: -5712.57 | I17: -5351.79 | J17: -3329.6 | K17: -2152.88 | L17: 0 | M17: 0 | N17: 0 | O17: 0 | P17: 0 | Q17: 0 | R17: =SUM(B17:Q17) -> -569510.75 | S17: =-R17/$R$14 -> 0.059813316 | U17: =SUM(B17:Q17) -> -569510.75 | V17: =R17-U17 -> 0 | W17: =R17-B17-C17-D17 -> -239667.18
A18: Combustíveis - 322 | B18: -176.92 | C18: =-176.92-B18 -> 0 | D18: 0 | E18: 0 | F18: 0 | G18: 0 | H18: 0 | I18: 0 | J18: 0 | K18: 0 | L18: 0 | M18: 0 | N18: 0 | O18: 0 | P18: 0 | Q18: 0 | R18: =SUM(B18:Q18) -> -176.92 | S18: =-R18/$R$14 -> 1.8581163e-05 | U18: =SUM(B18:Q18) -> -176.92 | V18: =R18-U18 -> 0 | W18: =R18-B18-C18-D18 -> 0
A19: Despesa com Radio e Telefonia Celular | B19: -117 | C19: =-1282-B19 -> -1165 | D19: -3067.2 | E19: -3888 | F19: -120 | G19: -72 | H19: -72 | I19: -72 | J19: -72 | K19: -45.6 | L19: 0 | M19: 0 | N19: 0 | O19: 0 | P19: 0 | Q19: 0 | R19: =SUM(B19:Q19) -> -8690.8 | S19: =-R19/$R$14 -> 0.00091275813 | U19: =SUM(B19:Q19) -> -8690.8 | V19: =R19-U19 -> 0 | W19: =R19-B19-C19-D19 -> -4341.6
A20: Equipamento de Segurança - EPIs - 360 | B20: -2696.67 | C20: =-5299.1-B20 -> -2602.43 | D20: -10055.29 | E20: -2771.34 | F20: -302.63 | G20: 0 | H20: =-1.73 -> -1.73 | I20: 0 | J20: 0 | K20: 0 | L20: 0 | M20: 0 | N20: 0 | O20: 0 | P20: 0 | Q20: 0 | R20: =SUM(B20:Q20) -> -18430.09 | S20: =-R20/$R$14 -> 0.0019356347 | U20: =SUM(B20:Q20) -> -18430.09 | V20: =R20-U20 -> 0 | W20: =R20-B20-C20-D20 -> -3075.7
A21: Ferias - 315 | B21: -5642.82 | C21: =-49752.51-B21 -> -44109.69 | D21: -94490.4 | E21: -66933.69 | F21: -2424.36 | G21: -1385.35 | H21: -1039.01 | I21: -1039.01 | J21: -728.35 | K21: 0 | L21: 0 | M21: 0 | N21: 0 | O21: 0 | P21: 0 | Q21: 0 | R21: =SUM(B21:Q21) -> -217792.68 | S21: =-R21/$R$14 -> 0.022873848 | U21: =SUM(B21:Q21) -> -217792.68 | V21: =R21-U21 -> 0 | W21: =R21-B21-C21-D21 -> -73549.77
A22: FGTS - 317 | B22: -3434.75 | C22: =-31943.18-B22 -> -28508.43 | D22: -64516.12 | E22: -57242.15 | F22: -4297.78 | G22: -5106.34 | H22: -1363.09 | I22: -683.66 | J22: -488.61 | K22: 0 | L22: 0 | M22: 0 | N22: 0 | O22: 0 | P22: 0 | Q22: 0 | R22: =SUM(B22:Q22) -> -165640.93 | S22: =-R22/$R$14 -> 0.017396569 | U22: =SUM(B22:Q22) -> -165640.93 | V22: =R22-U22 -> 0 | W22: =R22-B22-C22-D22 -> -69181.63
A23: Horas Extras - 499 | B23: -3249.13 | C23: =-36025.16-B23 -> -32776.03 | D23: -78523.44 | E23: -59425.89 | F23: -1067.69 | G23: -1975.22 | H23: -1928.65 | I23: -906.78 | J23: -503.86 | K23: 0 | L23: 0 | M23: 0 | N23: 0 | O23: 0 | P23: 0 | Q23: 0 | R23: =SUM(B23:Q23) -> -180356.69 | S23: =-R23/$R$14 -> 0.018942104 | U23: =SUM(B23:Q23) -> -180356.69 | V23: =R23-U23 -> 0 | W23: =R23-B23-C23-D23 -> -65808.09
A24: Indenizações e Aviso Prévio - 318 | B24: 1877 | C24: =6315.01-B24 -> 4438.01 | D24: 0 | E24: -6206.32 | F24: -2664.75 | G24: 0 | H24: 0 | I24: 0 | J24: 0 | K24: 0 | L24: 0 | M24: 0 | N24: 0 | O24: 0 | P24: 0 | Q24: 0 | R24: =SUM(B24:Q24) -> -2556.06 | S24: =-R24/$R$14 -> 0.00026845222 | U24: =SUM(B24:Q24) -> -2556.06 | V24: =R24-U24 -> 0 | W24: =R24-B24-C24-D24 -> -8871.07
A25: Indenizações Trabalhistas Judiciais - 369 | B25: 0 | C25: =0-B25 -> 0 | D25: -503.84 | E25: -2689.89 | F25: 0 | G25: 0 | H25: 0 | I25: 0 | J25: 0 | K25: 0 | L25: 0 | M25: 0 | N25: 0 | O25: 0 | P25: 0 | Q25: 0 | R25: =SUM(B25:Q25) -> -3193.73 | S25: =-R25/$R$14 -> 0.00033542401 | U25: =SUM(B25:Q25) -> -3193.73 | V25: =R25-U25 -> 0 | W25: =R25-B25-C25-D25 -> -2689.89
A26: INSS - 316 | B26: -4404.78 | C26: =-37296.65-B26 -> -32891.87 | D26: -72140.85 | E26: -85273.83 | F26: -6575.95 | G26: -3681.66 | H26: -3352.29 | I26: -1522.3 | J26: -1127.13 | K26: 0 | L26: 0 | M26: 0 | N26: 0 | O26: 0 | P26: 0 | Q26: 0 | R26: =SUM(B26:Q26) -> -210970.66 | S26: =-R26/$R$14 -> 0.02215736 | U26: =SUM(B26:Q26) -> -210970.66 | V26: =R26-U26 -> 0 | W26: =R26-B26-C26-D26 -> -101533.16
A27: Locação de Andaimes - 328 | B27: 0 | C27: =0-B27 -> 0 | D27: -12088.1 | E27: -17475.96 | F27: 0 | G27: 0 | H27: 0 | I27: 0 | J27: 0 | K27: 0 | L27: 0 | M27: 0 | N27: 0 | O27: 0 | P27: 0 | Q27: 0 | R27: =SUM(B27:Q27) -> -29564.06 | S27: =-R27/$R$14 -> 0.0031049887 | U27: =SUM(B27:Q27) -> -29564.06 | V27: =R27-U27 -> 0 | W27: =R27-B27-C27-D27 -> -17475.96
A28: Locação de Máqs, Ferramentas e Equipamentos - | B28: -8219.8 | C28: =-36060.63-B28 -> -27840.83 | D28: -67139.23 | E28: -66798.92 | F28: -3989 | G28: -4569 | H28: -1140.12 | I28: -4859.49 | J28: -3185.26 | K28: -376.7 | L28: 0 | M28: 0 | N28: 0 | O28: 0 | P28: 0 | Q28: 0 | R28: =SUM(B28:Q28) -> -188118.35 | S28: =-R28/$R$14 -> 0.019757278 | U28: =SUM(B28:Q28) -> -188118.35 | V28: =R28-U28 -> 0 | W28: =R28-B28-C28-D28 -> -84918.49
A29: Manutenção de Equipamento - 394 | B29: 0 | C29: =0-B29 -> 0 | D29: 0 | E29: 0 | F29: 0 | G29: 0 | H29: 0 | I29: 0 | J29: 0 | K29: 0 | L29: 0 | M29: 0 | N29: 0 | O29: 0 | P29: 0 | Q29: 0 | R29: =SUM(B29:Q29) -> 0 | S29: =-R29/$R$14 -> 0 | U29: =SUM(B29:Q29) -> 0 | V29: =R29-U29 -> 0 | W29: =R29-B29-C29-D29 -> 0
A30: Manutenção de Veículos - 510 | B30: 0 | C30: =0-B30 -> 0 | D30: 0 | E30: 0 | F30: 0 | G30: 0 | H30: 0 | I30: 0 | J30: 0 | K30: 0 | L30: 0 | M30: 0 | N30: 0 | O30: 0 | P30: 0 | Q30: 0 | R30: =SUM(B30:Q30) -> 0 | S30: =-R30/$R$14 -> 0 | U30: =SUM(B30:Q30) -> 0 | V30: =R30-U30 -> 0 | W30: =R30-B30-C30-D30 -> 0
A31: Medicina Ocupacional e Assist médica - 3 | B31: -850.77 | C31: =-4962.23-B31 -> -4111.46 | D31: -4033 | E31: -6170 | F31: -135 | G31: 0 | H31: -2615 | I31: 0 | J31: -2480 | K31: -2480 | L31: 0 | M31: 0 | N31: 0 | O31: 0 | P31: 0 | Q31: 0 | R31: =SUM(B31:Q31) -> -22875.23 | S31: =-R31/$R$14 -> 0.0024024891 | U31: =SUM(B31:Q31) -> -22875.23 | V31: =R31-U31 -> 0 | W31: =R31-B31-C31-D31 -> -13880
A32: Móveis Não Imobilizado - 364 | B32: -1599.9 | C32: =-1599.9-B32 -> 0 | D32: 0 | E32: 0 | F32: 0 | G32: 0 | H32: 0 | I32: 0 | J32: 0 | K32: 0 | L32: 0 | M32: 0 | N32: 0 | O32: 0 | P32: 0 | Q32: 0 | R32: =SUM(B32:Q32) -> -1599.9 | S32: =-R32/$R$14 -> 0.00016803076 | U32: =SUM(B32:Q32) -> -1599.9 | V32: =R32-U32 -> 0 | W32: =R32-B32-C32-D32 -> 0
A33: Peças, Ferramentas e Acessórios - 361 | B33: -2679.1 | C33: =-6737.6-B33 -> -4058.5 | D33: -12315.74 | E33: -1708.41 | F33: 0 | G33: 0 | H33: -1.03 | I33: 0 | J33: 0 | K33: 0 | L33: 0 | M33: 0 | N33: 0 | O33: 0 | P33: 0 | Q33: 0 | R33: =SUM(B33:Q33) -> -20762.78 | S33: =-R33/$R$14 -> 0.0021806274 | U33: =SUM(B33:Q33) -> -20762.78 | V33: =R33-U33 -> 0 | W33: =R33-B33-C33-D33 -> -1709.44
A34: Premios e Gratificacoes - 313 | B34: -4497 | C34: =-108705.03-B34 -> -104208.03 | D34: -391035.72 | E34: -285138.05 | F34: -11690 | G34: -17003 | H34: -6439 | I34: -5038 | J34: -2383 | K34: 0 | L34: 0 | M34: 0 | N34: 0 | O34: 0 | P34: 0 | Q34: 0 | R34: =SUM(B34:Q34) -> -827431.8 | S34: =-R34/$R$14 -> 0.086901678 | U34: =SUM(B34:Q34) -> -827431.8 | V34: =R34-U34 -> 0 | W34: =R34-B34-C34-D34 -> -327691.05
A35: Salarios e Ordenados - 311 | B35: -41175.17 | C35: =-355305.04-B35 -> -314129.87 | D35: -670348.77 | E35: -461918.07 | F35: -25784.76 | G35: -15463.5 | H35: -12284.01 | I35: -7639 | J35: -5603.84 | K35: 0 | L35: 0 | M35: 0 | N35: 0 | O35: 0 | P35: 0 | Q35: 0 | R35: =SUM(B35:Q35) -> -1554347 | S35: =-R35/$R$14 -> 0.16324652 | U35: =SUM(B35:Q35) -> -1554347 | V35: =R35-U35 -> 0 | W35: =R35-B35-C35-D35 -> -528693.18
A36: Serviços de Terceiros - 324 | B36: -64.5 | C36: =-137.22-B36 -> -72.72 | D36: -2495 | E36: -4048.35 | F36: -347.67 | G36: -347.23 | H36: -347.67 | I36: -347.67 | J36: -347.67 | K36: -342.58 | L36: 0 | M36: 0 | N36: 0 | O36: 0 | P36: 0 | Q36: 0 | R36: =SUM(B36:Q36) -> -8761.06 | S36: =-R36/$R$14 -> 0.00092013724 | U36: =SUM(B36:Q36) -> -8761.06 | V36: =R36-U36 -> 0 | W36: =R36-B36-C36-D36 -> -6128.84
A37: Seguro Riscos Execução de Serv. Trab. | B37: 0 | C37: =0-B37 -> 0 | D37: 0 | E37: 0 | F37: 0 | G37: 0 | H37: 0 | I37: 0 | J37: 0 | K37: 0 | L37: 0 | M37: 0 | N37: 0 | O37: 0 | P37: 0 | Q37: 0 | R37: =SUM(B37:Q37) -> 0 | S37: =-R37/$R$14 -> 0 | U37: =SUM(B37:Q37) -> 0 | V37: =R37-U37 -> 0 | W37: =R37-B37-C37-D37 -> 0
A38: Uniformes - 425 | B38: -2206.73 | C38: =-8669.21-B38 -> -6462.48 | D38: -5374.98 | E38: -3835.53 | F38: 0 | G38: -20.06 | H38: 0 | I38: -153.65 | J38: 0 | K38: 0 | L38: 0 | M38: 0 | N38: 0 | O38: 0 | P38: 0 | Q38: 0 | R38: =SUM(B38:Q38) -> -18053.43 | S38: =-R38/$R$14 -> 0.0018960757 | U38: =SUM(B38:Q38) -> -18053.43 | V38: =R38-U38 -> 0 | W38: =R38-B38-C38-D38 -> -4009.24
A39: Vale Transporte e Condução - 321 | B39: -3013.32 | C39: =-32691.96-B39 -> -29678.64 | D39: -62295.32 | E39: -61894.54 | F39: -2489.03 | G39: -2097.9 | H39: -1552.68 | I39: -1220.01 | J39: -800.64 | K39: -825.44 | L39: 0 | M39: 0 | N39: 0 | O39: 0 | P39: 0 | Q39: 0 | R39: =SUM(B39:Q39) -> -165867.52 | S39: =-R39/$R$14 -> 0.017420367 | U39: =SUM(B39:Q39) -> -165867.52 | V39: =R39-U39 -> 0 | W39: =R39-B39-C39-D39 -> -70880.24
A40: Provisão 13º Salario - 314 | B40: -3181.71 | C40: =-34970.67-B40 -> -31788.96 | D40: -53237.4 | E40: -50453.43 | F40: -3024.48 | G40: -1725.71 | H40: -1252.49 | I40: -779.26 | J40: -546.26 | K40: 0 | L40: 0 | M40: 0 | N40: 0 | O40: 0 | P40: 0 | Q40: 0 | R40: =SUM(B40:Q40) -> -145989.7 | S40: =-R40/$R$14 -> 0.015332683 | U40: =SUM(B40:Q40) -> -145989.7 | V40: =R40-U40 -> 0 | W40: =R40-B40-C40-D40 -> -57781.63
A41: Cursos e treinamentos | B41: 0 | C41: =0-B41 -> 0 | D41: 0 | E41: -300 | F41: 0 | G41: 0 | H41: 0 | I41: 0 | J41: 0 | K41: 0 | L41: 0 | M41: 0 | N41: 0 | O41: 0 | P41: 0 | Q41: 0 | R41: =SUM(B41:Q41) -> -300 | S41: =-R41/$R$14 -> 3.1507737e-05 | U41: =SUM(B41:Q41) -> -300 | V41: =R41-U41 -> 0 | W41: =R41-B41-C41-D41 -> -300
A42: Confraternização de Funcionários | B42: 0 | C42: 0 | D42: 0 | E42: 0 | F42: 0 | G42: 0 | H42: 0 | I42: 0 | J42: 0 | K42: 0 | L42: 0 | M42: 0 | N42: 0 | O42: 0 | P42: 0 | Q42: 0 | R42: =SUM(B42:Q42) -> 0 | S42: =-R42/$R$14 -> 0 | U42: =SUM(B42:Q42) -> 0 | V42: =R42-U42 -> 0 | W42: =R42-B42-C42-D42 -> 0
A43: Custos Total... | B43: =SUM(B17:B42) -> -94793.65 | C43: =SUM(C17:C42) -> -761618.79 | D43: =SUM(D17:D42) -> -1822391.5 | E43: =SUM(E17:E42) -> -1451113 | F43: =SUM(F17:F42) -> -72084.65 | G43: =SUM(G17:G42) -> -62455.17 | H43: =SUM(H17:H42) -> -39101.34 | I43: =SUM(I17:I42) -> -29612.62 | ... R43: =SUM(R17:R42) -> -4360990.1 | S43: =-R43/$R$14 -> 0.45801643 | U43: =SUM(B43:Q43) -> -4360990.1 | V43: =R43-U43 -> 0 | W43: =R43-B43-C43-D43 -> -1682186.2
U44: =SUM(B44:Q44) -> 0 | V44: =R44-U44 -> 0 | W44: =R44-B44-C44-D44 -> 0
A45: = Lucro/Prejuízo Bruto | B45: =B14+B43 -> 360.29 | C45: =C14+C43 -> 239179.76 | D45: =D14+D43 -> 2805975.9 | E45: =E14+E43 -> 2166038.1 | F45: =F14+F43 -> 47915.35 | G45: =G14+G43 -> -62455.17 | H45: =H14+H43 -> -9101.34 | I45: =I14+I43 -> -29612.62 | ... Q45: =Q14+Q43 -> 0 | R45: =SUM(B45:Q45) -> 5160480.8 | S45: =R45/$R$14 -> 0.54198357 | U45: =SUM(B45:Q45) -> 5160480.8 | V45: =R45-U45 -> 0 | W45: =R45-B45-C45-D45 -> 2114964.9
U46: =SUM(B46:Q46) -> 0 | V46: =R46-U46 -> 0 | W46: =R46-B46-C46-D46 -> 0
A47: (-) Impostos s/ Serviços - (13,15% s/ Faturamento) | B47: -12512.74 | C47: =-C12*13.15% -> -131605.01 | D47: =-D12*13.15% -> -608630.32 | E47: =-E12*13.15% -> -475655.36 | F47: =-F12*13.15% -> -15780 | G47: =-G12*13.15% -> 0 | H47: =-H12*13.15% -> -3945 | I47: =-I12*13.15% -> 0 | J47: =-J12*13.15% -> 0 | ... Q47: =-Q12*13.15% -> 0 | R47: =SUM(B47:Q47) -> -1252073.4 | S47: =-R47/$R$14 -> 0.1315 | U47: =SUM(B47:Q47) -> -1252073.4 | V47: =R47-U47 -> 0 | W47: =R47-B47-C47-D47 -> -499325.36
U48: =SUM(B48:Q48) -> 0 | V48: =R48-U48 -> 0 | W48: =R48-B48-C48-D48 -> 0
A49: (-) IRPJ e CSLL - (1,22% s/faturamento) | B49: =-B12*1.22% -> -1160.8781 | C49: =-C12*1.22% -> -12209.742 | D49: =-D12*1.22% -> -56466.083 | E49: =-E12*1.22% -> -44129.242 | F49: =-F12*1.22% -> -1464 | G49: =-G12*1.22% -> 0 | H49: =-H12*1.22% -> -366 | I49: =-I12*1.22% -> 0 | ... Q49: =-Q12*1.22% -> 0 | R49: =SUM(B49:Q49) -> -116161.95 | S49: =-R49/$R$14 -> 0.0122 | U49: =SUM(B49:Q49) -> -116161.95 | V49: =R49-U49 -> 0 | W49: =R49-B49-C49-D49 -> -46325.242
U50: =SUM(B50:Q50) -> 0 | V50: =R50-U50 -> 0 | W50: =R50-B50-C50-D50 -> 0
A51: Total Desp Administrativas/Técnico - ( 5,56% Taxa Adm. Prevista) | B51: =B43*5.56% -> -5270.5269 | C51: =C43*5.56% -> -42346.005 | D51: =D43*5.56% -> -101324.97 | E51: =E43*5.56% -> -80681.881 | F51: =F43*5.56% -> -4007.9065 | G51: =G43*5.56% -> -3472.5075 | H51: =H43*5.56% -> -2174.0345 | I51: =I43*5.56% -> -1646.4617 | ... Q51: =Q43*5.56% -> 0 | R51: =SUM(B51:Q51) -> -242471.05 | S51: =-R51/$R$14 -> 0.025465713 | U51: =SUM(B51:Q51) -> -242471.05 | V51: =R51-U51 -> 0 | W51: =R51-B51-C51-D51 -> -93529.55
U52: =SUM(B52:Q52) -> 0 | V52: =R52-U52 -> 0 | W52: =R52-B52-C52-D52 -> 0
A53: Total Despesas Financeiras -( 0,01% s/ Custo de Obras-média) | B53: -9.48 | C53: =C43*0.01% -> -76.161879 | D53: =D43*0.01% -> -182.23915 | E53: =E43*0.01% -> -145.1113 | F53: =F43*0.01% -> -7.208465 | G53: =G43*0.01% -> -6.245517 | H53: =H43*0.01% -> -3.910134 | I53: =I43*0.01% -> -2.961262 | J53: =J43*0.01% -> -2.159622 | ... Q53: =Q43*0.01% -> 0 | R53: =SUM(B53:Q53) -> -436.09965 | S53: =-R53/$R$14 -> 4.580171e-05 | U53: =SUM(B53:Q53) -> -436.09965 | V53: =R53-U53 -> 0 | W53: =R53-B53-C53-D53 -> -168.21862
U54: =SUM(B54:Q54) -> 0 | V54: =R54-U54 -> 0 | W54: =R54-B54-C54-D54 -> 0
A55: LUCRO/PREJUIZO - LIQUIDO DA OBRA - 274 - | B55: =B45+B51+B53+B47+B49 -> -18593.335 | C55: =C45+C51+C53+C47+C49 -> 52942.842 | D55: =D45+D51+D53+D47+D49 -> 2039372.3 | E55: =E45+E51+E53+E47+E49 -> 1565426.5 | F55: =F45+F51+F53+F47+F49 -> 26656.235 | G55: =G45+G51+G53+G47+G49 -> -65933.923 | H55: =H45+H51+H53+H47+H49 -> -15590.285 | I55: =I45+I51+I53+I47+I49 -> -31262.043 | ... Q55: =Q45+Q51+Q53+Q47+Q49 -> 0 | R55: =SUM(B55:Q55) -> 3549338.3 | S55: =R55/$R$14 -> 0.37277206 | U55: =SUM(B55:Q55) -> 3549338.3 | V55: =R55-U55 -> 0 | W55: =R55-B55-C55-D55 -> 1475616.5
A57: NÚMERO DE FUNCIONÁRIOS - FINAL DO MÊS | F57: 16 | G57: 8 | H57: 7 | I57: 3 | J57: 2
A59: Elaborado: INOV SOLUÇÃO EMPRESARIAL E CONTÁBIL LTDA | S59: 46203
B61: =B14+B43+B47+B49+B51+B53 -> -18593.335 | C61: =C14+C43+C47+C49+C51+C53 -> 52942.842 | D61: =D14+D43+D47+D49+D51+D53 -> 2039372.3 | E61: =E14+E43+E47+E49+E51+E53 -> 1565426.5 | F61: =F14+F43+F47+F49+F51+F53 -> 26656.235 | G61: =G14+G43+G47+G49+G51+G53 -> -65933.923 | H61: =H14+H43+H47+H49+H51+H53 -> -15590.285 | I61: =I14+I43+I47+I49+I51+I53 -> -31262.043 | ... R61: =R14+R43+R47+R49+R51+R53 -> 3549338.3
B63: =B55-B61 -> 0 | C63: =C55-C61 -> 0 | D63: =D55-D61 -> 0 | E63: =E55-E61 -> 0 | F63: =F55-F61 -> 0 | G63: =G55-G61 -> 0 | H63: =H55-H61 -> 0 | I63: =I55-I61 -> 0 | ... R63: =R55-R61 -> 0

Sheet OBRA 275
C1: BELA NOVA CONSTRUTORA LTDA
C3: DEMONSTRAÇÃO DO RESULTADO APURADO
C5: OBRA 275 - FIT CASA JB - EZTEC
C7: OBRA ENCERRADA
B10: Out a Dez/2022 | C10: Jan a Dez/2023 | D10: Janeiro/2024 | E10: Fevereiro/2024 | F10: Março/2024 | G10: Abril/2024 | H10: Maio/2024 | I10: Junho/2024 | J10: Julho/2024 | K10: Agosto/2024 | L10: Setembro/2024 | M10: Outubro/2024 | N10: Novembro/2024 | O10: Dezembro/2024 | P10: Acumulado | Q10: % S/FAT
A11: Receitas Brutas
A12: Servicos prestados | B12: 99222.99 | C12: 1853141.9 | D12: 104503.5 | E12: 100000 | F12: 0 | G12: 140000 | H12: 0 | I12: 30000 | J12: 0 | K12: 0 | L12: 0 | M12: 0 | N12: 0 | O12: 0 | P12: =B12+C12+D12+E12+F12+G12+H12+I12+J12+K12+L12+M12+N12+O12 -> 2326868.4 | Q12: 1 | S12: =SUM(B12:O12) -> 2326868.4 | T12: =P12-S12 -> 0
A13: Locação de Equipamentos - 450 | B13: 0 | C13: 0 | D13: 0 | E13: 0 | F13: 0 | G13: 0 | H13: 0 | I13: 0 | J13: 0 | K13: 0 | L13: 0 | M13: 0 | N13: 0 | O13: 0 | P13: =B13+C13+D13+E13+F13+G13+H13+I13+J13+K13+L13+M13+N13+O13 -> 0 | S13: =SUM(B13:O13) -> 0 | T13: =P13-S13 -> 0
A14: Receitas Brutas Total... | B14: =B12+B13 -> 99222.99 | C14: =C12+C13 -> 1853141.9 | D14: =D12+D13 -> 104503.5 | E14: =E12+E13 -> 100000 | F14: =F12+F13 -> 0 | G14: =SUM(G12:G13) -> 140000 | H14: =SUM(H12:H13) -> 0 | I14: =SUM(I12:I13) -> 30000 | J14: =SUM(J12:J13) -> 0 | K14: =SUM(K12:K13) -> 0 | L14: =SUM(L12:L13) -> 0 | M14: =SUM(M12:M13) -> 0 | N14: =SUM(N12:N13) -> 0 | ... P14: =SUM(P12:P13) -> 2326868.4 | Q14: 1 | S14: =SUM(B14:O14) -> 2326868.4 | T14: =P14-S14 -> 0
T15: =P15-S15 -> 0
A16: Custos | S16: =SUM(B16:O16) -> 0 | T16: =P16-S16 -> 0
A17: Alimentação - 320 | B17: -3556.42 | C17: -64608.3 | D17: -4352.7 | E17: -3746.58 | F17: -2459.1 | G17: -2016.86 | H17: -1015.59 | I17: -1350 | J17: 0 | K17: 0 | L17: 0 | M17: 0 | N17: 0 | O17: 0 | P17: =B17+C17+D17+E17+F17+G17+H17+I17+J17+K17+L17+M17+N17+O17 -> -83105.55 | Q17: =-P17/$P$14 -> 0.035715621 | S17: =SUM(B17:O17) -> -83105.55 | T17: =P17-S17 -> 0
A18: Combustíveis - 322 | B18: -176.92 | C18: -176.92 | D18: 0 | E18: 0 | F18: 0 | G18: 0 | H18: 0 | I18: 0 | J18: 0 | K18: 0 | L18: 0 | M18: 0 | N18: 0 | O18: 0 | P18: =B18+C18+D18+E18+F18+G18+H18+I18+J18+K18+L18+M18+N18+O18 -> -353.84 | Q18: =-P18/$P$14 -> 0.00015206704 | S18: =SUM(B18:O18) -> -353.84 | T18: =P18-S18 -> 0
A19: Despesa com Radio e Telefonia Celular | B19: -130 | C19: -720 | D19: 0 | E19: 0 | F19: 0 | G19: 0 | H19: 0 | I19: 0 | J19: 0 | K19: 0 | L19: 0 | M19: 0 | N19: 0 | O19: 0 | P19: =B19+C19+D19+E19+F19+G19+H19+I19+J19+K19+L19+M19+N19+O19 -> -850 | Q19: =-P19/$P$14 -> 0.00036529784 | S19: =SUM(B19:O19) -> -850 | T19: =P19-S19 -> 0
A20: Equipamento de Segurança - EPIs - 360 | B20: -1134.81 | C20: -3665.07 | D20: -192.16 | E20: -119.84 | F20: 0 | G20: -108.72 | H20: 0 | I20: 0 | J20: 0 | K20: 0 | L20: 0 | M20: 0 | N20: 0 | O20: 0 | P20: =B20+C20+D20+E20+F20+G20+H20+I20+J20+K20+L20+M20+N20+O20 -> -5220.6 | Q20: =-P20/$P$14 -> 0.0022436163 | S20: =SUM(B20:O20) -> -5220.6 | T20: =P20-S20 -> 0
A21: Ferias - 315 | B21: -4424.85 | C21: -54896.17 | D21: -3266.71 | E21: -2330.34 | F21: -1761.65 | G21: -880.82 | H21: -652.5 | I21: 0 | J21: 0 | K21: 0 | L21: 0 | M21: 0 | N21: 0 | O21: 0 | P21: =B21+C21+D21+E21+F21+G21+H21+I21+J21+K21+L21+M21+N21+O21 -> -68213.04 | Q21: =-P21/$P$14 -> 0.029315384 | S21: =SUM(B21:O21) -> -68213.04 | T21: =P21-S21 -> 0
A22: FGTS - 317 | B22: -2185.27 | C22: -32343.52 | D22: -1783.52 | E22: -1254.69 | F22: -927.78 | G22: -863.65 | H22: -402.23 | I22: -239.44 | J22: -17.1 | K22: 0 | L22: 0 | M22: 0 | N22: 0 | O22: 0 | P22: =B22+C22+D22+E22+F22+G22+H22+I22+J22+K22+L22+M22+N22+O22 -> -40017.2 | Q22: =-P22/$P$14 -> 0.017197878 | S22: =SUM(B22:O22) -> -40017.2 | T22: =P22-S22 -> 0
A23: Horas Extras - 499 | B23: -881.3 | C23: -9608.14 | D23: -461.9 | E23: -400 | F23: 0 | G23: 0 | H23: 0 | I23: 0 | J23: 0 | K23: 0 | L23: 0 | M23: 0 | N23: 0 | O23: 0 | P23: =B23+C23+D23+E23+F23+G23+H23+I23+J23+K23+L23+M23+N23+O23 -> -11351.34 | Q23: =-P23/$P$14 -> 0.0048783764 | S23: =SUM(B23:O23) -> -11351.34 | T23: =P23-S23 -> 0
A24: Indenizações e Aviso Prévio - 318 | B24: 0 | C24: 3272.81 | D24: 0 | E24: 0 | F24: 0 | G24: 0 | H24: 0 | I24: 0 | J24: 0 | K24: 0 | L24: 0 | M24: 0 | N24: 0 | O24: 0 | P24: =B24+C24+D24+E24+F24+G24+H24+I24+J24+K24+L24+M24+N24+O24 -> 3272.81 | Q24: =P24/$P$14 -> 0.0014065299 | S24: =SUM(B24:O24) -> 3272.81 | T24: =P24-S24 -> 0
A25: Indenizações Trabalhistas Judiciais - 369 | B25: 0 | C25: 0 | D25: 0 | E25: 0 | F25: 0 | G25: 0 | H25: 0 | I25: 0 | J25: 0 | K25: 0 | L25: 0 | M25: 0 | N25: 0 | O25: 0 | P25: =B25+C25+D25+E25+F25+G25+H25+I25+J25+K25+L25+M25+N25+O25 -> 0 | Q25: =-P25/$P$14 -> 0 | S25: =SUM(B25:O25) -> 0 | T25: =P25-S25 -> 0
A26: INSS - 316 | B26: -2589.83 | C26: -36875.48 | D26: -1961.87 | E26: -1380.16 | F26: -1172.25 | G26: -950.01 | H26: -645.47 | I26: -263.38 | J26: -18.81 | K26: 0 | L26: 0 | M26: 0 | N26: 0 | O26: 0 | P26: =B26+C26+D26+E26+F26+G26+H26+I26+J26+K26+L26+M26+N26+O26 -> -45857.26 | Q26: =-P26/$P$14 -> 0.019707715 | S26: =SUM(B26:O26) -> -45857.26 | T26: =P26-S26 -> 0
A27: Locação de Andaimes - 328 | B27: 0 | C27: 0 | D27: 0 | E27: 0 | F27: 0 | G27: 0 | H27: 0 | I27: 0 | J27: 0 | K27: 0 | L27: 0 | M27: 0 | N27: 0 | O27: 0 | P27: =B27+C27+D27+E27+F27+G27+H27+I27+J27+K27+L27+M27+N27+O27 -> 0 | Q27: =-P27/$P$14 -> 0 | S27: =SUM(B27:O27) -> 0 | T27: =P27-S27 -> 0
A28: Locação de Máqs, Ferramentas e Equipamentos - | B28: -11.87 | C28: -14643.65 | D28: -80 | E28: -2298.38 | F28: -730 | G28: -730 | H28: -730 | I28: 0 | J28: -23.55 | K28: 0 | L28: 0 | M28: 0 | N28: 0 | O28: 0 | P28: =B28+C28+D28+E28+F28+G28+H28+I28+J28+K28+L28+M28+N28+O28 -> -19247.45 | Q28: =-P28/$P$14 -> 0.0082718257 | S28: =SUM(B28:O28) -> -19247.45 | T28: =P28-S28 -> 0
A29: Manutenção de Equipamento - 394 | B29: 0 | C29: 0 | D29: 0 | E29: 0 | F29: 0 | G29: 0 | H29: 0 | I29: 0 | J29: 0 | K29: 0 | L29: 0 | M29: 0 | N29: 0 | O29: 0 | P29: =B29+C29+D29+E29+F29+G29+H29+I29+J29+K29+L29+M29+N29+O29 -> 0 | Q29: =-P29/$P$14 -> 0 | S29: =SUM(B29:O29) -> 0 | T29: =P29-S29 -> 0
A30: Manutenção de Veículos - 510 | B30: 0 | C30: 0 | D30: 0 | E30: 0 | F30: 0 | G30: 0 | H30: 0 | I30: 0 | J30: 0 | K30: 0 | L30: 0 | M30: 0 | N30: 0 | O30: 0 | P30: =B30+C30+D30+E30+F30+G30+H30+I30+J30+K30+L30+M30+N30+O30 -> 0 | Q30: =-P30/$P$14 -> 0 | S30: =SUM(B30:O30) -> 0 | T30: =P30-S30 -> 0
A31: Medicina Ocupacional e Assist médica - 3 | B31: -647.32 | C31: -3769.78 | D31: -405 | E31: 0 | F31: -180 | G31: 0 | H31: 0 | I31: -45 | J31: 0 | K31: 0 | L31: 0 | M31: 0 | N31: 0 | O31: 0 | P31: =B31+C31+D31+E31+F31+G31+H31+I31+J31+K31+L31+M31+N31+O31 -> -5047.1 | Q31: =-P31/$P$14 -> 0.0021690526 | S31: =SUM(B31:O31) -> -5047.1 | T31: =P31-S31 -> 0
A32: Móveis Não Imobilizado - 364 | B32: 0 | C32: 0 | D32: 0 | E32: 0 | F32: 0 | G32: 0 | H32: 0 | I32: 0 | J32: 0 | K32: 0 | L32: 0 | M32: 0 | N32: 0 | O32: 0 | P32: =B32+C32+D32+E32+F32+G32+H32+I32+J32+K32+L32+M32+N32+O32 -> 0 | Q32: =-P32/$P$14 -> 0 | S32: =SUM(B32:O32) -> 0 | T32: =P32-S32 -> 0
A33: Peças, Ferramentas e Acessórios - 361 | B33: -472.17 | C33: -773.31 | D33: 0 | E33: 0 | F33: 0 | G33: 0 | H33: 0 | I33: 0 | J33: 0 | K33: 0 | L33: 0 | M33: 0 | N33: 0 | O33: 0 | P33: =B33+C33+D33+E33+F33+G33+H33+I33+J33+K33+L33+M33+N33+O33 -> -1245.48 | Q33: =-P33/$P$14 -> 0.00053526018 | S33: =SUM(B33:O33) -> -1245.48 | T33: =P33-S33 -> 0
A34: Premios e Gratificacoes - 313 | B34: -9456 | C34: -130488.79 | D34: -5670 | E34: -4686 | F34: -6062.78 | G34: -4790 | H34: -2622.5 | I34: 0 | J34: 0 | K34: 0 | L34: 0 | M34: 0 | N34: 0 | O34: 0 | P34: =B34+C34+D34+E34+F34+G34+H34+I34+J34+K34+L34+M34+N34+O34 -> -163776.07 | Q34: =-P34/$P$14 -> 0.070384758 | S34: =SUM(B34:O34) -> -163776.07 | T34: =P34-S34 -> 0
A35: Salarios e Ordenados - 311 | B35: -26432.28 | C35: -382307.47 | D35: -21822.44 | E35: -15279.97 | F35: -12744.53 | G35: -4414.78 | H35: -6437.12 | I35: 0 | J35: 0 | K35: 0 | L35: 0 | M35: 0 | N35: 0 | O35: 0 | P35: =B35+C35+D35+E35+F35+G35+H35+I35+J35+K35+L35+M35+N35+O35 -> -469438.59 | Q35: =-P35/$P$14 -> 0.20174694 | S35: =SUM(B35:O35) -> -469438.59 | T35: =P35-S35 -> 0
A36: Serviços de Terceiros - 324 | B36: 0 | C36: -72.72 | D36: 0 | E36: 0 | F36: 0 | G36: 0 | H36: 0 | I36: 0 | J36: 0 | K36: 0 | L36: 0 | M36: 0 | N36: 0 | O36: 0 | P36: =B36+C36+D36+E36+F36+G36+H36+I36+J36+K36+L36+M36+N36+O36 -> -72.72 | Q36: =-P36/$P$14 -> 3.1252304e-05 | S36: =SUM(B36:O36) -> -72.72 | T36: =P36-S36 -> 0
... A42: Confraternização de Funcionários | B42: 0 | C42: 0 | D42: 0 | E42: 0 | F42: 0 | G42: 0 | H42: 0 | I42: 0 | J42: 0 | K42: 0 | L42: 0 | M42: 0 | N42: 0 | O42: 0 | P42: =B42+C42+D42+E42+F42+G42+H42+I42+J42+K42+L42+M42+N42+O42 -> 0 | Q42: =-P42/$P$14 -> 0 | S42: =SUM(B42:O42) -> 0 | T42: =P42-S42 -> 0
A43: Custos Total... | B43: =SUM(B17:B42) -> -56288.45 | C43: =SUM(C17:C42) -> -802196.74 | D43: =SUM(D17:D42) -> -43856.56 | E43: =SUM(E17:E42) -> -35284.55 | F43: =SUM(F17:F42) -> -28425.5 | G43: =SUM(G17:G42) -> -16979.74 | H43: =SUM(H17:H42) -> -13254.76 | I43: =SUM(I17:I42) -> -2425.82 | ... P43: =SUM(P17:P42) -> -998771.58 | Q43: =-P43/$P$14 -> 0.42923423 | S43: =SUM(B43:O43) -> -998771.58 | T43: =P43-S43 -> 0
S44: =SUM(B44:O44) -> 0 | T44: =P44-S44 -> 0
A45: = Lucro/Prejuízo Bruto | B45: =B14+B43 -> 42934.54 | C45: =C14+C43 -> 1050945.2 | D45: =D14+D43 -> 60646.94 | E45: =E14+E43 -> 64715.45 | F45: =F14+F43 -> -28425.5 | G45: =G14+G43 -> 123020.26 | H45: =H14+H43 -> -13254.76 | I45: =I14+I43 -> 27574.18 | ... O45: =O14+O43 -> 0 | P45: =B45+C45+D45+E45+F45+G45+H45+I45+J45+K45+L45+M45+N45+O45 -> 1328096.8 | Q45: =P45/$P$14 -> 0.57076577 | S45: =SUM(B45:O45) -> 1328096.8 | T45: =P45-S45 -> 0
S46: =SUM(B46:O46) -> 0 | T46: =P46-S46 -> 0
A47: (-) Impostos s/ Serviços - (13,15% s/ Faturamento) | B47: -13047.82 | C47: =-C12*13.15% -> -243688.16 | D47: =-D12*13.15% -> -13742.21 | E47: =-E12*13.15% -> -13150 | F47: =-F12*13.15% -> 0 | G47: =-G12*13.15% -> -18410 | H47: =-H12*13.15% -> 0 | I47: =-I12*13.15% -> -3945 | J47: =-J12*13.15% -> 0 | ... O47: =-O12*13.15% -> 0 | P47: =B47+C47+D47+E47+F47+G47+H47+I47+J47+K47+L47+M47+N47+O47 -> -305983.19 | Q47: =-P47/$P$14 -> 0.1315 | S47: =SUM(B47:O47) -> -305983.19 | T47: =P47-S47 -> 0
S48: =SUM(B48:O48) -> 0 | T48: =P48-S48 -> 0
A49: (-) IRPJ e CSLL - (1,22% s/faturamento) | B49: =-B12*1.22% -> -1210.5205 | C49: =-C12*1.22% -> -22608.331 | D49: =-D12*1.22% -> -1274.9427 | E49: =-E12*1.22% -> -1220 | F49: =-F12*1.22% -> 0 | G49: =-G12*1.22% -> -1708 | H49: =-H12*1.22% -> 0 | I49: =-I12*1.22% -> -366 | ... O49: =-O12*1.22% -> 0 | P49: =B49+C49+D49+E49+F49+G49+H49+I49+J49+K49+L49+M49+N49+O49 -> -28387.795 | Q49: =-P49/$P$14 -> 0.0122 | S49: =SUM(B49:O49) -> -28387.795 | T49: =P49-S49 -> 0
S50: =SUM(B50:O50) -> 0 | T50: =P50-S50 -> 0
A51: Total Desp Administrativas/Técnico - ( 5,56% Taxa Adm. Prevista) | B51: =B43*5.56% -> -3129.6378 | C51: =C43*5.56% -> -44602.139 | D51: =D43*5.56% -> -2438.4247 | E51: =E43*5.56% -> -1961.821 | F51: =F43*5.56% -> -1580.4578 | G51: =G43*5.56% -> -944.07354 | H51: =H43*5.56% -> -736.96466 | I51: =I43*5.56% -> -134.87559 | ... O51: =O43*5.56% -> 0 | P51: =B51+C51+D51+E51+F51+G51+H51+I51+J51+K51+L51+M51+N51+O51 -> -55531.7 | Q51: =-P51/$P$14 -> 0.023865423 | S51: =SUM(B51:O51) -> -55531.7 | T51: =P51-S51 -> 0
S52: =SUM(B52:O52) -> 0 | T52: =P52-S52 -> 0
A53: Total Despesas Financeiras -( 0,01% s/ Custo de Obras-média) | B53: -5.63 | C53: =C43*0.01% -> -80.219674 | D53: =D43*0.01% -> -4.385656 | E53: =E43*0.01% -> -3.528455 | F53: =F43*0.01% -> -2.84255 | G53: =G43*0.01% -> -1.697974 | H53: =H43*0.01% -> -1.325476 | I53: =I43*0.01% -> -0.242582 | J53: =J43*0.01% -> -0.005946 | ... O53: =O43*0.01% -> 0 | P53: =B53+C53+D53+E53+F53+G53+H53+I53+J53+K53+L53+M53+N53+O53 -> -99.878313 | Q53: =-P53/$P$14 -> 4.292392e-05 | S53: =SUM(B53:O53) -> -99.878313 | T53: =P53-S53 -> 0
S54: =SUM(B54:O54) -> 0 | T54: =P54-S54 -> 0
A55: LUCRO/PREJUIZO - LIQUIDO DA OBRA - 275 - | B55: =B45+B51+B53+B47+B49 -> 25540.932 | C55: =C45+C51+C53+C47+C49 -> 739966.33 | D55: =D45+D51+D53+D47+D49 -> 43186.977 | E55: =E45+E51+E53+E47+E49 -> 48380.101 | F55: =F45+F51+F53+F47+F49 -> -30008.8 | G55: =G45+G51+G53+G47+G49 -> 101956.49 | H55: =H45+H51+H53+H47+H49 -> -13993.05 | I55: =I45+I51+I53+I47+I49 -> 23128.062 | ... O55: =O45+O51+O53+O47+O49 -> 0 | P55: =B55+C55+D55+E55+F55+G55+H55+I55+J55+K55+L55+M55+N55+O55 -> 938094.26 | Q55: =P55/$P$14 -> 0.40315742 | S55: =SUM(B55:O55) -> 938094.26 | T55: =P55-S55 -> 0
A57: NÚMERO DE FUNCIONÁRIOS - FINAL DO MÊS | D57: 10 | E57: 7 | F57: 7 | G57: 4 | H57: 3 | I57: 1 | J57: 1
J58: FÉRIAS - LUIS AMANCIO SILVA BASTOS
A59: Elaborado: INOV SOLUÇÃO EMPRESARIAL E CONTÁBIL LTDA | Q59: 45535
B60: =B14+B43+B47+B49+B51+B53 -> 25540.932 | C60: =C14+C43+C47+C49+C51+C53 -> 739966.33 | D60: =D14+D43+D47+D49+D51+D53 -> 43186.977 | E60: =E14+E43+E47+E49+E51+E53 -> 48380.101 | F60: =F14+F43+F47+F49+F51+F53 -> -30008.8 | G60: =G14+G43+G47+G49+G51+G53 -> 101956.49 | H60: =H14+H43+H47+H49+H51+H53 -> -13993.05 | I60: =I14+I43+I47+I49+I51+I53 -> 23128.062 | ... P60: =P14+P43+P47+P49+P51+P53 -> 938094.26
B63: =B55-B60 -> 0 | C63: =C55-C60 -> 0 | D63: =D55-D60 -> 0 | E63: =E55-E60 -> 0 | F63: =F55-F60 -> 0 | G63: =G55-G60 -> 0 | H63: =H55-H60 -> 0 | I63: =I55-I60 -> 0 | ... P63: =P55-P60 -> 0

Sheet OBRA 277
B1: BELA NOVA CONSTRUTORA LTDA
B3: DEMONSTRAÇÃO DO RESULTADO APURADO
B5: OBRA 277 - DREAM VIEW - EZTEC
B7: OBRA ENCERRADA
B10: Out a Dez/2022 | C10: Jan a Dez/2023 | D10: Jan a Dez/2024 | E10: Janeiro/2025 | F10: Fevereiro/2025 | G10: Março/2025 | H10: Abril/2025 | I10: Maio/2025 | J10: Junho/2025 | K10: Julho/2025 | L10: Agosto/2025 | M10: Setembro/2025 | N10: Outubro/2025 | O10: Novembro/2025 | P10: Dezembro/2025 | Q10: Acumulado | R10: % S/FAT
A11: Receitas Brutas
A12: Servicos prestados | B12: 0 | C12: =312760.6-B12 -> 312760.6 | D12: 0 | E12: 0 | F12: 0 | G12: 0 | H12: 0 | I12: 0 | J12: 0 | K12: 0 | L12: 0 | M12: 0 | N12: 0 | O12: 0 | P12: 0 | Q12: =B12+C12+D12+E12+F12+G12+H12+I12+J12+K12+L12+M12+N12+O12+P12 -> 312760.6 | R12: 1 | T12: =SUM(B12:P12) -> 312760.6 | U12: =T12-Q12 -> 0
A13: Locação de Equipamentos - 450 | B13: 0 | C13: =0-B13 -> 0 | D13: 0 | E13: 0 | F13: 0 | G13: 0 | H13: 0 | I13: 0 | J13: 0 | K13: 0 | L13: 0 | M13: 0 | N13: 0 | O13: 0 | P13: 0 | Q13: =B13+C13+D13+E13+F13+G13+H13+I13+J13+K13+L13+M13+N13+O13+P13 -> 0 | T13: =SUM(B13:P13) -> 0 | U13: =T13-Q13 -> 0
A14: Receitas Brutas Total... | B14: =B12+B13 -> 0 | C14: =C12+C13 -> 312760.6 | D14: =SUM(D12:D13) -> 0 | E14: =E12+E13 -> 0 | F14: =F12+F13 -> 0 | G14: =G12+G13 -> 0 | H14: =SUM(H12:H13) -> 0 | I14: =SUM(I12:I13) -> 0 | J14: =SUM(J12:J13) -> 0 | K14: =SUM(K12:K13) -> 0 | L14: =SUM(L12:L13) -> 0 | M14: =SUM(M12:M13) -> 0 | N14: =SUM(N12:N13) -> 0 | O14: =SUM(O12:O13) -> 0 | ... Q14: =SUM(Q12:Q13) -> 312760.6 | R14: 1 | T14: =SUM(B14:P14) -> 312760.6 | U14: =T14-Q14 -> 0
T15: =SUM(B15:P15) -> 0
A16: Custos | T16: =SUM(B16:P16) -> 0
A17: Alimentação - 320 | B17: -1064.07 | C17: =-48233.12-B17 -> -47169.05 | D17: -34147.01 | E17: -1986.29 | F17: -3841.09 | G17: -1258.51 | H17: -900 | I17: 0 | J17: 0 | K17: 0 | L17: 0 | M17: 0 | N17: 0 | O17: 0 | P17: 0 | Q17: =B17+C17+D17+E17+F17+G17+H17+I17+J17+K17+L17+M17+N17+O17+P17 -> -90366.02 | R17: =-Q17/$Q$14 -> 0.28893032 | T17: =SUM(B17:P17) -> -90366.02 | U17: =T17-Q17 -> 0
A18: Combustíveis - 322 | B18: -176.92 | C18: =-176.92-B18 -> 0 | D18: 0 | E18: 0 | F18: 0 | G18: 0 | H18: 0 | I18: 0 | J18: 0 | K18: 0 | L18: 0 | M18: 0 | N18: 0 | O18: 0 | P18: 0 | Q18: =B18+C18+D18+E18+F18+G18+H18+I18+J18+K18+L18+M18+N18+O18+P18 -> -176.92 | R18: =-Q18/$Q$14 -> 0.00056567227 | T18: =SUM(B18:P18) -> -176.92 | U18: =T18-Q18 -> 0
A19: Despesa com Radio e Telefonia Celular | B19: 0 | C19: =0-B19 -> 0 | D19: 0 | E19: 0 | F19: 0 | G19: 0 | H19: 0 | I19: 0 | J19: 0 | K19: 0 | L19: 0 | M19: 0 | N19: 0 | O19: 0 | P19: 0 | Q19: =B19+C19+D19+E19+F19+G19+H19+I19+J19+K19+L19+M19+N19+O19+P19 -> 0 | R19: =-Q19/$Q$14 -> 0 | T19: =SUM(B19:P19) -> 0 | U19: =T19-Q19 -> 0
A20: Equipamento de Segurança - EPIs - 360 | B20: 0 | C20: =-1395.43-B20 -> -1395.43 | D20: -109.96 | E20: -11 | F20: 0 | G20: 0 | H20: 0 | I20: 0 | J20: 0 | K20: 0 | L20: 0 | M20: 0 | N20: 0 | O20: 0 | P20: 0 | Q20: =B20+C20+D20+E20+F20+G20+H20+I20+J20+K20+L20+M20+N20+O20+P20 -> -1516.39 | R20: =-Q20/$Q$14 -> 0.0048484048 | T20: =SUM(B20:P20) -> -1516.39 | U20: =T20-Q20 -> 0
A21: Ferias - 315 | B21: -1217.97 | C21: =-36734.8-B21 -> -35516.83 | D21: -27166.74 | E21: -2499.21 | F21: -980.9 | G21: -653.93 | H21: 0 | I21: 0 | J21: 0 | K21: 0 | L21: 0 | M21: 0 | N21: 0 | O21: 0 | P21: 0 | Q21: =B21+C21+D21+E21+F21+G21+H21+I21+J21+K21+L21+M21+N21+O21+P21 -> -68035.58 | R21: =-Q21/$Q$14 -> 0.21753245 | T21: =SUM(B21:P21) -> -68035.58 | U21: =T21-Q21 -> 0
A22: FGTS - 317 | B22: -662.73 | C22: =-23876.12-B22 -> -23213.39 | D22: -17650.79 | E22: -1441.88 | F22: -573.36 | G22: -402.22 | H22: 0 | I22: 0 | J22: 0 | K22: 0 | L22: 0 | M22: 0 | N22: 0 | O22: 0 | P22: 0 | Q22: =B22+C22+D22+E22+F22+G22+H22+I22+J22+K22+L22+M22+N22+O22+P22 -> -43944.37 | R22: =-Q22/$Q$14 -> 0.14050481 | T22: =SUM(B22:P22) -> -43944.37 | U22: =T22-Q22 -> 0
A23: Horas Extras - 499 | B23: -1026.34 | C23: =-30348.58-B23 -> -29322.24 | D23: -10457.96 | E23: -317.34 | F23: -127.9 | G23: 0 | H23: 0 | I23: 0 | J23: 0 | K23: 0 | L23: 0 | M23: 0 | N23: 0 | O23: 0 | P23: 0 | Q23: =B23+C23+D23+E23+F23+G23+H23+I23+J23+K23+L23+M23+N23+O23+P23 -> -41251.78 | R23: =-Q23/$Q$14 -> 0.13189571 | T23: =SUM(B23:P23) -> -41251.78 | U23: =T23-Q23 -> 0
A24: Indenizações e Aviso Prévio - 318 | B24: 0 | C24: =-2283.36-B24 -> -2283.36 | D24: 0 | E24: 0 | F24: 0 | G24: 0 | H24: 0 | I24: 0 | J24: 0 | K24: 0 | L24: 0 | M24: 0 | N24: 0 | O24: 0 | P24: 0 | Q24: =B24+C24+D24+E24+F24+G24+H24+I24+J24+K24+L24+M24+N24+O24+P24 -> -2283.36 | R24: =-Q24/$Q$14 -> 0.0073006638 | T24: =SUM(B24:P24) -> -2283.36 | U24: =T24-Q24 -> 0
A25: Indenizações Trabalhistas Judiciais - 369 | B25: 0 | C25: =0-B25 -> 0 | D25: 0 | E25: 0 | F25: 0 | G25: 0 | H25: 0 | I25: 0 | J25: 0 | K25: 0 | L25: 0 | M25: 0 | N25: 0 | O25: 0 | P25: 0 | Q25: =B25+C25+D25+E25+F25+G25+H25+I25+J25+K25+L25+M25+N25+O25+P25 -> 0 | R25: =-Q25/$Q$14 -> 0 | T25: =SUM(B25:P25) -> 0 | U25: =T25-Q25 -> 0
A26: INSS - 316 | B26: -784.05 | C26: =-27732.29-B26 -> -26948.24 | D26: -19928.43 | E26: -2532.29 | F26: -1004.19 | G26: -695.16 | H26: 0 | I26: 0 | J26: 0 | K26: 0 | L26: 0 | M26: 0 | N26: 0 | O26: 0 | P26: 0 | Q26: =B26+C26+D26+E26+F26+G26+H26+I26+J26+K26+L26+M26+N26+O26+P26 -> -51892.36 | R26: =-Q26/$Q$14 -> 0.16591719 | T26: =SUM(B26:P26) -> -51892.36 | U26: =T26-Q26 -> 0
A27: Locação de Andaimes - 328 | B27: 0 | C27: =0-B27 -> 0 | D27: 0 | E27: 0 | F27: 0 | G27: 0 | H27: 0 | I27: 0 | J27: 0 | K27: 0 | L27: 0 | M27: 0 | N27: 0 | O27: 0 | P27: 0 | Q27: =B27+C27+D27+E27+F27+G27+H27+I27+J27+K27+L27+M27+N27+O27+P27 -> 0 | R27: =-Q27/$Q$14 -> 0 | T27: =SUM(B27:P27) -> 0 | U27: =T27-Q27 -> 0
A28: Locação de Máqs, Ferramentas e Equipamentos - | B28: 0 | C28: =0-B28 -> 0 | D28: -610 | E28: 0 | F28: 0 | G28: 0 | H28: 0 | I28: 0 | J28: 0 | K28: 0 | L28: 0 | M28: 0 | N28: 0 | O28: 0 | P28: 0 | Q28: =B28+C28+D28+E28+F28+G28+H28+I28+J28+K28+L28+M28+N28+O28+P28 -> -610 | R28: =-Q28/$Q$14 -> 0.0019503735 | T28: =SUM(B28:P28) -> -610 | U28: =T28-Q28 -> 0
A29: Manutenção de Equipamento - 394 | B29: 0 | C29: =0-B29 -> 0 | D29: -280 | E29: 0 | F29: 0 | G29: 0 | H29: 0 | I29: 0 | J29: 0 | K29: 0 | L29: 0 | M29: 0 | N29: 0 | O29: 0 | P29: 0 | Q29: =B29+C29+D29+E29+F29+G29+H29+I29+J29+K29+L29+M29+N29+O29+P29 -> -280 | R29: =-Q29/$Q$14 -> 0.00089525343 | T29: =SUM(B29:P29) -> -280 | U29: =T29-Q29 -> 0
A30: Manutenção de Veículos - 510 | B30: 0 | C30: =0-B30 -> 0 | D30: 0 | E30: 0 | F30: 0 | G30: 0 | H30: 0 | I30: 0 | J30: 0 | K30: 0 | L30: 0 | M30: 0 | N30: 0 | O30: 0 | P30: 0 | Q30: =B30+C30+D30+E30+F30+G30+H30+I30+J30+K30+L30+M30+N30+O30+P30 -> 0 | R30: =-Q30/$Q$14 -> 0 | T30: =SUM(B30:P30) -> 0 | U30: =T30-Q30 -> 0
A31: Medicina Ocupacional e Assist médica - 3 | B31: -121.69 | C31: =-3216.98-B31 -> -3095.29 | D31: -990 | E31: 0 | F31: -270 | G31: 0 | H31: 0 | I31: 0 | J31: 0 | K31: 0 | L31: 0 | M31: 0 | N31: 0 | O31: 0 | P31: 0 | Q31: =B31+C31+D31+E31+F31+G31+H31+I31+J31+K31+L31+M31+N31+O31+P31 -> -4476.98 | R31: =-Q31/$Q$14 -> 0.014314399 | T31: =SUM(B31:P31) -> -4476.98 | U31: =T31-Q31 -> 0
A32: Móveis Não Imobilizado - 364 | B32: 0 | C32: =0-B32 -> 0 | D32: 0 | E32: 0 | F32: 0 | G32: 0 | H32: 0 | I32: 0 | J32: 0 | K32: 0 | L32: 0 | M32: 0 | N32: 0 | O32: 0 | P32: 0 | Q32: =B32+C32+D32+E32+F32+G32+H32+I32+J32+K32+L32+M32+N32+O32+P32 -> 0 | R32: =-Q32/$Q$14 -> 0 | T32: =SUM(B32:P32) -> 0 | U32: =T32-Q32 -> 0
A33: Peças, Ferramentas e Acessórios - 361 | B33: -1367.18 | C33: =-2115.95-B33 -> -748.77 | D33: -264.58 | E33: 0 | F33: 0 | G33: 0 | H33: 0 | I33: 0 | J33: 0 | K33: 0 | L33: 0 | M33: 0 | N33: 0 | O33: 0 | P33: 0 | Q33: =B33+C33+D33+E33+F33+G33+H33+I33+J33+K33+L33+M33+N33+O33+P33 -> -2380.53 | R33: =-Q33/$Q$14 -> 0.0076113487 | T33: =SUM(B33:P33) -> -2380.53 | U33: =T33-Q33 -> 0
A34: Premios e Gratificacoes - 313 | B34: 0 | C34: =-77037.83-B34 -> -77037.83 | D34: -93608.55 | E34: -1443.75 | F34: -3594 | G34: -1472 | H34: 0 | I34: 0 | J34: 0 | K34: 0 | L34: 0 | M34: 0 | N34: 0 | O34: 0 | P34: 0 | Q34: =B34+C34+D34+E34+F34+G34+H34+I34+J34+K34+L34+M34+N34+O34+P34 -> -177156.13 | R34: =-Q34/$Q$14 -> 0.56642726 | T34: =SUM(B34:P34) -> -177156.13 | U34: =T34-Q34 -> 0
A35: Salarios e Ordenados - 311 | B35: -7258.55 | C35: =-268313.1-B35 -> -261054.55 | D35: -185291.28 | E35: -17169.01 | F35: -7036.82 | G35: -5027.16 | H35: 0 | I35: 0 | J35: 0 | K35: 0 | L35: 0 | M35: 0 | N35: 0 | O35: 0 | P35: 0 | Q35: =B35+C35+D35+E35+F35+G35+H35+I35+J35+K35+L35+M35+N35+O35+P35 -> -482837.37 | R35: =-Q35/$Q$14 -> 1.5437922 | T35: =SUM(B35:P35) -> -482837.37 | U35: =T35-Q35 -> 0
A36: Serviços de Terceiros - 324 | B36: 0 | C36: =-72.72-B36 -> -72.72 | D36: -300 | E36: 0 | F36: 0 | G36: 0 | H36: 0 | I36: 0 | J36: 0 | K36: 0 | L36: 0 | M36: 0 | N36: 0 | O36: 0 | P36: 0 | Q36: =B36+C36+D36+E36+F36+G36+H36+I36+J36+K36+L36+M36+N36+O36+P36 -> -372.72 | R36: =-Q36/$Q$14 -> 0.0011917102 | T36: =SUM(B36:P36) -> -372.72 | U36: =T36-Q36 -> 0
A37: Seguro Riscos Execução de Serv. Trab. | B37: 0 | C37: =0-B37 -> 0 | D37: 0 | E37: 0 | F37: 0 | G37: 0 | H37: 0 | I37: 0 | J37: 0 | K37: 0 | L37: 0 | M37: 0 | N37: 0 | O37: 0 | P37: 0 | Q37: =B37+C37+D37+E37+F37+G37+H37+I37+J37+K37+L37+M37+N37+O37+P37 -> 0 | R37: =-Q37/$Q$14 -> 0 | T37: =SUM(B37:P37) -> 0 | U37: =T37-Q37 -> 0
A38: Uniformes - 425 | B38: -173.4 | C38: =-4198.71-B38 -> -4025.31 | D38: -1325.24 | E38: -198.84 | F38: 0 | G38: 0 | H38: 0 | I38: 0 | J38: 0 | K38: 0 | L38: 0 | M38: 0 | N38: 0 | O38: 0 | P38: 0 | Q38: =B38+C38+D38+E38+F38+G38+H38+I38+J38+K38+L38+M38+N38+O38+P38 -> -5722.79 | R38: =-Q38/$Q$14 -> 0.018297669 | T38: =SUM(B38:P38) -> -5722.79 | U38: =T38-Q38 -> 0
A39: Vale Transporte e Condução - 321 | B39: -498 | C39: =-23973.44-B39 -> -23475.44 | D39: -20337.71 | E39: -1928.9 | F39: -2793.21 | G39: -962.94 | H39: -732 | I39: 0 | J39: 0 | K39: 0 | L39: 0 | M39: 0 | N39: 0 | O39: 0 | P39: 0 | Q39: =B39+C39+D39+E39+F39+G39+H39+I39+J39+K39+L39+M39+N39+O39+P39 -> -50728.2 | R39: =-Q39/$Q$14 -> 0.16219498 | T39: =SUM(B39:P39) -> -50728.2 | U39: =T39-Q39 -> 0
A40: 13º Salario - 314 | B40: -182.69 | C40: =-26445.61-B40 -> -26262.92 | D40: -16203.39 | E40: -1874.41 | F40: -735.67 | G40: -490.45 | H40: 0 | I40: 0 | J40: 0 | K40: 0 | L40: 0 | M40: 0 | N40: 0 | O40: 0 | P40: 0 | Q40: =B40+C40+D40+E40+F40+G40+H40+I40+J40+K40+L40+M40+N40+O40+P40 -> -45749.53 | R40: =-Q40/$Q$14 -> 0.14627651 | T40: =SUM(B40:P40) -> -45749.53 | U40: =T40-Q40 -> 0
A41: Cursos e treinamentos | B41: 0 | C41: =100-B41 -> 100 | D41: 0 | E41: 0 | F41: 0 | G41: 0 | H41: 0 | I41: 0 | J41: 0 | K41: 0 | L41: 0 | M41: 0 | N41: 0 | O41: 0 | P41: 0 | Q41: =B41+C41+D41+E41+F41+G41+H41+I41+J41+K41+L41+M41+N41+O41+P41 -> 100 | R41: =Q41/$Q$14 -> 0.00031973337 | T41: =SUM(B41:P41) -> 100 | U41: =T41-Q41 -> 0
A42: Confraternização de Funcionários | B42: 0 | C42: 0 | D42: 0 | E42: 0 | F42: 0 | G42: 0 | H42: 0 | I42: 0 | J42: 0 | K42: 0 | L42: 0 | M42: 0 | N42: 0 | O42: 0 | P42: 0 | Q42: =B42+C42+D42+E42+F42+G42+H42+I42+J42+K42+L42+M42+N42+O42+P42 -> 0 | R42: =-Q42/$Q$14 -> 0 | T42: =SUM(B42:P42) -> 0 | U42: =T42-Q42 -> 0
A43: Custos Total... | B43: =SUM(B17:B42) -> -14533.59 | C43: =SUM(C17:C42) -> -561521.37 | D43: =SUM(D17:D42) -> -428671.64 | E43: =SUM(E17:E42) -> -31402.92 | F43: =SUM(F17:F42) -> -20957.14 | G43: =SUM(G17:G42) -> -10962.37 | H43: =SUM(H17:H42) -> -1632 | I43: =SUM(I17:I42) -> 0 | ... Q43: =SUM(Q17:Q42) -> -1069681 | R43: =-Q43/$Q$14 -> 3.4201272 | T43: =SUM(B43:P43) -> -1069681 | U43: =T43-Q43 -> 0
T44: =SUM(B44:P44) -> 0 | U44: =T44-Q44 -> 0
A45: = Lucro/Prejuízo Bruto | B45: =B14+B43 -> -14533.59 | C45: =C14+C43 -> -248760.77 | D45: =D14+D43 -> -428671.64 | E45: =E14+E43 -> -31402.92 | F45: =F14+F43 -> -20957.14 | G45: =G14+G43 -> -10962.37 | H45: =H14+H43 -> -1632 | I45: =I14+I43 -> 0 | ... P45: =P14+P43 -> 0 | Q45: =B45+C45+D45+E45+F45+G45+H45+I45+J45+K45+L45+M45+N45+O45+P45 -> -756920.43 | R45: =-Q45/$Q$14 -> 2.4201272 | T45: =SUM(B45:P45) -> -756920.43 | U45: =T45-Q45 -> 0
T46: =SUM(B46:P46) -> 0 | U46: =T46-Q46 -> 0
A47: (-) Impostos s/ Serviços - (13,15% s/ Faturamento) | B47: =-B12*12.46% -> 0 | C47: =-C12*13.15% -> -41128.019 | D47: =-D12*13.15% -> 0 | E47: =-E12*13.15% -> 0 | F47: =-F12*13.15% -> 0 | G47: =-G12*13.15% -> 0 | H47: =-H12*13.15% -> 0 | I47: =-I12*13.15% -> 0 | J47: =-J12*13.15% -> 0 | ... P47: =-P12*13.15% -> 0 | Q47: =B47+C47+D47+E47+F47+G47+H47+I47+J47+K47+L47+M47+N47+O47+P47 -> -41128.019 | R47: =-Q47/$Q$14 -> 0.1315 | T47: =SUM(B47:P47) -> -41128.019 | U47: =T47-Q47 -> 0
T48: =SUM(B48:P48) -> 0 | U48: =T48-Q48 -> 0
A49: (-) IRPJ e CSLL - (1,22% s/faturamento) | B49: =-B12*1.22% -> 0 | C49: =-C12*1.22% -> -3815.6793 | D49: =-D12*1.22% -> 0 | E49: =-E12*1.22% -> 0 | F49: =-F12*1.22% -> 0 | G49: =-G12*1.22% -> 0 | H49: =-H12*1.22% -> 0 | I49: =-I12*1.22% -> 0 | ... P49: =-P12*1.22% -> 0 | Q49: =B49+C49+D49+E49+F49+G49+H49+I49+J49+K49+L49+M49+N49+O49+P49 -> -3815.6793 | R49: =-Q49/$Q$14 -> 0.0122 | T49: =SUM(B49:P49) -> -3815.6793 | U49: =T49-Q49 -> 0
T50: =SUM(B50:P50) -> 0 | U50: =T50-Q50 -> 0
A51: Total Desp Administrativas/Técnico - ( 5,56% Taxa Adm. Prevista) | B51: =B43*5.56% -> -808.0676 | C51: =C43*5.56% -> -31220.588 | D51: =D43*5.56% -> -23834.143 | E51: =E43*5.56% -> -1746.0024 | F51: =F43*5.56% -> -1165.217 | G51: =G43*5.56% -> -609.50777 | H51: =H43*5.56% -> -90.7392 | I51: =I43*5.56% -> 0 | ... P51: =P43*5.56% -> 0 | Q51: =B51+C51+D51+E51+F51+G51+H51+I51+J51+K51+L51+M51+N51+O51+P51 -> -59474.265 | R51: =-Q51/$Q$14 -> 0.19015907 | T51: =SUM(B51:P51) -> -59474.265 | U51: =T51-Q51 -> 0
T52: =SUM(B52:P52) -> 0 | U52: =T52-Q52 -> 0
A53: Total Despesas Financeiras -( 0,01% s/ Custo de Obras-média) | B53: -1.45 | C53: =C43*0.01% -> -56.152137 | D53: =D43*0.01% -> -42.867164 | E53: =E43*0.01% -> -3.140292 | F53: =F43*0.01% -> -2.095714 | G53: =G43*0.01% -> -1.096237 | H53: =H43*0.01% -> -0.1632 | I53: =I43*0.01% -> 0 | J53: =J43*0.01% -> 0 | ... P53: =P43*0.01% -> 0 | Q53: =B53+C53+D53+E53+F53+G53+H53+I53+J53+K53+L53+M53+N53+O53+P53 -> -106.96474 | R53: =-Q53/$Q$14 -> 0.00034200198 | T53: =SUM(B53:P53) -> -106.96474 | U53: =T53-Q53 -> 0
T54: =SUM(B54:P54) -> 0 | U54: =T54-Q54 -> 0
A55: LUCRO/PREJUIZO - LIQUIDO DA OBRA - 277 - | B55: =B45+B51+B53+B47+B49 -> -15343.108 | C55: =C45+C51+C53+C47+C49 -> -324981.21 | D55: =D45+D51+D53+D47+D49 -> -452548.65 | E55: =E45+E51+E53+E47+E49 -> -33152.063 | F55: =F45+F51+F53+F47+F49 -> -22124.453 | G55: =G45+G51+G53+G47+G49 -> -11572.974 | H55: =H45+H51+H53+H47+H49 -> -1722.9024 | I55: =I45+I51+I53+I47+I49 -> 0 | ... P55: =P45+P51+P53+P47+P49 -> 0 | Q55: =B55+C55+D55+E55+F55+G55+H55+I55+J55+K55+L55+M55+N55+O55+P55 -> -861445.36 | R55: =-Q55/$Q$14 -> 2.7543283 | T55: =SUM(B55:P55) -> -861445.36 | U55: =T55-Q55 -> 0
A57: NÚMERO DE FUNCIONÁRIOS - FINAL DO MÊS | E57: 8 | F57: 3 | G57: 2 | H57: 5
A59: Elaborado: INOV SOLUÇÃO EMPRESARIAL E CONTÁBIL LTDA | R59: 45838
B61: =B14+B43+B47+B49+B51+B53 -> -15343.108 | C61: =C14+C43+C47+C49+C51+C53 -> -324981.21 | D61: =D14+D43+D47+D49+D51+D53 -> -452548.65 | E61: =E14+E43+E47+E49+E51+E53 -> -33152.063 | F61: =F14+F43+F47+F49+F51+F53 -> -22124.453 | G61: =G14+G43+G47+G49+G51+G53 -> -11572.974 | H61: =H14+H43+H47+H49+H51+H53 -> -1722.9024 | I61: =I14+I43+I47+I49+I51+I53 -> 0 | ... Q61: =Q14+Q43+Q47+Q49+Q51+Q53 -> -861445.36
B63: =B55-B61 -> 0 | C63: =C55-C61 -> 0 | D63: =D55-D61 -> 0 | E63: =E55-E61 -> 0 | F63: =F55-F61 -> 0 | G63: =G55-G61 -> 0 | H63: =H55-H61 -> 0 | I63: =I55-I61 -> 0 | ... Q63: =Q55-Q61 -> 0

Sheet OBRA 279
B1: BELA NOVA CONSTRUTORA EIRELI
B3: DEMONSTRAÇÃO DO RESULTADO APURADO
B5: OBRA 279 - GROENLANDIA - ADOLPHO LINDENBERG
B7: OBRA ENCERRADA
B10: Jan a Dez/2023 | C10: Janeiro/2024 | D10: Fevereiro/2024 | E10: Março/2024 | F10: Abril/2024 | G10: Maio/2024 | H10: Junho/2024 | I10: Julho/2024 | J10: Agosto/2024 | K10: Setembro/2024 | L10: Outubro/2024 | M10: Novembro/2024 | N10: Dezembro/2024 | O10: Acumulado | P10: % S/FAT
A11: Receitas Brutas
A12: Servicos prestados | B12: 0 | C12: 0 | D12: 0 | E12: 0 | F12: 0 | G12: 0 | H12: 0 | I12: 0 | J12: 0 | K12: 0 | L12: 0 | M12: 0 | N12: 0 | O12: =B12+C12+D12+E12+F12+G12+H12+I12+J12+K12+L12+M12+N12 -> 0 | P12: 1 | R12: =SUM(B12:N12) -> 0 | S12: =O12-R12 -> 0
A13: Locação de Equipamentos - 450 | B13: 0 | C13: 0 | D13: 0 | E13: 0 | F13: 0 | G13: 0 | H13: 0 | I13: 0 | J13: 0 | K13: 0 | L13: 0 | M13: 0 | N13: 0 | O13: =B13+C13+D13+E13+F13+G13+H13+I13+J13+K13+L13+M13+N13 -> 0 | R13: =SUM(B13:N13) -> 0 | S13: =O13-R13 -> 0
A14: Receitas Brutas Total... | B14: =B12+B13 -> 0 | F14: =SUM(F12:F13) -> 0 | G14: =SUM(G12:G13) -> 0 | H14: =SUM(H12:H13) -> 0 | I14: =SUM(I12:I13) -> 0 | J14: =SUM(J12:J13) -> 0 | K14: =SUM(K12:K13) -> 0 | L14: =SUM(L12:L13) -> 0 | M14: =SUM(M12:M13) -> 0 | ... O14: =SUM(O12:O13) -> 0 | P14: 1 | R14: =SUM(B14:N14) -> 0 | S14: =O14-R14 -> 0
R15: =SUM(B15:N15) -> 0 | S15: =O15-R15 -> 0
A16: Custos | R16: =SUM(B16:N16) -> 0 | S16: =O16-R16 -> 0
A17: Alimentação - 320 | B17: -6030.15 | C17: 0 | D17: 0 | E17: 0 | F17: 0 | G17: 0 | H17: 0 | I17: 0 | J17: 0 | K17: 0 | L17: 0 | M17: 0 | N17: 0 | O17: =B17+C17+D17+E17+F17+G17+H17+I17+J17+K17+L17+M17+N17 -> -6030.15 | R17: =SUM(B17:N17) -> -6030.15 | S17: =O17-R17 -> 0
A18: Combustíveis - 322 | B18: 0 | C18: 0 | D18: 0 | E18: 0 | F18: 0 | G18: 0 | H18: 0 | I18: 0 | J18: 0 | K18: 0 | L18: 0 | M18: 0 | N18: 0 | O18: =B18+C18+D18+E18+F18+G18+H18+I18+J18+K18+L18+M18+N18 -> 0 | R18: =SUM(B18:N18) -> 0 | S18: =O18-R18 -> 0
A19: Despesa com Radio e Telefonia Celular | B19: 0 | C19: 0 | D19: 0 | E19: 0 | F19: 0 | G19: 0 | H19: 0 | I19: 0 | J19: 0 | K19: 0 | L19: 0 | M19: 0 | N19: 0 | O19: =B19+C19+D19+E19+F19+G19+H19+I19+J19+K19+L19+M19+N19 -> 0 | R19: =SUM(B19:N19) -> 0 | S19: =O19-R19 -> 0
A20: Equipamento de Segurança - EPIs - 360 | B20: 0 | C20: 0 | D20: 0 | E20: 0 | F20: 0 | G20: 0 | H20: 0 | I20: 0 | J20: 0 | K20: 0 | L20: 0 | M20: 0 | N20: 0 | O20: =B20+C20+D20+E20+F20+G20+H20+I20+J20+K20+L20+M20+N20 -> 0 | R20: =SUM(B20:N20) -> 0 | S20: =O20-R20 -> 0
A21: Ferias - 315 | B21: -3604.9 | C21: 0 | D21: 0 | E21: 0 | F21: 0 | G21: 0 | H21: 0 | I21: 0 | J21: 0 | K21: 0 | L21: 0 | M21: 0 | N21: 0 | O21: =B21+C21+D21+E21+F21+G21+H21+I21+J21+K21+L21+M21+N21 -> -3604.9 | R21: =SUM(B21:N21) -> -3604.9 | S21: =O21-R21 -> 0
A22: FGTS - 317 | B22: -2382.93 | C22: 0 | D22: 0 | E22: 0 | F22: 0 | G22: 0 | H22: 0 | I22: 0 | J22: 0 | K22: 0 | L22: 0 | M22: 0 | N22: 0 | O22: =B22+C22+D22+E22+F22+G22+H22+I22+J22+K22+L22+M22+N22 -> -2382.93 | R22: =SUM(B22:N22) -> -2382.93 | S22: =O22-R22 -> 0
A23: Horas Extras - 499 | B23: -4602.01 | C23: 0 | D23: 0 | E23: 0 | F23: 0 | G23: 0 | H23: 0 | I23: 0 | J23: 0 | K23: 0 | L23: 0 | M23: 0 | N23: 0 | O23: =B23+C23+D23+E23+F23+G23+H23+I23+J23+K23+L23+M23+N23 -> -4602.01 | R23: =SUM(B23:N23) -> -4602.01 | S23: =O23-R23 -> 0
A24: Indenizações e Aviso Prévio - 318 | B24: 0 | C24: 0 | D24: 0 | E24: 0 | F24: 0 | G24: 0 | H24: 0 | I24: 0 | J24: 0 | K24: 0 | L24: 0 | M24: 0 | N24: 0 | O24: =B24+C24+D24+E24+F24+G24+H24+I24+J24+K24+L24+M24+N24 -> 0 | R24: =SUM(B24:N24) -> 0 | S24: =O24-R24 -> 0
A25: Indenizações Trabalhistas Judiciais - 369 | B25: 0 | C25: 0 | D25: 0 | E25: 0 | F25: 0 | G25: 0 | H25: 0 | I25: 0 | J25: 0 | K25: 0 | L25: 0 | M25: 0 | N25: 0 | O25: =B25+C25+D25+E25+F25+G25+H25+I25+J25+K25+L25+M25+N25 -> 0 | R25: =SUM(B25:N25) -> 0 | S25: =O25-R25 -> 0
A26: INSS - 316 | B26: -2621.22 | C26: 0 | D26: 0 | E26: 0 | F26: 0 | G26: 0 | H26: 0 | I26: 0 | J26: 0 | K26: 0 | L26: 0 | M26: 0 | N26: 0 | O26: =B26+C26+D26+E26+F26+G26+H26+I26+J26+K26+L26+M26+N26 -> -2621.22 | R26: =SUM(B26:N26) -> -2621.22 | S26: =O26-R26 -> 0
A27: Locação de Andaimes - 328 | B27: 0 | C27: 0 | D27: 0 | E27: 0 | F27: 0 | G27: 0 | H27: 0 | I27: 0 | J27: 0 | K27: 0 | L27: 0 | M27: 0 | N27: 0 | O27: =B27+C27+D27+E27+F27+G27+H27+I27+J27+K27+L27+M27+N27 -> 0 | R27: =SUM(B27:N27) -> 0 | S27: =O27-R27 -> 0
A28: Locação de Máqs, Ferramentas e Equipamentos - | B28: 0 | C28: 0 | D28: 0 | E28: 0 | F28: 0 | G28: 0 | H28: 0 | I28: 0 | J28: 0 | K28: 0 | L28: 0 | M28: 0 | N28: 0 | O28: =B28+C28+D28+E28+F28+G28+H28+I28+J28+K28+L28+M28+N28 -> 0 | R28: =SUM(B28:N28) -> 0 | S28: =O28-R28 -> 0
... A42: Confraternização de Funcionários | B42: 0 | C42: 0 | D42: 0 | E42: 0 | F42: 0 | G42: 0 | H42: 0 | I42: 0 | J42: 0 | K42: 0 | L42: 0 | M42: 0 | N42: 0 | O42: =B42+C42+D42+E42+F42+G42+H42+I42+J42+K42+L42+M42+N42 -> 0 | R42: =SUM(B42:N42) -> 0 | S42: =O42-R42 -> 0
A43: Custos Total... | B43: =SUM(B17:B42) -> -59188.85 | C43: =SUM(C17:C42) -> 0 | D43: =SUM(D17:D42) -> 0 | E43: =SUM(E17:E42) -> 0 | F43: =SUM(F17:F42) -> 0 | G43: =SUM(G17:G42) -> 0 | H43: =SUM(H17:H42) -> 0 | I43: =SUM(I17:I42) -> 0 | ... O43: =SUM(O17:O42) -> -59188.85 | R43: =SUM(B43:N43) -> -59188.85 | S43: =O43-R43 -> 0
R44: =SUM(B44:N44) -> 0 | S44: =O44-R44 -> 0
A45: = Lucro/Prejuízo Bruto | B45: =B14+B43 -> -59188.85 | C45: =C14+C43 -> 0 | D45: =D14+D43 -> 0 | E45: =E14+E43 -> 0 | F45: =F14+F43 -> 0 | G45: =G14+G43 -> 0 | H45: =H14+H43 -> 0 | I45: =I14+I43 -> 0 | ... N45: =N14+N43 -> 0 | O45: =B45+C45+D45+E45+F45+G45+H45+I45+J45+K45+L45+M45+N45 -> -59188.85 | R45: =SUM(B45:N45) -> -59188.85 | S45: =O45-R45 -> 0
R46: =SUM(B46:N46) -> 0 | S46: =O46-R46 -> 0
A47: (-) Impostos s/ Serviços - (13,15% s/ Faturamento) | B47: =-B12*13.15% -> 0 | C47: =-C12*13.15% -> 0 | D47: =-D12*13.15% -> 0 | E47: =-E12*13.15% -> 0 | F47: =-F12*13.15% -> 0 | G47: =-G12*13.15% -> 0 | H47: =-H12*13.15% -> 0 | I47: =-I12*13.15% -> 0 | ... N47: =-N12*13.15% -> 0 | O47: =B47+C47+D47+E47+F47+G47+H47+I47+J47+K47+L47+M47+N47 -> 0 | R47: =SUM(B47:N47) -> 0 | S47: =O47-R47 -> 0
R48: =SUM(B48:N48) -> 0 | S48: =O48-R48 -> 0
A49: (-) IRPJ e CSLL - (1,22% s/faturamento) | B49: =-B12*1.22% -> 0 | C49: =-C12*1.22% -> 0 | D49: =-D12*1.22% -> 0 | E49: =-E12*1.22% -> 0 | F49: =-F12*1.22% -> 0 | G49: =-G12*1.22% -> 0 | H49: =-H12*1.22% -> 0 | I49: =-I12*1.22% -> 0 | ... N49: =-N12*1.22% -> 0 | O49: =B49+C49+D49+E49+F49+G49+H49+I49+J49+K49+L49+M49+N49 -> 0 | R49: =SUM(B49:N49) -> 0 | S49: =O49-R49 -> 0
R50: =SUM(B50:N50) -> 0 | S50: =O50-R50 -> 0
A51: Total Desp Administrativas/Técnico - ( 5,56% Taxa Adm. Prevista) | B51: =B43*5.56% -> -3290.9001 | C51: =C43*5.56% -> 0 | D51: =D43*5.56% -> 0 | E51: =E43*5.56% -> 0 | F51: =F43*5.56% -> 0 | G51: =G43*5.56% -> 0 | H51: =H43*5.56% -> 0 | I51: =I43*5.56% -> 0 | ... N51: =N43*5.56% -> 0 | O51: =B51+C51+D51+E51+F51+G51+H51+I51+J51+K51+L51+M51+N51 -> -3290.9001 | R51: =SUM(B51:N51) -> -3290.9001 | S51: =O51-R51 -> 0
R52: =SUM(B52:N52) -> 0 | S52: =O52-R52 -> 0
A53: Total Despesas Financeiras -( 0,01% s/ Custo de Obras-média) | B53: =B43*0.01% -> -5.918885 | C53: =C43*0.01% -> 0 | D53: =D43*0.01% -> 0 | E53: =E43*0.01% -> 0 | F53: =F43*0.01% -> 0 | G53: =G43*0.01% -> 0 | H53: =H43*0.01% -> 0 | I53: =I43*0.01% -> 0 | ... N53: =N43*0.01% -> 0 | O53: =B53+C53+D53+E53+F53+G53+H53+I53+J53+K53+L53+M53+N53 -> -5.918885 | R53: =SUM(B53:N53) -> -5.918885 | S53: =O53-R53 -> 0
R54: =SUM(B54:N54) -> 0 | S54: =O54-R54 -> 0
A55: LUCRO/PREJUIZO - LIQUIDO DA OBRA - 279 - | B55: =B45+B51+B53+B47+B49 -> -62485.669 | C55: =C45+C51+C53+C47+C49 -> 0 | D55: =D45+D51+D53+D47+D49 -> 0 | E55: =E45+E51+E53+E47+E49 -> 0 | F55: =F45+F51+F53+F47+F49 -> 0 | G55: =G45+G51+G53+G47+G49 -> 0 | H55: =H45+H51+H53+H47+H49 -> 0 | I55: =I45+I51+I53+I47+I49 -> 0 | ... N55: =N45+N51+N53+N47+N49 -> 0 | O55: =B55+C55+D55+E55+F55+G55+H55+I55+J55+K55+L55+M55+N55 -> -62485.669 | R55: =SUM(B55:N55) -> -62485.669 | S55: =O55-R55 -> 0
A57: NÚMERO DE FUNCIONÁRIOS - FINAL DO MÊS
P58: 45382
A59: Elaborado: INOV SOLUÇÃO EMPRESARIAL E CONTÁBIL LTDA
B60: =B14+B43+B47+B49+B51+B53 -> -62485.669 | C60: =C14+C43+C47+C49+C51+C53 -> 0 | D60: =D14+D43+D47+D49+D51+D53 -> 0 | E60: =E14+E43+E47+E49+E51+E53 -> 0 | F60: =F14+F43+F47+F49+F51+F53 -> 0 | G60: =G14+G43+G47+G49+G51+G53 -> 0 | H60: =H14+H43+H47+H49+H51+H53 -> 0 | I60: =I14+I43+I47+I49+I51+I53 -> 0 | ... O60: =O14+O43+O47+O49+O51+O53 -> -62485.669
B62: =B55-B60 -> 0 | C62: =C55-C60 -> 0 | D62: =D55-D60 -> 0 | E62: =E55-E60 -> 0 | F62: =F55-F60 -> 0 | G62: =G55-G60 -> 0 | H62: =H55-H60 -> 0 | I62: =I55-I60 -> 0 | ... O62: =O55-O60 -> 0

Sheet OBRA 280
A1: BELA NOVA CONSTRUTORA LTDA
A3: DEMONSTRAÇÃO DO RESULTADO APURADO
A5: OBRA 280 - MONDO - EXTO
A7: OBRA ENCERRADA
B10: Jan a Dez/2023 | C10: Jan a Dez/2024 | D10: Janeiro/2025 | E10: Fevereiro/2025 | F10: Março/2025 | G10: Abril/2025 | H10: Maio/2024 | I10: Junho/2024 | J10: Julho/2024 | K10: Agosto/2024 | L10: Setembro/2024 | M10: Outubro/2024 | N10: Novembro/2024 | O10: Dezembro/2024 | P10: Acumulado | Q10: % S/FAT
A11: Receitas Brutas
A12: Servicos prestados | B12: 0 | D12: 0 | E12: 0 | F12: 0 | G12: 0 | H12: 0 | I12: 0 | J12: 0 | K12: 0 | L12: 0 | M12: 0 | N12: 0 | O12: 0 | P12: =B12+C12+D12+E12+F12+G12+H12+I12+J12+K12+L12+M12+N12+O12 -> 0 | Q12: 1 | S12: =SUM(B12:O12) -> 0 | T12: =P12-S12 -> 0
A13: Locação de Equipamentos - 450 | B13: 0 | D13: 0 | E13: 0 | F13: 0 | G13: 0 | H13: 0 | I13: 0 | J13: 0 | K13: 0 | L13: 0 | M13: 0 | N13: 0 | O13: 0 | P13: =B13+C13+D13+E13+F13+G13+H13+I13+J13+K13+L13+M13+N13+O13 -> 0 | S13: =SUM(B13:O13) -> 0 | T13: =P13-S13 -> 0
A14: Receitas Brutas Total... | B14: =B12+B13 -> 0 | D14: =D12+D13 -> 0 | E14: =E12+E13 -> 0 | F14: =F12+F13 -> 0 | G14: =SUM(G12:G13) -> 0 | H14: =SUM(H12:H13) -> 0 | I14: =SUM(I12:I13) -> 0 | J14: =SUM(J12:J13) -> 0 | K14: =SUM(K12:K13) -> 0 | L14: =SUM(L12:L13) -> 0 | M14: =SUM(M12:M13) -> 0 | N14: =SUM(N12:N13) -> 0 | ... P14: =SUM(P12:P13) -> 0 | Q14: 1 | S14: =SUM(B14:O14) -> 0 | T14: =P14-S14 -> 0
S15: =SUM(B15:O15) -> 0
A16: Custos | S16: =SUM(B16:O16) -> 0
A17: Alimentação - 320 | B17: -51320.74 | C17: -10258.64 | D17: 0 | E17: 0 | F17: 0 | G17: 0 | H17: 0 | I17: 0 | J17: 0 | K17: 0 | L17: 0 | M17: 0 | N17: 0 | O17: 0 | P17: =B17+C17+D17+E17+F17+G17+H17+I17+J17+K17+L17+M17+N17+O17 -> -61579.38 | S17: =SUM(B17:O17) -> -61579.38 | T17: =S17-P17 -> 0
A18: Combustíveis - 322 | B18: 0 | C18: 0 | D18: 0 | E18: 0 | F18: 0 | G18: 0 | H18: 0 | I18: 0 | J18: 0 | K18: 0 | L18: 0 | M18: 0 | N18: 0 | O18: 0 | P18: =B18+C18+D18+E18+F18+G18+H18+I18+J18+K18+L18+M18+N18+O18 -> 0 | S18: =SUM(B18:O18) -> 0 | T18: =S18-P18 -> 0
A19: Despesa com Radio e Telefonia Celular | B19: 0 | C19: 0 | D19: 0 | E19: 0 | F19: 0 | G19: 0 | H19: 0 | I19: 0 | J19: 0 | K19: 0 | L19: 0 | M19: 0 | N19: 0 | O19: 0 | P19: =B19+C19+D19+E19+F19+G19+H19+I19+J19+K19+L19+M19+N19+O19 -> 0 | S19: =SUM(B19:O19) -> 0 | T19: =S19-P19 -> 0
A20: Equipamento de Segurança - EPIs - 360 | B20: -483.05 | C20: -119.07 | D20: 0 | E20: 0 | F20: 0 | G20: 0 | H20: 0 | I20: 0 | J20: 0 | K20: 0 | L20: 0 | M20: 0 | N20: 0 | O20: 0 | P20: =B20+C20+D20+E20+F20+G20+H20+I20+J20+K20+L20+M20+N20+O20 -> -602.12 | S20: =SUM(B20:O20) -> -602.12 | T20: =S20-P20 -> 0
A21: Ferias - 315 | B21: -41917.71 | C21: -8721.07 | D21: 0 | E21: 0 | F21: 0 | G21: 0 | H21: 0 | I21: 0 | J21: 0 | K21: 0 | L21: 0 | M21: 0 | N21: 0 | O21: 0 | P21: =B21+C21+D21+E21+F21+G21+H21+I21+J21+K21+L21+M21+N21+O21 -> -50638.78 | S21: =SUM(B21:O21) -> -50638.78 | T21: =S21-P21 -> 0
A22: FGTS - 317 | B22: -24582.81 | C22: -5549.9 | D22: 0 | E22: 0 | F22: 0 | G22: 0 | H22: 0 | I22: 0 | J22: 0 | K22: 0 | L22: 0 | M22: 0 | N22: 0 | O22: 0 | P22: =B22+C22+D22+E22+F22+G22+H22+I22+J22+K22+L22+M22+N22+O22 -> -30132.71 | S22: =SUM(B22:O22) -> -30132.71 | T22: =S22-P22 -> 0
A23: Horas Extras - 499 | B23: -18841.1 | C23: -5651.46 | D23: 0 | E23: 0 | F23: 0 | G23: 0 | H23: 0 | I23: 0 | J23: 0 | K23: 0 | L23: 0 | M23: 0 | N23: 0 | O23: 0 | P23: =B23+C23+D23+E23+F23+G23+H23+I23+J23+K23+L23+M23+N23+O23 -> -24492.56 | S23: =SUM(B23:O23) -> -24492.56 | T23: =S23-P23 -> 0
A24: Indenizações e Aviso Prévio - 318 | B24: 1674.46 | C24: 0 | D24: 0 | E24: 0 | F24: 0 | G24: 0 | H24: 0 | I24: 0 | J24: 0 | K24: 0 | L24: 0 | M24: 0 | N24: 0 | O24: 0 | P24: =B24+C24+D24+E24+F24+G24+H24+I24+J24+K24+L24+M24+N24+O24 -> 1674.46 | S24: =SUM(B24:O24) -> 1674.46 | T24: =S24-P24 -> 0
A25: Indenizações Trabalhistas Judiciais - 369 | B25: 0 | C25: -520 | D25: 0 | E25: 0 | F25: 0 | G25: 0 | H25: 0 | I25: 0 | J25: 0 | K25: 0 | L25: 0 | M25: 0 | N25: 0 | O25: 0 | P25: =B25+C25+D25+E25+F25+G25+H25+I25+J25+K25+L25+M25+N25+O25 -> -520 | S25: =SUM(B25:O25) -> -520 | T25: =S25-P25 -> 0
A26: INSS - 316 | B26: -28395.43 | C26: -6543.9 | D26: 0 | E26: 0 | F26: 0 | G26: 0 | H26: 0 | I26: 0 | J26: 0 | K26: 0 | L26: 0 | M26: 0 | N26: 0 | O26: 0 | P26: =B26+C26+D26+E26+F26+G26+H26+I26+J26+K26+L26+M26+N26+O26 -> -34939.33 | S26: =SUM(B26:O26) -> -34939.33 | T26: =S26-P26 -> 0
A27: Locação de Andaimes - 328 | B27: 0 | C27: 0 | D27: 0 | E27: 0 | F27: 0 | G27: 0 | H27: 0 | I27: 0 | J27: 0 | K27: 0 | L27: 0 | M27: 0 | N27: 0 | O27: 0 | P27: =B27+C27+D27+E27+F27+G27+H27+I27+J27+K27+L27+M27+N27+O27 -> 0 | S27: =SUM(B27:O27) -> 0 | T27: =S27-P27 -> 0
A28: Locação de Máqs, Ferramentas e Equipamentos - | B28: 0 | C28: -3385.66 | D28: 0 | E28: 0 | F28: 0 | G28: 0 | H28: 0 | I28: 0 | J28: 0 | K28: 0 | L28: 0 | M28: 0 | N28: 0 | O28: 0 | P28: =B28+C28+D28+E28+F28+G28+H28+I28+J28+K28+L28+M28+N28+O28 -> -3385.66 | S28: =SUM(B28:O28) -> -3385.66 | T28: =S28-P28 -> 0
... A42: Confraternização de Funcionários | B42: 0 | C42: 0 | D42: 0 | E42: 0 | F42: 0 | G42: 0 | H42: 0 | I42: 0 | J42: 0 | K42: 0 | L42: 0 | M42: 0 | N42: 0 | O42: 0 | P42: =B42+C42+D42+E42+F42+G42+H42+I42+J42+K42+L42+M42+N42+O42 -> 0 | S42: =SUM(B42:O42) -> 0 | T42: =S42-P42 -> 0
A43: Custos Total... | B43: =SUM(B17:B42) -> -657907.4 | C43: =SUM(C17:C42) -> -135686.38 | D43: =SUM(D17:D42) -> 0 | E43: =SUM(E17:E42) -> 0 | F43: =SUM(F17:F42) -> 0 | G43: =SUM(G17:G42) -> 0 | H43: =SUM(H17:H42) -> 0 | I43: =SUM(I17:I42) -> 0 | ... P43: =SUM(P17:P42) -> -793593.78 | S43: =SUM(B43:O43) -> -793593.78 | T43: =S43-P43 -> 0
S44: =SUM(B44:O44) -> 0 | T44: =S44-P44 -> 0
A45: = Lucro/Prejuízo Bruto | B45: =B14+B43 -> -657907.4 | C45: =C14+C43 -> -135686.38 | D45: =D14+D43 -> 0 | E45: =E14+E43 -> 0 | F45: =F14+F43 -> 0 | G45: =G14+G43 -> 0 | H45: =H14+H43 -> 0 | I45: =I14+I43 -> 0 | ... O45: =O14+O43 -> 0 | P45: =B45+C45+D45+E45+F45+G45+H45+I45+J45+K45+L45+M45+N45+O45 -> -793593.78 | S45: =SUM(B45:O45) -> -793593.78 | T45: =S45-P45 -> 0
S46: =SUM(B46:O46) -> 0 | T46: =S46-P46 -> 0
A47: (-) Impostos s/ Serviços - (13,15% s/ Faturamento) | B47: =-B12*13.15% -> 0 | C47: =-C12*13.15% -> 0 | D47: =-D12*13.15% -> 0 | E47: =-E12*13.15% -> 0 | F47: =-F12*13.15% -> 0 | G47: =-G12*13.15% -> 0 | H47: =-H12*13.15% -> 0 | I47: =-I12*13.15% -> 0 | ... O47: =-O12*13.15% -> 0 | P47: =B47+C47+D47+E47+F47+G47+H47+I47+J47+K47+L47+M47+N47+O47 -> 0 | S47: =SUM(B47:O47) -> 0 | T47: =S47-P47 -> 0
S48: =SUM(B48:O48) -> 0 | T48: =S48-P48 -> 0
A49: (-) IRPJ e CSLL - (1,22% s/faturamento) | B49: =-B12*1.22% -> 0 | C49: =-C12*1.22% -> 0 | D49: =-D12*1.22% -> 0 | E49: =-E12*1.22% -> 0 | F49: =-F12*1.22% -> 0 | G49: =-G12*1.22% -> 0 | H49: =-H12*1.22% -> 0 | I49: =-I12*1.22% -> 0 | ... O49: =-O12*1.22% -> 0 | P49: =B49+C49+D49+E49+F49+G49+H49+I49+J49+K49+L49+M49+N49+O49 -> 0 | S49: =SUM(B49:O49) -> 0 | T49: =S49-P49 -> 0
S50: =SUM(B50:O50) -> 0 | T50: =S50-P50 -> 0
A51: Total Desp Administrativas/Técnico - ( 5,56% Taxa Adm. Prevista) | B51: =B43*5.56% -> -36579.651 | C51: =C43*5.56% -> -7544.1627 | D51: =D43*5.56% -> 0 | E51: =E43*5.56% -> 0 | F51: =F43*5.56% -> 0 | G51: =G43*5.56% -> 0 | H51: =H43*5.56% -> 0 | I51: =I43*5.56% -> 0 | ... O51: =O43*5.56% -> 0 | P51: =B51+C51+D51+E51+F51+G51+H51+I51+J51+K51+L51+M51+N51+O51 -> -44123.814 | S51: =SUM(B51:O51) -> -44123.814 | T51: =S51-P51 -> 0
S52: =SUM(B52:O52) -> 0 | T52: =S52-P52 -> 0
A53: Total Despesas Financeiras -( 0,01% s/ Custo de Obras-média) | B53: =B43*0.01% -> -65.79074 | C53: =C43*0.01% -> -13.568638 | D53: =D43*0.01% -> 0 | E53: =E43*0.01% -> 0 | F53: =F43*0.01% -> 0 | G53: =G43*0.01% -> 0 | H53: =H43*0.01% -> 0 | I53: =I43*0.01% -> 0 | ... O53: =O43*0.01% -> 0 | P53: =B53+C53+D53+E53+F53+G53+H53+I53+J53+K53+L53+M53+N53+O53 -> -79.359378 | S53: =SUM(B53:O53) -> -79.359378 | T53: =S53-P53 -> 0
S54: =SUM(B54:O54) -> 0 | T54: =S54-P54 -> 0
A55: LUCRO/PREJUIZO - LIQUIDO DA OBRA - 280 - | B55: =B45+B51+B53+B47+B49 -> -694552.84 | C55: =C45+C51+C53+C47+C49 -> -143244.11 | D55: =D45+D51+D53+D47+D49 -> 0 | E55: =E45+E51+E53+E47+E49 -> 0 | F55: =F45+F51+F53+F47+F49 -> 0 | G55: =G45+G51+G53+G47+G49 -> 0 | H55: =H45+H51+H53+H47+H49 -> 0 | I55: =I45+I51+I53+I47+I49 -> 0 | ... O55: =O45+O51+O53+O47+O49 -> 0 | P55: =B55+C55+D55+E55+F55+G55+H55+I55+J55+K55+L55+M55+N55+O55 -> -837796.95 | S55: =SUM(B55:O55) -> -837796.95 | T55: =S55-P55 -> 0
A57: NÚMERO DE FUNCIONÁRIOS - FINAL DO MÊS
A59: Elaborado: INOV SOLUÇÃO EMPRESARIAL E CONTÁBIL LTDA | Q59: 45777
B61: =B14+B43+B47+B49+B51+B53 -> -694552.84 | C61: =C14+C43+C47+C49+C51+C53 -> -143244.11 | D61: =D14+D43+D47+D49+D51+D53 -> 0 | E61: =E14+E43+E47+E49+E51+E53 -> 0 | F61: =F14+F43+F47+F49+F51+F53 -> 0 | G61: =G14+G43+G47+G49+G51+G53 -> 0 | H61: =H14+H43+H47+H49+H51+H53 -> 0 | I61: =I14+I43+I47+I49+I51+I53 -> 0 | ... P61: =P14+P43+P47+P49+P51+P53 -> -837796.95
B63: =B61-B55 -> 0 | C63: =C61-C55 -> 0 | D63: =D61-D55 -> 0 | E63: =E61-E55 -> 0 | F63: =F61-F55 -> 0 | G63: =G61-G55 -> 0 | H63: =H61-H55 -> 0 | I63: =I61-I55 -> 0 | ... P63: =P61-P55 -> 0

Sheet OBRA 281
A1: DEMONSTRAÇÃO DO RESULTADO APURADO
A3: OBRA 281 - SPETTACOLO - PATRIANI
A5: OBRA ENCERRADA
B8: Mar a Dez/2023 | C8: Jan a Dez/2024 | D8: Janeiro/2025 | E8: Fevereiro/2025 | F8: Março/2024 | G8: Abril/2024 | H8: Maio/2024 | I8: Junho/2024 | J8: Julho/2024 | K8: Agosto/2024 | L8: Setembro/2024 | M8: Outubro/2024 | N8: Novembro/2024 | O8: Dezembro/2024 | P8: Acumulado | Q8: % S/FAT
A9: Receitas Brutas
A10: Servicos prestados | B10: 1765630 | C10: 777420.65 | D10: 0 | E10: 0 | F10: 0 | G10: 0 | H10: 0 | I10: 0 | J10: 0 | K10: 0 | L10: 0 | M10: 0 | N10: 0 | O10: 0 | P10: =B10+C10+D10+E10+F10+G10+H10+I10+J10+K10+L10+M10+N10+O10 -> 2543050.7 | Q10: 1 | S10: =SUM(B10:O10) -> 2543050.7 | T10: =P10-S10 -> 0
A11: Locação de Equipamentos - 450 | B11: 0 | D11: 0 | E11: 0 | F11: 0 | G11: 0 | H11: 0 | I11: 0 | J11: 0 | K11: 0 | L11: 0 | M11: 0 | N11: 0 | O11: 0 | P11: =B11+C11+D11+E11+F11+G11+H11+I11+J11+K11+L11+M11+N11+O11 -> 0 | S11: =SUM(B11:O11) -> 0 | T11: =P11-S11 -> 0
A12: Receitas Brutas Total... | B12: =SUM(B10:B11) -> 1765630 | C12: =SUM(C10:C11) -> 777420.65 | D12: =SUM(D10:D11) -> 0 | E12: =SUM(E10:E11) -> 0 | F12: =SUM(F10:F11) -> 0 | G12: =SUM(G10:G11) -> 0 | H12: =SUM(H10:H11) -> 0 | I12: =SUM(I10:I11) -> 0 | ... P12: =SUM(P10:P11) -> 2543050.7 | Q12: 1 | S12: =SUM(B12:O12) -> 2543050.7 | T12: =P12-S12 -> 0
S13: =SUM(B13:O13) -> 0
A14: Custos | S14: =SUM(B14:O14) -> 0
A15: Alimentação - 320 | B15: -118811.95 | C15: -75125.68 | D15: 0 | E15: 0 | F15: 0 | G15: 0 | H15: 0 | I15: 0 | J15: 0 | K15: 0 | L15: 0 | M15: 0 | N15: 0 | O15: 0 | P15: =B15+C15+D15+E15+F15+G15+H15+I15+J15+K15+L15+M15+N15+O15 -> -193937.63 | Q15: =-P15/$P$12 -> 0.076261803 | S15: =SUM(B15:O15) -> -193937.63 | T15: =P15-S15 -> 0
A16: Combustíveis - 322 | B16: 0 | C16: 0 | D16: 0 | E16: 0 | F16: 0 | G16: 0 | H16: 0 | I16: 0 | J16: 0 | K16: 0 | L16: 0 | M16: 0 | N16: 0 | O16: 0 | P16: =B16+C16+D16+E16+F16+G16+H16+I16+J16+K16+L16+M16+N16+O16 -> 0 | Q16: =-P16/$P$12 -> 0 | S16: =SUM(B16:O16) -> 0 | T16: =P16-S16 -> 0
A17: Despesa com Radio e Telefonia Celular | B17: -579.99 | C17: -240 | D17: 0 | E17: 0 | F17: 0 | G17: 0 | H17: 0 | I17: 0 | J17: 0 | K17: 0 | L17: 0 | M17: 0 | N17: 0 | O17: 0 | P17: =B17+C17+D17+E17+F17+G17+H17+I17+J17+K17+L17+M17+N17+O17 -> -819.99 | Q17: =-P17/$P$12 -> 0.00032244344 | S17: =SUM(B17:O17) -> -819.99 | T17: =P17-S17 -> 0
A18: Equipamento de Segurança - EPIs - 360 | B18: -7902.89 | C18: -2164.17 | D18: 0 | E18: 0 | F18: 0 | G18: 0 | H18: 0 | I18: 0 | J18: 0 | K18: 0 | L18: 0 | M18: 0 | N18: 0 | O18: 0 | P18: =B18+C18+D18+E18+F18+G18+H18+I18+J18+K18+L18+M18+N18+O18 -> -10067.06 | Q18: =-P18/$P$12 -> 0.0039586549 | S18: =SUM(B18:O18) -> -10067.06 | T18: =P18-S18 -> 0
A19: Ferias - 315 | B19: -71650.58 | C19: -29535.52 | D19: 0 | E19: 0 | F19: 0 | G19: 0 | H19: 0 | I19: 0 | J19: 0 | K19: 0 | L19: 0 | M19: 0 | N19: 0 | O19: 0 | P19: =B19+C19+D19+E19+F19+G19+H19+I19+J19+K19+L19+M19+N19+O19 -> -101186.1 | Q19: =-P19/$P$12 -> 0.039789258 | S19: =SUM(B19:O19) -> -101186.1 | T19: =P19-S19 -> 0
A20: FGTS - 317 | B20: -43076.14 | C20: -18215.31 | D20: 0 | E20: 0 | F20: 0 | G20: 0 | H20: 0 | I20: 0 | J20: 0 | K20: 0 | L20: 0 | M20: 0 | N20: 0 | O20: 0 | P20: =B20+C20+D20+E20+F20+G20+H20+I20+J20+K20+L20+M20+N20+O20 -> -61291.45 | Q20: =-P20/$P$12 -> 0.024101545 | S20: =SUM(B20:O20) -> -61291.45 | T20: =P20-S20 -> 0
A21: Horas Extras - 499 | B21: -19440.33 | C21: -7380.21 | D21: 0 | E21: 0 | F21: 0 | G21: 0 | H21: 0 | I21: 0 | J21: 0 | K21: 0 | L21: 0 | M21: 0 | N21: 0 | O21: 0 | P21: =B21+C21+D21+E21+F21+G21+H21+I21+J21+K21+L21+M21+N21+O21 -> -26820.54 | Q21: =-P21/$P$12 -> 0.010546601 | S21: =SUM(B21:O21) -> -26820.54 | T21: =P21-S21 -> 0
A22: Indenizações e Aviso Prévio - 318 | B22: -329.58 | C22: 0 | D22: 0 | E22: 0 | F22: 0 | G22: 0 | H22: 0 | I22: 0 | J22: 0 | K22: 0 | L22: 0 | M22: 0 | N22: 0 | O22: 0 | P22: =B22+C22+D22+E22+F22+G22+H22+I22+J22+K22+L22+M22+N22+O22 -> -329.58 | Q22: =-P22/$P$12 -> 0.00012960025 | S22: =SUM(B22:O22) -> -329.58 | T22: =P22-S22 -> 0
A23: Indenizações Trabalhistas Judiciais - 369 | B23: 0 | C23: -240 | D23: 0 | E23: 0 | F23: 0 | G23: 0 | H23: 0 | I23: 0 | J23: 0 | K23: 0 | L23: 0 | M23: 0 | N23: 0 | O23: 0 | P23: =B23+C23+D23+E23+F23+G23+H23+I23+J23+K23+L23+M23+N23+O23 -> -240 | Q23: =-P23/$P$12 -> 9.437484e-05 | S23: =SUM(B23:O23) -> -240 | T23: =P23-S23 -> 0
A24: INSS - 316 | B24: -48191.93 | C24: -20709.51 | D24: 0 | E24: 0 | F24: 0 | G24: 0 | H24: 0 | I24: 0 | J24: 0 | K24: 0 | L24: 0 | M24: 0 | N24: 0 | O24: 0 | P24: =B24+C24+D24+E24+F24+G24+H24+I24+J24+K24+L24+M24+N24+O24 -> -68901.44 | Q24: =-P24/$P$12 -> 0.02709401 | S24: =SUM(B24:O24) -> -68901.44 | T24: =P24-S24 -> 0
A25: Locação de Andaimes - 328 | B25: -7027.2 | C25: -3621.04 | D25: 0 | E25: 0 | F25: 0 | G25: 0 | H25: 0 | I25: 0 | J25: 0 | K25: 0 | L25: 0 | M25: 0 | N25: 0 | O25: 0 | P25: =B25+C25+D25+E25+F25+G25+H25+I25+J25+K25+L25+M25+N25+O25 -> -10648.24 | Q25: =-P25/$P$12 -> 0.0041871914 | S25: =SUM(B25:O25) -> -10648.24 | T25: =P25-S25 -> 0
A26: Locação de Máqs, Ferramentas e Equipamentos - | B26: -26174.3 | C26: -18135.49 | D26: 0 | E26: 0 | F26: 0 | G26: 0 | H26: 0 | I26: 0 | J26: 0 | K26: 0 | L26: 0 | M26: 0 | N26: 0 | O26: 0 | P26: =B26+C26+D26+E26+F26+G26+H26+I26+J26+K26+L26+M26+N26+O26 -> -44309.79 | Q26: =-P26/$P$12 -> 0.017423872 | S26: =SUM(B26:O26) -> -44309.79 | T26: =P26-S26 -> 0
... A38: 13º Salario - 314 | B38: -53972.69 | C38: -21548.37 | D38: 0 | E38: 0 | F38: 0 | G38: 0 | H38: 0 | I38: 0 | J38: 0 | K38: 0 | L38: 0 | M38: 0 | N38: 0 | O38: 0 | P38: =B38+C38+D38+E38+F38+G38+H38+I38+J38+K38+L38+M38+N38+O38 -> -75521.06 | Q38: =-P38/$P$12 -> 0.029697033 | S38: =SUM(B38:O38) -> -75521.06 | T38: =P38-S38 -> 0
A39: Cursos e treinamentos | B39: 300 | C39: 0 | D39: 0 | E39: 0 | F39: 0 | G39: 0 | H39: 0 | I39: 0 | J39: 0 | K39: 0 | L39: 0 | M39: 0 | N39: 0 | O39: 0 | P39: =B39+C39+D39+E39+F39+G39+H39+I39+J39+K39+L39+M39+N39+O39 -> 300 | Q39: =P39/$P$12 -> 0.00011796855 | S39: =SUM(B39:O39) -> 300 | T39: =P39-S39 -> 0
A40: Confraternização de Funcionários | B40: 0 | C40: 0 | D40: 0 | E40: 0 | F40: 0 | G40: 0 | H40: 0 | I40: 0 | J40: 0 | K40: 0 | L40: 0 | M40: 0 | N40: 0 | O40: 0 | P40: =B40+C40+D40+E40+F40+G40+H40+I40+J40+K40+L40+M40+N40+O40 -> 0 | Q40: =P40/$P$12 -> 0 | S40: =SUM(B40:O40) -> 0 | T40: =P40-S40 -> 0
A41: Custos Total... | B41: =SUM(B15:B40) -> -1374216.7 | C41: =SUM(C15:C40) -> -546391.95 | D41: =SUM(D15:D40) -> 0 | E41: =SUM(E15:E40) -> 0 | F41: =SUM(F15:F40) -> 0 | G41: =SUM(G15:G40) -> 0 | H41: =SUM(H15:H40) -> 0 | I41: =SUM(I15:I40) -> 0 | ... P41: =SUM(P15:P40) -> -1920608.6 | Q41: =-P41/$P$12 -> 0.75523805 | S41: =SUM(B41:O41) -> -1920608.6 | T41: =P41-S41 -> 0
S42: =SUM(B42:O42) -> 0 | T42: =P42-S42 -> 0
A43: = Lucro/Prejuízo Bruto | B43: =B12+B41 -> 391413.34 | C43: =C12+C41 -> 231028.7 | D43: =D12+D41 -> 0 | E43: =E12+E41 -> 0 | F43: =F12+F41 -> 0 | G43: =G12+G41 -> 0 | H43: =H12+H41 -> 0 | I43: =I12+I41 -> 0 | ... O43: =O12+O41 -> 0 | P43: =B43+C43+D43+E43+F43+G43+H43+I43+J43+K43+L43+M43+N43+O43 -> 622442.04 | Q43: =P43/$P$12 -> 0.24476195 | S43: =SUM(B43:O43) -> 622442.04 | T43: =P43-S43 -> 0
S44: =SUM(B44:O44) -> 0
A45: (-) Impostos s/ Serviços - (13,15% s/ Faturamento) | B45: =-B10*13.15% -> -232180.35 | C45: =-C10*13.15% -> -102230.82 | D45: =-D10*13.15% -> 0 | E45: =-E10*13.15% -> 0 | F45: =-F10*13.15% -> 0 | G45: =-G10*13.15% -> 0 | H45: =-H10*13.15% -> 0 | I45: =-I10*13.15% -> 0 | ... O45: =-O10*13.15% -> 0 | P45: =B45+C45+D45+E45+F45+G45+H45+I45+J45+K45+L45+M45+N45+O45 -> -334411.16 | Q45: =-P45/$P$12 -> 0.1315 | S45: =SUM(B45:O45) -> -334411.16 | T45: =P45-S45 -> 0
S46: =SUM(B46:O46) -> 0 | T46: =P46-S46 -> 0
A47: (-) IRPJ e CSLL - (1,22% s/faturamento) | B47: =-B10*1.22% -> -21540.686 | C47: =-C10*1.22% -> -9484.5319 | D47: =-D10*1.22% -> 0 | E47: =-E10*1.22% -> 0 | F47: =-F10*1.22% -> 0 | G47: =-G10*1.22% -> 0 | H47: =-H10*1.22% -> 0 | I47: =-I10*1.22% -> 0 | ... O47: =-O10*1.22% -> 0 | P47: =B47+C47+D47+E47+F47+G47+H47+I47+J47+K47+L47+M47+N47+O47 -> -31025.218 | Q47: =-P47/$P$12 -> 0.0122 | S47: =SUM(B47:O47) -> -31025.218 | T47: =P47-S47 -> 0
S48: =SUM(B48:O48) -> 0 | T48: =P48-S48 -> 0
A49: Total Desp Administrativas/Técnico - ( 5,56% Taxa Adm. Prevista) | B49: =B41*5.56% -> -76406.447 | C49: =C41*5.56% -> -30379.392 | D49: =D41*5.56% -> 0 | E49: =E41*5.56% -> 0 | F49: =F41*5.56% -> 0 | G49: =G41*5.56% -> 0 | H49: =H41*5.56% -> 0 | I49: =I41*5.56% -> 0 | ... O49: =O41*5.56% -> 0 | P49: =B49+C49+D49+E49+F49+G49+H49+I49+J49+K49+L49+M49+N49+O49 -> -106785.84 | Q49: =-P49/$P$12 -> 0.041991236 | S49: =SUM(B49:O49) -> -106785.84 | T49: =P49-S49 -> 0
S50: =SUM(B50:O50) -> 0 | T50: =P50-S50 -> 0
A51: Total Despesas Financeiras -( 0,01% s/ Custo de Obras-média) | B51: =B41*0.01% -> -137.42167 | C51: =C41*0.01% -> -54.639195 | D51: =D41*0.01% -> 0 | E51: =E41*0.01% -> 0 | F51: =F41*0.01% -> 0 | G51: =G41*0.01% -> 0 | H51: =H41*0.01% -> 0 | I51: =I41*0.01% -> 0 | ... O51: =O41*0.01% -> 0 | P51: =B51+C51+D51+E51+F51+G51+H51+I51+J51+K51+L51+M51+N51+O51 -> -192.06086 | Q51: =-P51/$P$12 -> 7.5523805e-05 | S51: =SUM(B51:O51) -> -192.06086 | T51: =P51-S51 -> 0
S52: =SUM(B52:O52) -> 0 | T52: =P52-S52 -> 0
A53: LUCRO/PREJUIZO - LIQUIDO DA OBRA - 281 - | B53: =B43+B49+B51+B45+B47 -> 61148.437 | C53: =C43+C49+C51+C45+C47 -> 88879.321 | D53: =D43+D49+D51+D45+D47 -> 0 | E53: =E43+E49+E51+E45+E47 -> 0 | F53: =F43+F49+F51+F45+F47 -> 0 | G53: =G43+G49+G51+G45+G47 -> 0 | H53: =H43+H49+H51+H45+H47 -> 0 | I53: =I43+I49+I51+I45+I47 -> 0 | ... O53: =O43+O49+O51+O45+O47 -> 0 | P53: =B53+C53+D53+E53+F53+G53+H53+I53+J53+K53+L53+M53+N53+O53 -> 150027.76 | Q53: =P53/$P$12 -> 0.05899519 | S53: =SUM(B53:O53) -> 150027.76 | T53: =P53-S53 -> 0
A55: NÚMERO DE FUNCIONÁRIOS - FINAL DO MÊS
A57: Elaborado: INOV SOLUÇÃO EMPRESARIAL E CONTÁBIL LTDA | Q57: 45688
B58: =B12+B41+B45+B47+B49+B51 -> 61148.437 | C58: =C12+C41+C45+C47+C49+C51 -> 88879.321 | D58: =D12+D41+D45+D47+D49+D51 -> 0 | E58: =E12+E41+E45+E47+E49+E51 -> 0 | F58: =F12+F41+F45+F47+F49+F51 -> 0 | G58: =G12+G41+G45+G47+G49+G51 -> 0 | H58: =H12+H41+H45+H47+H49+H51 -> 0 | I58: =I12+I41+I45+I47+I49+I51 -> 0 | ... P58: =P12+P41+P45+P47+P49+P51 -> 150027.76
B60: =B53-B58 -> 0 | C60: =C53-C58 -> 0 | D60: =D53-D58 -> 0 | E60: =E53-E58 -> 0 | F60: =F53-F58 -> 0 | G60: =G53-G58 -> 0 | H60: =H53-H58 -> 0 | I60: =I53-I58 -> 0 | ... P60: =P53-P58 -> 3.2014214e-10

Sheet OBRA 282
A1: DEMONSTRAÇÃO DO RESULTADO APURADO
A3: OBRA 282 - MORIAH - PATRIANI
A5: OBRA ENCERRADA
B7: Abril a Dez/2023 | C7: Jan a Dez/2024 | D7: Janeiro/2025 | E7: Fevereiro/2025 | F7: Março/2024 | G7: Abril/2024 | H7: Maio/2024 | I7: Junho/2024 | J7: Julho/2024 | K7: Agosto/2024 | L7: Setembro/2024 | M7: Outubro/2024 | N7: Novembro/2024 | O7: Dezembro/2024 | P7: Acumulado | Q7: % S/FAT
A8: Receitas Brutas
A9: Servicos prestados | B9: 937178.75 | C9: 1034579.1 | D9: 0 | E9: 0 | F9: 0 | G9: 0 | H9: 0 | I9: 0 | J9: 0 | K9: 0 | L9: 0 | M9: 0 | N9: 0 | O9: 0 | P9: =B9+C9+D9+E9+F9+G9+H9+I9+J9+K9+L9+M9+N9+O9 -> 1971757.9 | Q9: 1 | S9: =SUM(B9:O9) -> 1971757.9 | T9: =P9-S9 -> 0
A10: Locação de Equipamentos - 450 | B10: 0 | C10: 0 | D10: 0 | E10: 0 | F10: 0 | G10: 0 | H10: 0 | I10: 0 | J10: 0 | K10: 0 | L10: 0 | M10: 0 | N10: 0 | O10: 0 | P10: =B10+C10+D10+E10+F10+G10+H10+I10+J10+K10+L10+M10+N10+O10 -> 0 | S10: =SUM(B10:O10) -> 0 | T10: =P10-S10 -> 0
A11: Receitas Brutas Total... | B11: =SUM(B9:B10) -> 937178.75 | C11: =SUM(C9:C10) -> 1034579.1 | D11: =SUM(D9:D10) -> 0 | E11: =SUM(E9:E10) -> 0 | F11: =SUM(F9:F10) -> 0 | G11: =SUM(G9:G10) -> 0 | H11: =SUM(H9:H10) -> 0 | I11: =SUM(I9:I10) -> 0 | ... P11: =SUM(P9:P10) -> 1971757.9 | Q11: 1 | S11: =SUM(B11:O11) -> 1971757.9 | T11: =P11-S11 -> 0
S12: =SUM(B12:O12) -> 0
A13: Custos | S13: =SUM(B13:O13) -> 0
A14: Alimentação - 320 | B14: -55614.57 | C14: -76745.87 | D14: 0 | E14: 0 | F14: 0 | G14: 0 | H14: 0 | I14: 0 | J14: 0 | K14: 0 | L14: 0 | M14: 0 | N14: 0 | O14: 0 | P14: =B14+C14+D14+E14+F14+G14+H14+I14+J14+K14+L14+M14+N14+O14 -> -132360.44 | Q14: =-P14/$P$11 -> 0.06712814 | S14: =SUM(B14:O14) -> -132360.44 | T14: =P14-S14 -> 0
A15: Combustíveis - 322 | B15: 0 | C15: 0 | D15: 0 | E15: 0 | F15: 0 | G15: 0 | H15: 0 | I15: 0 | J15: 0 | K15: 0 | L15: 0 | M15: 0 | N15: 0 | O15: 0 | P15: =B15+C15+D15+E15+F15+G15+H15+I15+J15+K15+L15+M15+N15+O15 -> 0 | Q15: =-P15/$P$11 -> 0 | S15: =SUM(B15:O15) -> 0 | T15: =P15-S15 -> 0
A16: Despesa com Radio e Telefonia Celular | B16: -1708.5 | C16: -6408.72 | D16: 0 | E16: 0 | F16: 0 | G16: 0 | H16: 0 | I16: 0 | J16: 0 | K16: 0 | L16: 0 | M16: 0 | N16: 0 | O16: 0 | P16: =B16+C16+D16+E16+F16+G16+H16+I16+J16+K16+L16+M16+N16+O16 -> -8117.22 | Q16: =-P16/$P$11 -> 0.0041167428 | S16: =SUM(B16:O16) -> -8117.22 | T16: =P16-S16 -> 0
A17: Equipamento de Segurança - EPIs - 360 | B17: -3776.66 | C17: -3948.9 | D17: 0 | E17: 0 | F17: 0 | G17: 0 | H17: 0 | I17: 0 | J17: 0 | K17: 0 | L17: 0 | M17: 0 | N17: 0 | O17: 0 | P17: =B17+C17+D17+E17+F17+G17+H17+I17+J17+K17+L17+M17+N17+O17 -> -7725.56 | Q17: =-P17/$P$11 -> 0.0039181078 | S17: =SUM(B17:O17) -> -7725.56 | T17: =P17-S17 -> 0
A18: Ferias - 315 | B18: -30409.3 | C18: -33134.99 | D18: 0 | E18: 0 | F18: 0 | G18: 0 | H18: 0 | I18: 0 | J18: 0 | K18: 0 | L18: 0 | M18: 0 | N18: 0 | O18: 0 | P18: =B18+C18+D18+E18+F18+G18+H18+I18+J18+K18+L18+M18+N18+O18 -> -63544.29 | Q18: =-P18/$P$11 -> 0.032227228 | S18: =SUM(B18:O18) -> -63544.29 | T18: =P18-S18 -> 0
A19: FGTS - 317 | B19: -17939.38 | C19: -21241.24 | D19: 0 | E19: 0 | F19: 0 | G19: 0 | H19: 0 | I19: 0 | J19: 0 | K19: 0 | L19: 0 | M19: 0 | N19: 0 | O19: 0 | P19: =B19+C19+D19+E19+F19+G19+H19+I19+J19+K19+L19+M19+N19+O19 -> -39180.62 | Q19: =-P19/$P$11 -> 0.019870908 | S19: =SUM(B19:O19) -> -39180.62 | T19: =P19-S19 -> 0
A20: Horas Extras - 499 | B20: -10693.92 | C20: -19868.86 | D20: 0 | E20: 0 | F20: 0 | G20: 0 | H20: 0 | I20: 0 | J20: 0 | K20: 0 | L20: 0 | M20: 0 | N20: 0 | O20: 0 | P20: =B20+C20+D20+E20+F20+G20+H20+I20+J20+K20+L20+M20+N20+O20 -> -30562.78 | Q20: =-P20/$P$11 -> 0.01550027 | S20: =SUM(B20:O20) -> -30562.78 | T20: =P20-S20 -> 0
A21: Indenizações e Aviso Prévio - 318 | B21: 0 | C21: 0 | D21: 0 | E21: 0 | F21: 0 | G21: 0 | H21: 0 | I21: 0 | J21: 0 | K21: 0 | L21: 0 | M21: 0 | N21: 0 | O21: 0 | P21: =B21+C21+D21+E21+F21+G21+H21+I21+J21+K21+L21+M21+N21+O21 -> 0 | Q21: =-P21/$P$11 -> 0 | S21: =SUM(B21:O21) -> 0 | T21: =P21-S21 -> 0
A22: Indenizações Trabalhistas Judiciais - 369 | B22: 0 | C22: -300 | D22: 0 | E22: 0 | F22: 0 | G22: 0 | H22: 0 | I22: 0 | J22: 0 | K22: 0 | L22: 0 | M22: 0 | N22: 0 | O22: 0 | P22: =B22+C22+D22+E22+F22+G22+H22+I22+J22+K22+L22+M22+N22+O22 -> -300 | Q22: =-P22/$P$11 -> 0.0001521485 | S22: =SUM(B22:O22) -> -300 | T22: =P22-S22 -> 0
A23: INSS - 316 | B23: -20168.74 | C23: -24439.28 | D23: 0 | E23: 0 | F23: 0 | G23: 0 | H23: 0 | I23: 0 | J23: 0 | K23: 0 | L23: 0 | M23: 0 | N23: 0 | O23: 0 | P23: =B23+C23+D23+E23+F23+G23+H23+I23+J23+K23+L23+M23+N23+O23 -> -44608.02 | Q23: =-P23/$P$11 -> 0.022623477 | S23: =SUM(B23:O23) -> -44608.02 | T23: =P23-S23 -> 0
A24: Locação de Andaimes - 328 | B24: -3819.02 | C24: -8902.55 | D24: 0 | E24: 0 | F24: 0 | G24: 0 | H24: 0 | I24: 0 | J24: 0 | K24: 0 | L24: 0 | M24: 0 | N24: 0 | O24: 0 | P24: =B24+C24+D24+E24+F24+G24+H24+I24+J24+K24+L24+M24+N24+O24 -> -12721.57 | Q24: =-P24/$P$11 -> 0.0064518926 | S24: =SUM(B24:O24) -> -12721.57 | T24: =P24-S24 -> 0
A25: Locação de Máqs, Ferramentas e Equipamentos - | B25: -14360.53 | C25: -31743.42 | D25: 0 | E25: 0 | F25: 0 | G25: 0 | H25: 0 | I25: 0 | J25: 0 | K25: 0 | L25: 0 | M25: 0 | N25: 0 | O25: 0 | P25: =B25+C25+D25+E25+F25+G25+H25+I25+J25+K25+L25+M25+N25+O25 -> -46103.95 | Q25: =-P25/$P$11 -> 0.023382156 | S25: =SUM(B25:O25) -> -46103.95 | T25: =P25-S25 -> 0
... A37: 13º Salario - 314 | B37: -22530.85 | C37: -24030.49 | D37: 0 | E37: 0 | F37: 0 | G37: 0 | H37: 0 | I37: 0 | J37: 0 | K37: 0 | L37: 0 | M37: 0 | N37: 0 | O37: 0 | P37: =B37+C37+D37+E37+F37+G37+H37+I37+J37+K37+L37+M37+N37+O37 -> -46561.34 | Q37: =-P37/$P$11 -> 0.023614126 | S37: =SUM(B37:O37) -> -46561.34 | T37: =P37-S37 -> 0
A38: Cursos e treinamentos | B38: 100 | C38: 0 | D38: 0 | E38: 0 | F38: 0 | G38: 0 | H38: 0 | I38: 0 | J38: 0 | K38: 0 | L38: 0 | M38: 0 | N38: 0 | O38: 0 | P38: =B38+C38+D38+E38+F38+G38+H38+I38+J38+K38+L38+M38+N38+O38 -> 100 | Q38: =P38/$P$11 -> 5.0716166e-05 | S38: =SUM(B38:O38) -> 100 | T38: =P38-S38 -> 0
A39: Confraternização de Funcionários | B39: 0 | C39: 0 | D39: 0 | E39: 0 | F39: 0 | G39: 0 | H39: 0 | I39: 0 | J39: 0 | K39: 0 | L39: 0 | M39: 0 | N39: 0 | O39: 0 | P39: =B39+C39+D39+E39+F39+G39+H39+I39+J39+K39+L39+M39+N39+O39 -> 0 | Q39: =P39/$P$11 -> 0 | S39: =SUM(B39:O39) -> 0 | T39: =P39-S39 -> 0
A40: Custos Total... | B40: =SUM(B14:B39) -> -518922.91 | C40: =SUM(C14:C39) -> -648847.87 | D40: =SUM(D14:D39) -> 0 | E40: =SUM(E14:E39) -> 0 | F40: =SUM(F14:F39) -> 0 | G40: =SUM(G14:G39) -> 0 | H40: =SUM(H14:H39) -> 0 | I40: =SUM(I14:I39) -> 0 | ... P40: =SUM(P14:P39) -> -1167770.8 | Q40: =-P40/$P$11 -> 0.59224857 | S40: =SUM(B40:O40) -> -1167770.8 | T40: =P40-S40 -> 0
S41: =SUM(B41:O41) -> 0 | T41: =P41-S41 -> 0
A42: = Lucro/Prejuízo Bruto | B42: =B11+B40 -> 418255.84 | C42: =C11+C40 -> 385731.26 | D42: =D11+D40 -> 0 | E42: =E11+E40 -> 0 | F42: =F11+F40 -> 0 | G42: =G11+G40 -> 0 | H42: =H11+H40 -> 0 | I42: =I11+I40 -> 0 | ... O42: =O11+O40 -> 0 | P42: =B42+C42+D42+E42+F42+G42+H42+I42+J42+K42+L42+M42+N42+O42 -> 803987.1 | Q42: =P42/$P$11 -> 0.40775143 | S42: =SUM(B42:O42) -> 803987.1 | T42: =P42-S42 -> 0
S43: =SUM(B43:O43) -> 0 | T43: =P43-S43 -> 0
A44: (-) Impostos s/ Serviços - (13,15% s/ Faturamento) | B44: =-B9*13.15% -> -123239.01 | C44: =-C9*13.15% -> -136047.16 | D44: =-D9*13.15% -> 0 | E44: =-E9*13.15% -> 0 | F44: =-F9*13.15% -> 0 | G44: =-G9*13.15% -> 0 | H44: =-H9*13.15% -> 0 | I44: =-I9*13.15% -> 0 | ... O44: =-O9*13.15% -> 0 | P44: =B44+C44+D44+E44+F44+G44+H44+I44+J44+K44+L44+M44+N44+O44 -> -259286.16 | Q44: =-P44/$P$11 -> 0.1315 | S44: =SUM(B44:O44) -> -259286.16 | T44: =P44-S44 -> 0
S45: =SUM(B45:O45) -> 0 | T45: =P45-S45 -> 0
A46: (-) IRPJ e CSLL - (1,22% s/faturamento) | B46: =-B9*1.22% -> -11433.581 | C46: =-C9*1.22% -> -12621.865 | D46: =-D9*1.22% -> 0 | E46: =-E9*1.22% -> 0 | F46: =-F9*1.22% -> 0 | G46: =-G9*1.22% -> 0 | H46: =-H9*1.22% -> 0 | I46: =-I9*1.22% -> 0 | ... O46: =-O9*1.22% -> 0 | P46: =B46+C46+D46+E46+F46+G46+H46+I46+J46+K46+L46+M46+N46+O46 -> -24055.446 | Q46: =-P46/$P$11 -> 0.0122 | S46: =SUM(B46:O46) -> -24055.446 | T46: =P46-S46 -> 0
S47: =SUM(B47:O47) -> 0 | T47: =P47-S47 -> 0
A48: Total Desp Administrativas/Técnico - ( 5,56% Taxa Adm. Prevista) | B48: =B40*5.56% -> -28852.114 | C48: =C40*5.56% -> -36075.942 | D48: =D40*5.56% -> 0 | E48: =E40*5.56% -> 0 | F48: =F40*5.56% -> 0 | G48: =G40*5.56% -> 0 | H48: =H40*5.56% -> 0 | I48: =I40*5.56% -> 0 | ... O48: =O40*5.56% -> 0 | P48: =B48+C48+D48+E48+F48+G48+H48+I48+J48+K48+L48+M48+N48+O48 -> -64928.055 | Q48: =-P48/$P$11 -> 0.03292902 | S48: =SUM(B48:O48) -> -64928.055 | T48: =P48-S48 -> 0
S49: =SUM(B49:O49) -> 0 | T49: =P49-S49 -> 0
A50: Total Despesas Financeiras -( 0,01% s/ Custo de Obras-média) | B50: =B40*0.01% -> -51.892291 | C50: =C40*0.01% -> -64.884787 | D50: =D40*0.01% -> 0 | E50: =E40*0.01% -> 0 | F50: =F40*0.01% -> 0 | G50: =G40*0.01% -> 0 | H50: =H40*0.01% -> 0 | I50: =I40*0.01% -> 0 | ... O50: =O40*0.01% -> 0 | P50: =B50+C50+D50+E50+F50+G50+H50+I50+J50+K50+L50+M50+N50+O50 -> -116.77708 | Q50: =-P50/$P$11 -> 5.9224857e-05 | S50: =SUM(B50:O50) -> -116.77708 | T50: =P50-S50 -> 0
S51: =SUM(B51:O51) -> 0 | T51: =P51-S51 -> 0
A52: LUCRO/PREJUIZO - LIQUIDO DA OBRA - 282 - | B52: =B42+B48+B50+B44+B46 -> 254679.25 | C52: =C42+C48+C50+C44+C46 -> 200921.41 | D52: =D42+D48+D50+D44+D46 -> 0 | E52: =E42+E48+E50+E44+E46 -> 0 | F52: =F42+F48+F50+F44+F46 -> 0 | G52: =G42+G48+G50+G44+G46 -> 0 | H52: =H42+H48+H50+H44+H46 -> 0 | I52: =I42+I48+I50+I44+I46 -> 0 | ... O52: =O42+O48+O50+O44+O46 -> 0 | P52: =B52+C52+D52+E52+F52+G52+H52+I52+J52+K52+L52+M52+N52+O52 -> 455600.66 | Q52: =P52/$P$11 -> 0.23106319 | S52: =SUM(B52:O52) -> 455600.66 | T52: =P52-S52 -> 0
A54: NÚMERO DE FUNCIONÁRIOS - FINAL DO MÊS
A56: Elaborado: INOV SOLUÇÃO EMPRESARIAL E CONTÁBIL LTDA | Q56: 45688
B57: =B11+B40+B44+B46+B48+B50 -> 254679.25 | C57: =C11+C40+C44+C46+C48+C50 -> 200921.41 | D57: =D11+D40+D44+D46+D48+D50 -> 0 | E57: =E11+E40+E44+E46+E48+E50 -> 0 | F57: =F11+F40+F44+F46+F48+F50 -> 0 | G57: =G11+G40+G44+G46+G48+G50 -> 0 | H57: =H11+H40+H44+H46+H48+H50 -> 0 | I57: =I11+I40+I44+I46+I48+I50 -> 0 | ... P57: =P11+P40+P44+P46+P48+P50 -> 455600.66
B59: =B52-B57 -> 0 | C59: =C52-C57 -> 0 | D59: =D52-D57 -> 0 | E59: =E52-E57 -> 0 | F59: =F52-F57 -> 0 | G59: =G52-G57 -> 0 | H59: =H52-H57 -> 0 | I59: =I52-I57 -> 0 | ... P59: =P52-P57 -> 0

Sheet OBRA 283
A1: DEMONSTRAÇÃO DO RESULTADO APURADO
A3: OBRA 283 - EMERALD (BANDEIRANTES) - EZTEC
A5: OBRA ENCERRADA
B7: Julho a Dez/2023 | C7: Jan a Dez/2024 | D7: Jan a Dez/2025 | E7: Janeiro/2026 | F7: Fevereiro/2026 | G7: Março/2026 | H7: Abril/2026 | I7: Maio/2026 | J7: Junho/2026 | K7: Julho/2026 | L7: Agosto/2026 | M7: Setembro/2026 | N7: Outubro/2026 | O7: Novembro/2026 | P7: Dezembro/2026 | Q7: Acumulado | R7: % S/FAT | V7: 2025
A8: Receitas Brutas
A9: Servicos prestados | B9: 552589.4 | C9: 0 | D9: 0 | E9: 0 | F9: 0 | G9: 0 | H9: 0 | I9: 0 | J9: 0 | K9: 0 | L9: 0 | M9: 0 | N9: 0 | O9: 0 | P9: 0 | Q9: =SUM(B9:P9) -> 552589.4 | R9: 1 | T9: =SUM(B9:P9) -> 552589.4 | U9: =Q9-T9 -> 0 | V9: =Q9-B9-C9 -> 0
A10: Locação de Equipamentos - 450 | B10: 0 | C10: 0 | D10: 0 | E10: 0 | F10: 0 | G10: 0 | H10: 0 | I10: 0 | J10: 0 | K10: 0 | L10: 0 | M10: 0 | N10: 0 | O10: 0 | P10: 0 | Q10: =SUM(B10:P10) -> 0 | T10: =SUM(B10:P10) -> 0 | U10: =Q10-T10 -> 0 | V10: =Q10-B10-C10 -> 0
A11: Receitas Brutas Total... | B11: =SUM(B9:B10) -> 552589.4 | C11: =SUM(C9:C10) -> 0 | D11: =SUM(D9:D10) -> 0 | E11: =SUM(E9:E10) -> 0 | F11: =SUM(F9:F10) -> 0 | G11: =SUM(G9:G10) -> 0 | H11: =SUM(H9:H10) -> 0 | I11: =SUM(I9:I10) -> 0 | ... Q11: =SUM(Q9:Q10) -> 552589.4 | R11: 1 | T11: =SUM(B11:P11) -> 552589.4 | U11: =Q11-T11 -> 0 | V11: =Q11-B11-C11 -> 0
T12: =SUM(B12:P12) -> 0 | V12: =Q12-B12-C12 -> 0
A13: Custos | T13: =SUM(B13:P13) -> 0 | V13: =Q13-B13-C13 -> 0
A14: Alimentação - 320 | B14: -25268.87 | C14: -71280.52 | D14: -21726.86 | E14: 0 | F14: 0 | G14: 0 | H14: 0 | I14: 0 | J14: 0 | K14: 0 | L14: 0 | M14: 0 | N14: 0 | O14: 0 | P14: 0 | Q14: =SUM(B14:P14) -> -118276.25 | R14: =-Q14/$Q$11 -> 0.21404003 | T14: =SUM(B14:P14) -> -118276.25 | U14: =Q14-T14 -> 0 | V14: =Q14-B14-C14 -> -21726.86
A15: Combustíveis - 322 | B15: 0 | C15: 0 | D15: 0 | E15: 0 | F15: 0 | G15: 0 | H15: 0 | I15: 0 | J15: 0 | K15: 0 | L15: 0 | M15: 0 | N15: 0 | O15: 0 | P15: 0 | Q15: =SUM(B15:P15) -> 0 | R15: =-Q15/$Q$11 -> 0 | T15: =SUM(B15:P15) -> 0 | U15: =Q15-T15 -> 0 | V15: =Q15-B15-C15 -> 0
A16: Despesa com Radio e Telefonia Celular | B16: 0 | C16: 0 | D16: 0 | E16: 0 | F16: 0 | G16: 0 | H16: 0 | I16: 0 | J16: 0 | K16: 0 | L16: 0 | M16: 0 | N16: 0 | O16: 0 | P16: 0 | Q16: =SUM(B16:P16) -> 0 | R16: =-Q16/$Q$11 -> 0 | T16: =SUM(B16:P16) -> 0 | U16: =Q16-T16 -> 0 | V16: =Q16-B16-C16 -> 0
A17: Equipamento de Segurança - EPIs - 360 | B17: -1474.06 | C17: -632.44 | D17: 0 | E17: 0 | F17: 0 | G17: 0 | H17: 0 | I17: 0 | J17: 0 | K17: 0 | L17: 0 | M17: 0 | N17: 0 | O17: 0 | P17: 0 | Q17: =SUM(B17:P17) -> -2106.5 | R17: =-Q17/$Q$11 -> 0.0038120529 | T17: =SUM(B17:P17) -> -2106.5 | U17: =Q17-T17 -> 0 | V17: =Q17-B17-C17 -> 0
A18: Ferias - 315 | B18: -20520.77 | C18: -55066.43 | D18: -13635.72 | E18: 0 | F18: 0 | G18: 0 | H18: 0 | I18: 0 | J18: 0 | K18: 0 | L18: 0 | M18: 0 | N18: 0 | O18: 0 | P18: 0 | Q18: =SUM(B18:P18) -> -89222.92 | R18: =-Q18/$Q$11 -> 0.16146332 | T18: =SUM(B18:P18) -> -89222.92 | U18: =Q18-T18 -> 0 | V18: =Q18-B18-C18 -> -13635.72
A19: FGTS - 317 | B19: -12181.97 | C19: -39106.24 | D19: -9845.78 | E19: 0 | F19: 0 | G19: 0 | H19: 0 | I19: 0 | J19: 0 | K19: 0 | L19: 0 | M19: 0 | N19: 0 | O19: 0 | P19: 0 | Q19: =SUM(B19:P19) -> -61133.99 | R19: =-Q19/$Q$11 -> 0.11063185 | T19: =SUM(B19:P19) -> -61133.99 | U19: =Q19-T19 -> 0 | V19: =Q19-B19-C19 -> -9845.78
A20: Horas Extras - 499 | B20: -18695.85 | C20: -38384.87 | D20: -4033.32 | E20: 0 | F20: 0 | G20: 0 | H20: 0 | I20: 0 | J20: 0 | K20: 0 | L20: 0 | M20: 0 | N20: 0 | O20: 0 | P20: 0 | Q20: =SUM(B20:P20) -> -61114.04 | R20: =-Q20/$Q$11 -> 0.11059575 | T20: =SUM(B20:P20) -> -61114.04 | U20: =Q20-T20 -> 0 | V20: =Q20-B20-C20 -> -4033.32
A21: Indenizações e Aviso Prévio - 318 | B21: -329.5 | C21: -2206.44 | D21: 0 | E21: 0 | F21: 0 | G21: 0 | H21: 0 | I21: 0 | J21: 0 | K21: 0 | L21: 0 | M21: 0 | N21: 0 | O21: 0 | P21: 0 | Q21: =SUM(B21:P21) -> -2535.94 | R21: =-Q21/$Q$11 -> 0.0045891941 | T21: =SUM(B21:P21) -> -2535.94 | U21: =Q21-T21 -> 0 | V21: =Q21-B21-C21 -> 0
A22: Indenizações Trabalhistas Judiciais - 369 | B22: 0 | C22: -2200 | D22: 0 | E22: 0 | F22: 0 | G22: 0 | H22: 0 | I22: 0 | J22: 0 | K22: 0 | L22: 0 | M22: 0 | N22: 0 | O22: 0 | P22: 0 | Q22: =SUM(B22:P22) -> -2200 | R22: =-Q22/$Q$11 -> 0.0039812562 | T22: =SUM(B22:P22) -> -2200 | U22: =Q22-T22 -> 0 | V22: =Q22-B22-C22 -> 0
A23: INSS - 316 | B23: -14623.16 | C23: -41635.24 | D23: -17012.38 | E23: 0 | F23: 0 | G23: 0 | H23: 0 | I23: 0 | J23: 0 | K23: 0 | L23: 0 | M23: 0 | N23: 0 | O23: 0 | P23: 0 | Q23: =SUM(B23:P23) -> -73270.78 | R23: =-Q23/$Q$11 -> 0.13259534 | T23: =SUM(B23:P23) -> -73270.78 | U23: =Q23-T23 -> 0 | V23: =Q23-B23-C23 -> -17012.38
A24: Locação de Andaimes - 328 | B24: 0 | C24: 0 | D24: 0 | E24: 0 | F24: 0 | G24: 0 | H24: 0 | I24: 0 | J24: 0 | K24: 0 | L24: 0 | M24: 0 | N24: 0 | O24: 0 | P24: 0 | Q24: =SUM(B24:P24) -> 0 | R24: =-Q24/$Q$11 -> 0 | T24: =SUM(B24:P24) -> 0 | U24: =Q24-T24 -> 0 | V24: =Q24-B24-C24 -> 0
A25: Locação de Máqs, Ferramentas e Equipamentos - | B25: 0 | C25: 0 | D25: 0 | E25: 0 | F25: 0 | G25: 0 | H25: 0 | I25: 0 | J25: 0 | K25: 0 | L25: 0 | M25: 0 | N25: 0 | O25: 0 | P25: 0 | Q25: =SUM(B25:P25) -> 0 | R25: =-Q25/$Q$11 -> 0 | T25: =SUM(B25:P25) -> 0 | U25: =Q25-T25 -> 0 | V25: =Q25-B25-C25 -> 0
... A39: Confraternização de Funcionários | B39: 0 | C39: 0 | D39: 0 | E39: 0 | F39: 0 | G39: 0 | H39: 0 | I39: 0 | J39: 0 | K39: 0 | L39: 0 | M39: 0 | N39: 0 | O39: 0 | P39: 0 | Q39: =SUM(B39:P39) -> 0 | R39: =-Q39/$Q$11 -> 0 | T39: =SUM(B39:P39) -> 0 | U39: =Q39-T39 -> 0 | V39: =Q39-B39-C39 -> 0
A40: Custos Total... | B40: =SUM(B14:B39) -> -283837.07 | C40: =SUM(C14:C39) -> -885568.17 | D40: =SUM(D14:D39) -> -256882.91 | E40: =SUM(E14:E39) -> 0 | F40: =SUM(F14:F39) -> 0 | G40: =SUM(G14:G39) -> 0 | H40: =SUM(H14:H39) -> 0 | I40: =SUM(I14:I39) -> 0 | ... Q40: =SUM(Q14:Q39) -> -1426288.1 | R40: =-Q40/$Q$11 -> 2.5810994 | T40: =SUM(B40:P40) -> -1426288.1 | U40: =Q40-T40 -> 0 | V40: =Q40-B40-C40 -> -256882.91
T41: =SUM(B41:P41) -> 0 | U41: =Q41-T41 -> 0 | V41: =Q41-B41-C41 -> 0
A42: = Lucro/Prejuízo Bruto | B42: =B11+B40 -> 268752.33 | C42: =C11+C40 -> -885568.17 | D42: =D11+D40 -> -256882.91 | E42: =E11+E40 -> 0 | F42: =F11+F40 -> 0 | G42: =G11+G40 -> 0 | H42: =H11+H40 -> 0 | I42: =I11+I40 -> 0 | ... P42: =P11+P40 -> 0 | Q42: =SUM(B42:P42) -> -873698.75 | R42: =-Q42/$Q$11 -> 1.5810994 | T42: =SUM(B42:P42) -> -873698.75 | U42: =Q42-T42 -> 0 | V42: =Q42-B42-C42 -> -256882.91
T43: =SUM(B43:P43) -> 0 | U43: =Q43-T43 -> 0 | V43: =Q43-B43-C43 -> 0
A44: (-) Impostos s/ Serviços - (13,15% s/ Faturamento) | B44: =-B9*13.15% -> -72665.506 | C44: =-C9*13.15% -> 0 | D44: =-D9*13.15% -> 0 | E44: =-E9*13.15% -> 0 | F44: =-F9*13.15% -> 0 | G44: =-G9*13.15% -> 0 | H44: =-H9*13.15% -> 0 | I44: =-I9*13.15% -> 0 | ... P44: =-P9*13.15% -> 0 | Q44: =SUM(B44:P44) -> -72665.506 | R44: =-Q44/$Q$11 -> 0.1315 | T44: =SUM(B44:P44) -> -72665.506 | U44: =Q44-T44 -> 0 | V44: =Q44-B44-C44 -> 0
T45: =SUM(B45:P45) -> 0 | U45: =Q45-T45 -> 0 | V45: =Q45-B45-C45 -> 0
A46: (-) IRPJ e CSLL - (1,22% s/faturamento) | B46: =-B9*1.22% -> -6741.5907 | C46: =-C9*1.22% -> 0 | D46: =-D9*1.22% -> 0 | E46: =-E9*1.22% -> 0 | F46: =-F9*1.22% -> 0 | G46: =-G9*1.22% -> 0 | H46: =-H9*1.22% -> 0 | I46: =-I9*1.22% -> 0 | ... P46: =-P9*1.22% -> 0 | Q46: =SUM(B46:P46) -> -6741.5907 | R46: =-Q46/$Q$11 -> 0.0122 | T46: =SUM(B46:P46) -> -6741.5907 | U46: =Q46-T46 -> 0 | V46: =Q46-B46-C46 -> 0
T47: =SUM(B47:P47) -> 0 | U47: =Q47-T47 -> 0 | V47: =Q47-B47-C47 -> 0
A48: Total Desp Administrativas/Técnico - ( 5,56% Taxa Adm. Prevista) | B48: =B40*5.56% -> -15781.341 | C48: =C40*5.56% -> -49237.59 | D48: =D40*5.56% -> -14282.69 | E48: =E40*5.56% -> 0 | F48: =F40*5.56% -> 0 | G48: =G40*5.56% -> 0 | H48: =H40*5.56% -> 0 | I48: =I40*5.56% -> 0 | ... P48: =P40*5.56% -> 0 | Q48: =SUM(B48:P48) -> -79301.621 | R48: =-Q48/$Q$11 -> 0.14350912 | T48: =SUM(B48:P48) -> -79301.621 | U48: =Q48-T48 -> 0 | V48: =Q48-B48-C48 -> -14282.69
T49: =SUM(B49:P49) -> 0 | U49: =Q49-T49 -> 0 | V49: =Q49-B49-C49 -> 0
A50: Total Despesas Financeiras -( 0,01% s/ Custo de Obras-média) | B50: =B40*0.01% -> -28.383707 | C50: =C40*0.01% -> -88.556817 | D50: =D40*0.01% -> -25.688291 | E50: =E40*0.01% -> 0 | F50: =F40*0.01% -> 0 | G50: =G40*0.01% -> 0 | H50: =H40*0.01% -> 0 | I50: =I40*0.01% -> 0 | ... P50: =P40*0.01% -> 0 | Q50: =SUM(B50:P50) -> -142.62882 | R50: =-Q50/$Q$11 -> 0.00025810994 | T50: =SUM(B50:P50) -> -142.62882 | U50: =Q50-T50 -> 0 | V50: =Q50-B50-C50 -> -25.688291
T51: =SUM(B51:P51) -> 0 | U51: =Q51-T51 -> 0 | V51: =Q51-B51-C51 -> 0
A52: LUCRO/PREJUIZO - LIQUIDO DA OBRA - 283 - | B52: =B42+B48+B50+B44+B46 -> 173535.51 | C52: =C42+C48+C50+C44+C46 -> -934894.32 | D52: =D42+D48+D50+D44+D46 -> -271191.29 | E52: =E42+E48+E50+E44+E46 -> 0 | F52: =F42+F48+F50+F44+F46 -> 0 | G52: =G42+G48+G50+G44+G46 -> 0 | H52: =H42+H48+H50+H44+H46 -> 0 | I52: =I42+I48+I50+I44+I46 -> 0 | ... P52: =P42+P48+P50+P44+P46 -> 0 | Q52: =SUM(B52:P52) -> -1032550.1 | R52: =-Q52/$Q$11 -> 1.8685666 | T52: =SUM(B52:P52) -> -1032550.1 | U52: =Q52-T52 -> 0 | V52: =Q52-B52-C52 -> -271191.29
A54: NÚMERO DE FUNCIONÁRIOS - FINAL DO MÊS
A56: Elaborado: INOV SOLUÇÃO EMPRESARIAL E CONTÁBIL LTDA
A57: Verificar as obras 283 e 290 sempre juntas | R57: 46053
B58: =B11+B40+B44+B46+B48+B50 -> 173535.51 | C58: =C11+C40+C44+C46+C48+C50 -> -934894.32 | E58: =E11+E40+E44+E46+E48+E50 -> 0 | F58: =F11+F40+F44+F46+F48+F50 -> 0 | G58: =G11+G40+G44+G46+G48+G50 -> 0 | H58: =H11+H40+H44+H46+H48+H50 -> 0 | I58: =I11+I40+I44+I46+I48+I50 -> 0 | J58: =J11+J40+J44+J46+J48+J50 -> 0 | K58: =K11+K40+K44+K46+K48+K50 -> 0 | L58: =L11+L40+L44+L46+L48+L50 -> 0 | ... Q58: =Q11+Q40+Q44+Q46+Q48+Q50 -> -1032550.1
B60: =B52-B58 -> 0 | C60: =C52-C58 -> 0 | E60: =E52-E58 -> 0 | F60: =F52-F58 -> 0 | G60: =G52-G58 -> 0 | H60: =H52-H58 -> 0 | I60: =I52-I58 -> 0 | J60: =J52-J58 -> 0 | K60: =K52-K58 -> 0 | L60: =L52-L58 -> 0 | ... Q60: =Q52-Q58 -> 0

Sheet OBRA 284
A1: DEMONSTRAÇÃO DO RESULTADO APURADO
A3: OBRA 284 - MIRAI CAMPESTRE - PATRIANI
A5: OBRA ENCERRADA
B7: Maio a Dez/2023 | C7: Jan a Dez/2024 | D7: Janeiro/2025 | E7: Fevereiro/2025 | F7: Março/2024 | G7: Abril/2024 | H7: Maio/2024 | I7: Junho/2024 | J7: Julho/2024 | K7: Agosto/2024 | L7: Setembro/2024 | M7: Outubro/2024 | N7: Novembro/2024 | O7: Dezembro/2024 | P7: Acumulado | Q7: % S/FAT
A8: Receitas Brutas
A9: Servicos prestados | B9: 995814.24 | C9: 2050602.5 | D9: 106332.57 | E9: 0 | F9: 0 | G9: 0 | H9: 0 | I9: 0 | J9: 0 | K9: 0 | L9: 0 | M9: 0 | N9: 0 | O9: 0 | P9: =B9+C9+D9+E9+F9+G9+H9+I9+J9+K9+L9+M9+N9+O9 -> 3152749.3 | Q9: 1 | S9: =SUM(B9:O9) -> 3152749.3 | T9: =P9-S9 -> 0
A10: Locação de Equipamentos - 450 | B10: 0 | C10: 0 | D10: 0 | E10: 0 | F10: 0 | G10: 0 | H10: 0 | I10: 0 | J10: 0 | K10: 0 | L10: 0 | M10: 0 | N10: 0 | O10: 0 | P10: =B10+C10+D10+E10+F10+G10+H10+I10+J10+K10+L10+M10+N10+O10 -> 0 | S10: =SUM(B10:O10) -> 0 | T10: =P10-S10 -> 0
A11: Receitas Brutas Total... | B11: =SUM(B9:B10) -> 995814.24 | C11: =SUM(C9:C10) -> 2050602.5 | D11: =SUM(D9:D10) -> 106332.57 | E11: =SUM(E9:E10) -> 0 | F11: =SUM(F9:F10) -> 0 | G11: =SUM(G9:G10) -> 0 | H11: =SUM(H9:H10) -> 0 | I11: =SUM(I9:I10) -> 0 | ... P11: =SUM(P9:P10) -> 3152749.3 | Q11: 1 | S11: =SUM(B11:O11) -> 3152749.3 | T11: =P11-S11 -> 0
S12: =SUM(B12:O12) -> 0
A13: Custos | S13: =SUM(B13:O13) -> 0
A14: Alimentação - 320 | B14: -71167.12 | C14: -131608.76 | D14: 0 | E14: 0 | F14: 0 | G14: 0 | H14: 0 | I14: 0 | J14: 0 | K14: 0 | L14: 0 | M14: 0 | N14: 0 | O14: 0 | P14: =B14+C14+D14+E14+F14+G14+H14+I14+J14+K14+L14+M14+N14+O14 -> -202775.88 | Q14: =-P14/$P$11 -> 0.064317159 | S14: =SUM(B14:O14) -> -202775.88 | T14: =P14-S14 -> 0
A15: Combustíveis - 322 | B15: 0 | C15: 0 | D15: 0 | E15: 0 | F15: 0 | G15: 0 | H15: 0 | I15: 0 | J15: 0 | K15: 0 | L15: 0 | M15: 0 | N15: 0 | O15: 0 | P15: =B15+C15+D15+E15+F15+G15+H15+I15+J15+K15+L15+M15+N15+O15 -> 0 | Q15: =-P15/$P$11 -> 0 | S15: =SUM(B15:O15) -> 0 | T15: =P15-S15 -> 0
A16: Despesa com Radio e Telefonia Celular | B16: -988.5 | C16: -4871.64 | D16: 0 | E16: 0 | F16: 0 | G16: 0 | H16: 0 | I16: 0 | J16: 0 | K16: 0 | L16: 0 | M16: 0 | N16: 0 | O16: 0 | P16: =B16+C16+D16+E16+F16+G16+H16+I16+J16+K16+L16+M16+N16+O16 -> -5860.14 | Q16: =-P16/$P$11 -> 0.0018587396 | S16: =SUM(B16:O16) -> -5860.14 | T16: =P16-S16 -> 0
A17: Equipamento de Segurança - EPIs - 360 | B17: -4719.78 | C17: -7515.34 | D17: 0 | E17: 0 | F17: 0 | G17: 0 | H17: 0 | I17: 0 | J17: 0 | K17: 0 | L17: 0 | M17: 0 | N17: 0 | O17: 0 | P17: =B17+C17+D17+E17+F17+G17+H17+I17+J17+K17+L17+M17+N17+O17 -> -12235.12 | Q17: =-P17/$P$11 -> 0.0038807779 | S17: =SUM(B17:O17) -> -12235.12 | T17: =P17-S17 -> 0
A18: Ferias - 315 | B18: -37970.45 | C18: -65236.89 | D18: 0 | E18: 0 | F18: 0 | G18: 0 | H18: 0 | I18: 0 | J18: 0 | K18: 0 | L18: 0 | M18: 0 | N18: 0 | O18: 0 | P18: =B18+C18+D18+E18+F18+G18+H18+I18+J18+K18+L18+M18+N18+O18 -> -103207.34 | Q18: =-P18/$P$11 -> 0.032735663 | S18: =SUM(B18:O18) -> -103207.34 | T18: =P18-S18 -> 0
A19: FGTS - 317 | B19: -22890.74 | C19: -47960.35 | D19: 0 | E19: 0 | F19: 0 | G19: 0 | H19: 0 | I19: 0 | J19: 0 | K19: 0 | L19: 0 | M19: 0 | N19: 0 | O19: 0 | P19: =B19+C19+D19+E19+F19+G19+H19+I19+J19+K19+L19+M19+N19+O19 -> -70851.09 | Q19: =-P19/$P$11 -> 0.022472795 | S19: =SUM(B19:O19) -> -70851.09 | T19: =P19-S19 -> 0
A20: Horas Extras - 499 | B20: -13960.57 | C20: -37492.23 | D20: 0 | E20: 0 | F20: 0 | G20: 0 | H20: 0 | I20: 0 | J20: 0 | K20: 0 | L20: 0 | M20: 0 | N20: 0 | O20: 0 | P20: =B20+C20+D20+E20+F20+G20+H20+I20+J20+K20+L20+M20+N20+O20 -> -51452.8 | Q20: =-P20/$P$11 -> 0.016319978 | S20: =SUM(B20:O20) -> -51452.8 | T20: =P20-S20 -> 0
A21: Indenizações e Aviso Prévio - 318 | B21: 0 | C21: -449.09 | D21: 0 | E21: 0 | F21: 0 | G21: 0 | H21: 0 | I21: 0 | J21: 0 | K21: 0 | L21: 0 | M21: 0 | N21: 0 | O21: 0 | P21: =B21+C21+D21+E21+F21+G21+H21+I21+J21+K21+L21+M21+N21+O21 -> -449.09 | Q21: =-P21/$P$11 -> 0.00014244393 | S21: =SUM(B21:O21) -> -449.09 | T21: =P21-S21 -> 0
A22: Indenizações Trabalhistas Judiciais - 369 | B22: 0 | C22: -2026.4 | D22: 0 | E22: 0 | F22: 0 | G22: 0 | H22: 0 | I22: 0 | J22: 0 | K22: 0 | L22: 0 | M22: 0 | N22: 0 | O22: 0 | P22: =B22+C22+D22+E22+F22+G22+H22+I22+J22+K22+L22+M22+N22+O22 -> -2026.4 | Q22: =-P22/$P$11 -> 0.0006427406 | S22: =SUM(B22:O22) -> -2026.4 | T22: =P22-S22 -> 0
A23: INSS - 316 | B23: -26033.53 | C23: -48822.32 | D23: 0 | E23: 0 | F23: 0 | G23: 0 | H23: 0 | I23: 0 | J23: 0 | K23: 0 | L23: 0 | M23: 0 | N23: 0 | O23: 0 | P23: =B23+C23+D23+E23+F23+G23+H23+I23+J23+K23+L23+M23+N23+O23 -> -74855.85 | Q23: =-P23/$P$11 -> 0.023743039 | S23: =SUM(B23:O23) -> -74855.85 | T23: =P23-S23 -> 0
A24: Locação de Andaimes - 328 | B24: 0 | C24: 0 | D24: 0 | E24: 0 | F24: 0 | G24: 0 | H24: 0 | I24: 0 | J24: 0 | K24: 0 | L24: 0 | M24: 0 | N24: 0 | O24: 0 | P24: =B24+C24+D24+E24+F24+G24+H24+I24+J24+K24+L24+M24+N24+O24 -> 0 | Q24: =-P24/$P$11 -> 0 | S24: =SUM(B24:O24) -> 0 | T24: =P24-S24 -> 0
A25: Locação de Máqs, Ferramentas e Equipamentos - | B25: -17152.48 | C25: -42330.06 | D25: 0 | E25: 0 | F25: 0 | G25: 0 | H25: 0 | I25: 0 | J25: 0 | K25: 0 | L25: 0 | M25: 0 | N25: 0 | O25: 0 | P25: =B25+C25+D25+E25+F25+G25+H25+I25+J25+K25+L25+M25+N25+O25 -> -59482.54 | Q25: =-P25/$P$11 -> 0.018866879 | S25: =SUM(B25:O25) -> -59482.54 | T25: =P25-S25 -> 0
... A39: Confraternização de Funcionários | B39: 0 | C39: 0 | D39: 0 | E39: 0 | F39: 0 | G39: 0 | H39: 0 | I39: 0 | J39: 0 | K39: 0 | L39: 0 | M39: 0 | N39: 0 | O39: 0 | P39: =B39+C39+D39+E39+F39+G39+H39+I39+J39+K39+L39+M39+N39+O39 -> 0 | Q39: =-P39/$P$11 -> 0 | S39: =SUM(B39:O39) -> 0 | T39: =P39-S39 -> 0
A40: Custos Total... | B40: =SUM(B14:B39) -> -678750.08 | C40: =SUM(C14:C39) -> -1243451.6 | D40: =SUM(D14:D39) -> 0 | E40: =SUM(E14:E39) -> 0 | F40: =SUM(F14:F39) -> 0 | G40: =SUM(G14:G39) -> 0 | H40: =SUM(H14:H39) -> 0 | I40: =SUM(I14:I39) -> 0 | ... P40: =SUM(P14:P39) -> -1922201.7 | Q40: =-P40/$P$11 -> 0.60969061 | S40: =SUM(B40:O40) -> -1922201.7 | T40: =P40-S40 -> 0
S41: =SUM(B41:O41) -> 0 | T41: =P41-S41 -> 0
A42: = Lucro/Prejuízo Bruto | B42: =B11+B40 -> 317064.16 | C42: =C11+C40 -> 807150.94 | D42: =D11+D40 -> 106332.57 | E42: =E11+E40 -> 0 | F42: =F11+F40 -> 0 | G42: =G11+G40 -> 0 | H42: =H11+H40 -> 0 | I42: =I11+I40 -> 0 | ... O42: =O11+O40 -> 0 | P42: =B42+C42+D42+E42+F42+G42+H42+I42+J42+K42+L42+M42+N42+O42 -> 1230547.7 | Q42: =P42/$P$11 -> 0.39030939 | S42: =SUM(B42:O42) -> 1230547.7 | T42: =P42-S42 -> 0
S43: =SUM(B43:O43) -> 0 | T43: =P43-S43 -> 0
A44: (-) Impostos s/ Serviços - (13,15% s/ Faturamento) | B44: =-B9*13.15% -> -130949.57 | C44: =-C9*13.15% -> -269654.23 | D44: =-D9*13.15% -> -13982.733 | E44: =-E9*13.15% -> 0 | F44: =-F9*13.15% -> 0 | G44: =-G9*13.15% -> 0 | H44: =-H9*13.15% -> 0 | I44: =-I9*13.15% -> 0 | ... O44: =-O9*13.15% -> 0 | P44: =B44+C44+D44+E44+F44+G44+H44+I44+J44+K44+L44+M44+N44+O44 -> -414586.54 | Q44: =-P44/$P$11 -> 0.1315 | S44: =SUM(B44:O44) -> -414586.54 | T44: =P44-S44 -> 0
S45: =SUM(B45:O45) -> 0 | T45: =P45-S45 -> 0
A46: (-) IRPJ e CSLL - (1,22% s/faturamento) | B46: =-B9*1.22% -> -12148.934 | C46: =-C9*1.22% -> -25017.351 | D46: =-D9*1.22% -> -1297.2574 | E46: =-E9*1.22% -> 0 | F46: =-F9*1.22% -> 0 | G46: =-G9*1.22% -> 0 | H46: =-H9*1.22% -> 0 | I46: =-I9*1.22% -> 0 | ... O46: =-O9*1.22% -> 0 | P46: =B46+C46+D46+E46+F46+G46+H46+I46+J46+K46+L46+M46+N46+O46 -> -38463.542 | Q46: =-P46/$P$11 -> 0.0122 | S46: =SUM(B46:O46) -> -38463.542 | T46: =P46-S46 -> 0
S47: =SUM(B47:O47) -> 0 | T47: =P47-S47 -> 0
